Workbook
Name AA: #REF!
Name AA: #REF!
Name AA: #REF!
Name aaa: #REF!
Name bu: #REF!
Name bu: #REF!
Name bu: #REF!
Name cenarios: #REF!
Name CSM: #REF!
Name CSM: #REF!
Name CSM: #REF!
Name CUSTOS3: #REF!
Name CUSTOS3: #REF!
Name CUSTOS3: #REF!
Name DATA_QI: #REF!
Name DATA_QI: #REF!
Name DATA_QI: #REF!
Name fe: #REF!
Name fe: #REF!
Name fe: #REF!
Name fgts: #REF!
Name fgts: #REF!
Name fgts: #REF!
Name fgts2: #REF!
Name fgts2: #REF!
Name fgts2: #REF!
Name Início_do_projeto: #REF!
Name Início_do_projeto: #REF!
Name Início_do_projeto: #REF!
Name MAC: #REF!
Name MAC: #REF!
Name MAC: #REF!
Name oo: #REF!
Name oo: #REF!
Name oo: #REF!
Name PIPELINE: #REF!
Name PIPELINE: #REF!
Name PIPELINE: #REF!
Name PIPELINE2: #REF!
Name PIPELINE2: #REF!
Name PIPELINE2: #REF!
Name possibilidades: #REF!
Name PROBABILIDADE: #REF!
Name PROBABILIDADE: #REF!
Name PROBABILIDADE: #REF!
Name PROBABILIDADE2: #REF!
Name PROBABILIDADE2: #REF!
Name PROBABILIDADE2: #REF!
Name Semana_de_exibição: #REF!
Name Semana_de_exibição: #REF!
Name Semana_de_exibição: #REF!
Name TP_FLUXO: #REF!
Name TP_FLUXO: #REF!
Name TP_FLUXO: #REF!
Name TP_FLUXO2: #REF!
Name TP_FLUXO2: #REF!
Name TP_FLUXO2: #REF!
Name XX: #REF!
Name XX: #REF!
Name XX: #REF!

Sheet Sumário

Sheet Estrutura_Mínima_BEP
B1: Data de atualização: | H1: 45903
B2: Documentos originais utilizados para atualização: | H2: 202508_Maclinea_Reorganization_Analysis_Provisório_3_v2
A4: 9 | F4: =F105 -> -1362955 | H4: =H105 -> 83819.757 | K4: =K105 -> -122417.79
F5: Custo estrutura (sem faturamento) | H5: Peças/Service + Máquinas Selecionadas | I5: % RL | K5: Somente Peças/Service | L5: % RL | N5: Origem
A7: 0.075 | C7: Receita Bruta | F7: =SUM(F8:F11) -> 0 | H7: =SUM(H8:H11) -> 2171500 | I7: =H7/H$19 -> 1.2355489 | K7: =SUM(K8:K11) -> 850000 | L7: =K7/K$19 -> 1.2804194 | N7: Premissas_Receita!A1
D8: Service | H8: =SUMIFS(Premissas_Receita!I:I,Premissas_Receita!A:A,Estrutura_Mínima_BEP!D8) -> 150000 | K8: =H8 -> 150000
D9: Peças | H9: =SUMIFS(Premissas_Receita!I:I,Premissas_Receita!A:A,Estrutura_Mínima_BEP!D9) -> 700000 | K9: =H9 -> 700000
D10: Máquinas Pequenas | H10: =SUMIFS(Premissas_Receita!I:I,Premissas_Receita!A:A,Estrutura_Mínima_BEP!D10) -> 365833.33
D11: Máquinas Grandes | H11: =SUMIFS(Premissas_Receita!I:I,Premissas_Receita!A:A,Estrutura_Mínima_BEP!D11) -> 955666.67
C13: Impostos Indiretos | F13: =SUM(F14:F17) -> 0 | H13: =SUM(H14:H17) -> 413981.6 | I13: =H13/H$19 -> 0.23554894 | K13: =SUM(K14:K17) -> 186155 | L13: =K13/K$19 -> 0.28041938 | N13: Premissas_Receita!A1
D14: Service | H14: =SUMIFS(Premissas_Receita!I:I,Premissas_Receita!A:A,Estrutura_Mínima_BEP!D14)*VLOOKUP(Estrutura_Mínima_BEP!D14,Premissas_Receita!A:J,10,0) -> 21375 | I14: =H14/H8 -> 0.1425 | K14: =H14 -> 21375 | L14: =K14/K8 -> 0.1425
D15: Peças | H15: =SUMIFS(Premissas_Receita!I:I,Premissas_Receita!A:A,Estrutura_Mínima_BEP!D15)*VLOOKUP(Estrutura_Mínima_BEP!D15,Premissas_Receita!A:J,10,0) -> 164780 | I15: =H15/H9 -> 0.2354 | K15: =H15 -> 164780 | L15: =K15/K9 -> 0.2354
A16: =F16/F6 -> #DIV/0! | D16: Máquinas Pequenas | H16: =SUMIFS(Premissas_Receita!I:I,Premissas_Receita!A:A,Estrutura_Mínima_BEP!D16)*VLOOKUP(Estrutura_Mínima_BEP!D16,Premissas_Receita!A:J,10,0) -> 63069.667 | I16: =H16/H10 -> 0.1724 | L16: =K16/K10 -> #DIV/0!
A17: =F17/F7 -> #DIV/0! | D17: Máquinas Grandes | H17: =SUMIFS(Premissas_Receita!I:I,Premissas_Receita!A:A,Estrutura_Mínima_BEP!D17)*VLOOKUP(Estrutura_Mínima_BEP!D17,Premissas_Receita!A:J,10,0) -> 164756.93 | I17: =H17/H11 -> 0.1724 | L17: =K17/K11 -> #DIV/0!
C19: Receita Líquida | F19: =SUM(F20:F23) -> 0 | H19: =SUM(H20:H23) -> 1757518.4 | I19: =H19/H$19 -> 1 | K19: =SUM(K20:K23) -> 663845 | L19: =K19/K$19 -> 1
D20: Service | H20: =H8-H14 -> 128625 | I20: =H20/$K$8 -> 0.8575 | K20: =H20 -> 128625 | L20: =K20/$K$8 -> 0.8575
D21: Peças | H21: =H9-H15 -> 535220 | I21: =H21/$K$9 -> 0.7646 | K21: =H21 -> 535220 | L21: =K21/$K$9 -> 0.7646
A22: =F22/F12 -> #DIV/0! | D22: Máquinas Pequenas | H22: =H10-H16 -> 302763.67 | I22: =H22/$K$19 -> 0.45607584 | L22: =K22/$K$19 -> 0
A23: =F23/F13 -> #DIV/0! | D23: Máquinas Grandes | H23: =H11-H17 -> 790909.73 | I23: =H23/$K$19 -> 1.1914072 | L23: =K23/$K$19 -> 0
C25: Comissão | F25: =SUM(F26:F29) -> 0 | H25: =SUM(H26:H29) -> 60658.275 | I25: =H25/H$19 -> 0.034513593 | K25: =SUM(K26:K29) -> 5974.605 | L25: =K25/K$19 -> 0.009 | N25: Premissas_Receita!A1
D26: Service | H26: =SUMIFS(Premissas_Receita!M:M,Premissas_Receita!A:A,Estrutura_Mínima_BEP!D26) -> 1157.625 | I26: =H26/$H20 -> 0.009 | K26: =H26 -> 1157.625 | L26: =K26/$H20 -> 0.009
D27: Peças | H27: =SUMIFS(Premissas_Receita!M:M,Premissas_Receita!A:A,Estrutura_Mínima_BEP!D27) -> 4816.98 | I27: =H27/$H21 -> 0.009 | K27: =H27 -> 4816.98 | L27: =K27/$H21 -> 0.009
A28: =F28/F19 -> #DIV/0! | D28: Máquinas Pequenas | H28: =SUMIFS(Premissas_Receita!M:M,Premissas_Receita!A:A,Estrutura_Mínima_BEP!D28) -> 15138.183 | I28: =H28/$H22 -> 0.05 | L28: =K28/$H22 -> 0
A29: =F29/F20 -> #DIV/0! | D29: Máquinas Grandes | H29: =SUMIFS(Premissas_Receita!M:M,Premissas_Receita!A:A,Estrutura_Mínima_BEP!D29) -> 39545.487 | I29: =H29/$H23 -> 0.05 | L29: =K29/$H23 -> 0
C31: Material | F31: =SUM(F32:F35) -> 0 | H31: =SUM(H32:H35) -> 897206.96 | I31: =H31/H$19 -> 0.51049648 | K31: =SUM(K32:K35) -> 328686 | L31: =K31/K$19 -> 0.49512461 | N31: Premissas_Receita!A1
D32: Service | H32: =SUMIFS(Premissas_Receita!O:O,Premissas_Receita!A:A,Estrutura_Mínima_BEP!D32) -> 0 | I32: =H32/$H20 -> 0 | K32: =H32 -> 0 | L32: =K32/$H20 -> 0
D33: Peças | H33: =SUMIFS(Premissas_Receita!O:O,Premissas_Receita!A:A,Estrutura_Mínima_BEP!D33) -> 328686 | I33: =H33/$H21 -> 0.61411382 | K33: =H33 -> 328686 | L33: =K33/$H21 -> 0.61411382
A34: =F34/F25 -> #DIV/0! | D34: Máquinas Pequenas | H34: =SUMIFS(Premissas_Receita!O:O,Premissas_Receita!A:A,Estrutura_Mínima_BEP!D34) -> 171918.06 | I34: =H34/$H22 -> 0.56782924 | L34: =K34/$H22 -> 0
A35: =F35/F26 -> #DIV/0! | D35: Máquinas Grandes | H35: =SUMIFS(Premissas_Receita!O:O,Premissas_Receita!A:A,Estrutura_Mínima_BEP!D35) -> 396602.9 | I35: =H35/$H23 -> 0.50145154 | L35: =K35/$H23 -> 0
C37: 1a Margem | H37: =SUM(H38:H41) -> 799653.16 | I37: =H37/H$19 -> 0.45498992 | K37: =SUM(K38:K41) -> 329184.4 | L37: =K37/K$19 -> 0.49587539
D38: Service | H38: =H20-H26-H32 -> 127467.38 | I38: =H38/H20 -> 0.991 | K38: =K20-K26-K32 -> 127467.38 | L38: =K38/K20 -> 0.991
D39: Peças | H39: =H21-H27-H33 -> 201717.02 | I39: =H39/H21 -> 0.37688618 | K39: =K21-K27-K33 -> 201717.02 | L39: =K39/K21 -> 0.37688618
A40: =F40/F31 -> #DIV/0! | D40: Máquinas Pequenas | H40: =H22-H28-H34 -> 115707.42 | I40: =H40/H22 -> 0.38217076 | L40: =K40/K22 -> #DIV/0!
A41: =F41/F32 -> #DIV/0! | D41: Máquinas Grandes | H41: =H23-H29-H35 -> 354761.35 | I41: =H41/H23 -> 0.44854846 | L41: =K41/K23 -> #DIV/0!
C43: Custo Fixo | F43: =F44+F56+F70+F80+F90 -> 1362955 | H43: =H44+H56+H70+H80+H90 -> 715833.41 | I43: =H43/H$19 -> 0.40729782 | K43: =K44+K56+K70+K80+K90 -> 451602.19 | L43: =K43/K$19 -> 0.68028258
D44: Custo de Pessoal | F44: =SUM(F45:F54) -> 1022332.3 | H44: =SUM(H45:H54) -> 458211.92 | I44: =H44/H$19 -> 0.26071529 | K44: =SUM(K45:K54) -> 301399.04 | L44: =K44/K$19 -> 0.4540202 | N44: Análise_Rescisões_Estrutura!A1
E45: ADM | F45: 255459.91 | H45: =SUMIFS(Análise_Rescisões_Estrutura!I:I,Análise_Rescisões_Estrutura!E:E,Estrutura_Mínima_BEP!E45,Análise_Rescisões_Estrutura!G:G,FALSE) -> 93830.735 | K45: =SUMIFS(Análise_Rescisões_Estrutura!I:I,Análise_Rescisões_Estrutura!E:E,Estrutura_Mínima_BEP!E45,Análise_Rescisões_Estrutura!H:H,FALSE) -> 93830.735
E46: ADM Produção | F46: 102758.41 | H46: =SUMIFS(Análise_Rescisões_Estrutura!I:I,Análise_Rescisões_Estrutura!E:E,Estrutura_Mínima_BEP!E46,Análise_Rescisões_Estrutura!G:G,FALSE) -> 36189.867 | K46: =SUMIFS(Análise_Rescisões_Estrutura!I:I,Análise_Rescisões_Estrutura!E:E,Estrutura_Mínima_BEP!E46,Análise_Rescisões_Estrutura!H:H,FALSE) -> 36189.867
E47: Almoxarifado | F47: 22791.386 | H47: =SUMIFS(Análise_Rescisões_Estrutura!I:I,Análise_Rescisões_Estrutura!E:E,Estrutura_Mínima_BEP!E47,Análise_Rescisões_Estrutura!G:G,FALSE) -> 5278.2793 | K47: =SUMIFS(Análise_Rescisões_Estrutura!I:I,Análise_Rescisões_Estrutura!E:E,Estrutura_Mínima_BEP!E47,Análise_Rescisões_Estrutura!H:H,FALSE) -> 5278.2793
E48: Assist.Tecnica | F48: 179000.89 | H48: =SUMIFS(Análise_Rescisões_Estrutura!I:I,Análise_Rescisões_Estrutura!E:E,Estrutura_Mínima_BEP!E48,Análise_Rescisões_Estrutura!G:G,FALSE) -> 98530.343 | K48: =SUMIFS(Análise_Rescisões_Estrutura!I:I,Análise_Rescisões_Estrutura!E:E,Estrutura_Mínima_BEP!E48,Análise_Rescisões_Estrutura!H:H,FALSE) -> 69499.807
E49: Contr.Qualid. | F49: 8925.0904 | H49: =SUMIFS(Análise_Rescisões_Estrutura!I:I,Análise_Rescisões_Estrutura!E:E,Estrutura_Mínima_BEP!E49,Análise_Rescisões_Estrutura!G:G,FALSE) -> 8925.0904 | K49: =SUMIFS(Análise_Rescisões_Estrutura!I:I,Análise_Rescisões_Estrutura!E:E,Estrutura_Mínima_BEP!E49,Análise_Rescisões_Estrutura!H:H,FALSE) -> 0
E50: Custos | F50: 14766.08 | H50: =SUMIFS(Análise_Rescisões_Estrutura!I:I,Análise_Rescisões_Estrutura!E:E,Estrutura_Mínima_BEP!E50,Análise_Rescisões_Estrutura!G:G,FALSE) -> 14766.08 | K50: =SUMIFS(Análise_Rescisões_Estrutura!I:I,Análise_Rescisões_Estrutura!E:E,Estrutura_Mínima_BEP!E50,Análise_Rescisões_Estrutura!H:H,FALSE) -> 14766.08
E51: Engenharia | F51: 157204.69 | H51: =SUMIFS(Análise_Rescisões_Estrutura!I:I,Análise_Rescisões_Estrutura!E:E,Estrutura_Mínima_BEP!E51,Análise_Rescisões_Estrutura!G:G,FALSE) -> 66499.931 | K51: =SUMIFS(Análise_Rescisões_Estrutura!I:I,Análise_Rescisões_Estrutura!E:E,Estrutura_Mínima_BEP!E51,Análise_Rescisões_Estrutura!H:H,FALSE) -> 23824.701
E52: Montagem | F52: 78913.7 | H52: =SUMIFS(Análise_Rescisões_Estrutura!I:I,Análise_Rescisões_Estrutura!E:E,Estrutura_Mínima_BEP!E52,Análise_Rescisões_Estrutura!G:G,FALSE) -> 55487.054 | K52: =SUMIFS(Análise_Rescisões_Estrutura!I:I,Análise_Rescisões_Estrutura!E:E,Estrutura_Mínima_BEP!E52,Análise_Rescisões_Estrutura!H:H,FALSE) -> 17922.157
E53: PPCP_Compras | F53: 45670.031 | H53: =SUMIFS(Análise_Rescisões_Estrutura!I:I,Análise_Rescisões_Estrutura!E:E,Estrutura_Mínima_BEP!E53,Análise_Rescisões_Estrutura!G:G,FALSE) -> 5452.7678 | K53: =SUMIFS(Análise_Rescisões_Estrutura!I:I,Análise_Rescisões_Estrutura!E:E,Estrutura_Mínima_BEP!E53,Análise_Rescisões_Estrutura!H:H,FALSE) -> 5452.7678
E54: Usinagem | F54: 156842.15 | H54: =SUMIFS(Análise_Rescisões_Estrutura!I:I,Análise_Rescisões_Estrutura!E:E,Estrutura_Mínima_BEP!E54,Análise_Rescisões_Estrutura!G:G,FALSE) -> 73251.769 | K54: =SUMIFS(Análise_Rescisões_Estrutura!I:I,Análise_Rescisões_Estrutura!E:E,Estrutura_Mínima_BEP!E54,Análise_Rescisões_Estrutura!H:H,FALSE) -> 34634.644
D56: Relacionados a Produção | F56: =SUM(F57:F69) -> 19131.501 | H56: =SUM(H57:H69) -> 110483.24 | I56: =H56/H$19 -> 0.062863205 | K56: =SUM(K57:K69) -> 61150.9 | L56: =K56/K$19 -> 0.092116232 | N56: Custos e Despesas Estrutura'!A1
E57: 3.03.01.004.00272 - Locação de Cilindros | F57: 0 | H57: 987 | K57: 494
E58: 3.04.01.005.00468 - Despesas com Exportação | F58: 0 | H58: 2800 | K58: 2800
E59: 3.03.01.005.00277 - Energia Elétrica | F59: 7703.4675 | H59: 14425.24 | K59: 9376.4
E60: 3.03.01.005.00279 - Água | F60: 2646.7117 | H60: 2647 | K60: 1059
E61: 3.03.01.006.00289 - Manutenção e Reparos | F61: 0 | H61: 15000 | K61: 10000
E62: 3.04.01.005.00324 - Manutenção e Reparos | F62: 0 | H62: =1400+700+11000 -> 13100 | K62: =1400+700+5000 -> 7100
E63: 3.04.01.004.00315 - Aluguéis e Condomínios | F63: 0 | H63: 38901 | K63: 18899
E64: 3.04.01.004.00316 - Energia Elétrica | F64: 0 | H64: 0 | K64: 0
E65: 3.04.01.004.00317 - Telefone | F65: 3283.4283 | H65: 3283 | K65: =H65*0.5 -> 1641.5
E66: 3.04.01.004.00319 - IPTU | F66: 0 | H66: 18590 | K66: 9031
E67: 3.04.01.004.00426 - Amortizações | F67: 0 | H67: 0 | K67: 0
E68: 3.04.01.005.00330 - Impostos e Taxas | F68: 5497.8933 | H68: 750 | K68: 750
D70: Utilidades e Serviços | F70: =SUM(F71:F78) -> 267225.62 | H70: =SUM(H71:H78) -> 87818.25 | I70: =H70/H$19 -> 0.049967187 | K70: =SUM(K71:K78) -> 60608.25 | L70: =K70/K$19 -> 0.091298797 | N70: Custos e Despesas Estrutura'!A1
E71: 3.03.01.004.00273 - Serviços de Terceiros | F71: 173938.95 | H71: =5000+12000+5000 -> 22000 | K71: =5000+5000 -> 10000
E72: 3.04.01.005.00323 - Lanches e Refeições | F72: 4734.7817 | H72: 20000 | K72: 13000
E73: 3.04.01.005.00325 - Limpeza e Conservação | F73: 67784.39 | H73: 9820 | K73: =H73/2 -> 4910
E74: 3.04.01.005.00326 - Segurança | F74: 4550 | H74: 21000 | K74: 21000
E75: 3.04.01.006.00339 - Fotocópias e Reproduções | F75: 0 | H75: 0 | K75: 0
E76: 3.04.01.006.00340 - Materiais de Escritório | F76: 4532.8342 | H76: 2500 | K76: 1200
E77: 3.04.01.006.00343 - Cartórios e Tabelionatos | F77: 0 | H77: 200 | K77: 200
E78: 3.04.01.005.00327 - Seguros | F78: 11684.66 | H78: =3394+(58851/12)+4000 -> 12298.25 | K78: =3394+(58851/12)+2000 -> 10298.25
D80: SG&A | F80: =SUM(F81:F88) -> 50345.279 | H80: =SUM(H81:H88) -> 55112 | I80: =H80/H$19 -> 0.031357851 | K80: =SUM(K81:K88) -> 27444 | L80: =K80/K$19 -> 0.041340976 | N80: Custos e Despesas Estrutura'!A1
E81: 3.04.01.005.00320 - Correios | F81: 0 | H81: 300 | K81: 150
E82: 3.04.01.006.00335 - Assessoria e Consultoria | F82: 34722.989 | H82: =1518+490+904+8000 -> 10912 | K82: =490+904+6000 -> 7394
E83: 3.04.01.006.00336 - Auditoria | F83: 4722.29 | H83: 0 | K83: 0
E84: 3.04.01.006.00337 - Honorários Advocatícios | F84: 10900 | H84: 4400 | K84: 4400
E85: 3.04.01.005.00328 - Viagens e Estadias | F85: 0 | H85: =36000-5000 -> 31000 | K85: 12000
E86: 3.04.01.005.00467 - Fretes e Combustíveis | F86: 0 | H86: 8500 | K86: 3500
E87: 3.04.01.006.00332 - Feiras e Exposição | F87: 0 | H87: 0 | K87: 0
E88: 3.04.01.006.00333 - Propaganda e Publicidade | F88: 0 | H88: 0 | K88: 0
D90: Outros | F90: =SUM(F91:F98) -> 3920.2617 | H90: =SUM(H91:H98) -> 4208 | I90: =H90/H$19 -> 0.002394285 | K90: =SUM(K91:K98) -> 1000 | L90: =K90/K$19 -> 0.0015063757 | N90: Custos e Despesas Estrutura'!A1
E91: 3.04.01.006.00338 - Assinaturas Jornais e Revistas | F91: 520.49 | H91: 0 | K91: 0
E92: 3.04.01.006.00341 - Donativos e Contribuições | F92: 3399.7717 | H92: =708+3500 -> 4208 | K92: 1000
E93: 3.04.01.006.00342 - Estacionamento | F93: 0 | H93: 0 | K93: 0
E94: 3.04.01.006.00344 - Custas Judiciais | F94: 0 | H94: 0 | K94: 0
E95: 3.04.01.006.00345 - Multas Fiscais | F95: 0 | H95: 0 | K95: 0
E96: 3.04.01.005.00322 - Cursos | F96: 0 | H96: 0 | K96: 0
E97: 3.04.01.006.00346 - Despesas Indedutíveis | F97: 0 | H97: 0 | K97: 0
E98: 3.04.01.007.00490 - Despesas com Indenizações | F98: 0 | H98: 0 | K98: 0
C100: EBITDA | F100: =F37-F43 -> -1362955 | H100: =H37-H43 -> 83819.757 | I100: =H100/H$19 -> 0.047692108 | K100: =K37-K43 -> -122417.79 | L100: =K100/K$19 -> -0.18440719
F101: =IFERROR(F100/#REF!,0) -> 0 | H101: =IFERROR(H100/H19,0) -> 0.047692108 | K101: =IFERROR(K100/K19,0) -> -0.18440719
E102: 3.03.01.005.00275 - Depreciações | F102: 0 | H102: 0 | K102: 0
E103: 3.04.01.004.00314 - Depreciações | F103: 0 | H103: 0 | K103: 0
C105: EBIT | F105: =F100-SUM(F102:F103) -> -1362955 | H105: =H100-SUM(H102:H103) -> 83819.757 | K105: =K100-SUM(K102:K103) -> -122417.79
D107: Juros | F107: 400000 | N107: Custo estimado do juros mensal da dívida bancária
C108: Custo Fixo + Juros Endividamento | F108: =F43+F107 -> 1762955
C110: Capital de Giro | H110: 3675508 | K110: 1150401
C112: Venda de Máquinas | H112: 2626728.8 | K112: 3245728.8

Sheet Mapa_Endividamento
B4: DÍVIDA | C4: GRUPO | D4: CREDOR | E4: GARANTIAS | F4: SALDO ATUAL | G4: PARCELAS | H4: VENCIMENTO | I4: Aprox. Juros [% a.m.] | J4: VALOR VENCIDO | L4: Termo da Dívida | M4: Valor Parcela | N4: Juros Mensais [R$/m]
B5: 1. Bancos | C5: GIROPRE | D5: Banco Itau | E5: SBLC (stand by) | F5: 4550000 | G5: =MAX(Empréstimos_e_Financiamento!J9-Empréstimos_e_Financiamento!K9,1) -> 1 | H5: MAI/2026 | I5: =N5/F5 -> 0.019050149 | M5: 0 | N5: 86678.18
C6: GIROPRE | D6: Banco Itau | F6: 2890000 | G6: =MAX(Empréstimos_e_Financiamento!J10-Empréstimos_e_Financiamento!K10,1) -> 1 | H6: MAI/2026 | I6: =N6/F6 -> 0.017820003 | M6: 0 | N6: 51499.81
C7: FINIMP | D7: Banco Brasil | F7: 766265.27 | G7: =MAX(Empréstimos_e_Financiamento!J21-Empréstimos_e_Financiamento!K21,1) -> 1 | H7: JUL/2025 | J7: 766265.27
C8: FINIMP | D8: Banco Brasil | F8: 383758.38 | G8: =MAX(Empréstimos_e_Financiamento!J20-Empréstimos_e_Financiamento!K20,1) -> 1 | H8: JUN/2025 | J8: 383758.38
C9: FINIMP | D9: Banco Brasil | F9: 317407.3 | G9: =MAX(Empréstimos_e_Financiamento!J23-Empréstimos_e_Financiamento!K23,1) -> 1 | H9: AGO/2025 | J9: 317407.3 | M9: 0
C10: FINIMP | D10: Banco Brasil | F10: 49372 | G10: =MAX(Empréstimos_e_Financiamento!J22-Empréstimos_e_Financiamento!K22,1) -> 1 | H10: AGO/2025 | J10: 49372
C11: SBLC (Stand by Letter of Credit) | F11: =SUM(F5:F10) -> 8956803 | J11: =SUM(J5:J10) -> 1516802.9
C12: GIRO | D12: Banco Brasil | E12: Aval Marcello | F12: =Empréstimos_e_Financiamento!G14 -> 1609756.2 | G12: =MAX(Empréstimos_e_Financiamento!J14-Empréstimos_e_Financiamento!K14,1) -> 33 | H12: MAR/2028 | J12: =Empréstimos_e_Financiamento!M14 -> 108195.19 | M12: =Empréstimos_e_Financiamento!H14 -> 48780.49
C13: FINAME | D13: Copel | F13: 1372792.7 | G13: =MAX(Empréstimos_e_Financiamento!J36-Empréstimos_e_Financiamento!K36,1) -> 84 | H13: JUL/2032 | J13: 0 | M13: 19266.64 | N13: 0
C14: NCE | D14: Santander | F14: =Empréstimos_e_Financiamento!G31 -> 742070.42 | G14: =MAX(Empréstimos_e_Financiamento!J31-Empréstimos_e_Financiamento!K31,1) -> 13 | H14: SET/2026 | J14: 0 | M14: =Empréstimos_e_Financiamento!H31 -> 57082.34
C15: GARANTIA | D15: Banco Itau | F15: 454364 | G15: =MAX(Empréstimos_e_Financiamento!J12-Empréstimos_e_Financiamento!K12,1) -> 1 | H15: JUN/2025 | I15: =N15/F15 -> 0.031499987 | M15: 0 | N15: 14312.46
C16: Aval Marcello | F16: =SUM(F12:F15) -> 4178983.3 | J16: =SUM(J12:J15) -> 108195.19
C17: =Empréstimos_e_Financiamento!C30 -> GIRO | D17: =Empréstimos_e_Financiamento!A30 -> BRADESCO | E17: Aval Flávio e Angelo | F17: =Empréstimos_e_Financiamento!G30 -> 949690.08 | G17: =Empréstimos_e_Financiamento!J30-Empréstimos_e_Financiamento!K30 -> 48 | H17: OUT/2029 | J17: =Empréstimos_e_Financiamento!M30 -> 0 | M17: =Empréstimos_e_Financiamento!H30 -> 19785.21 | N17: =Empréstimos_e_Financiamento!I30 -> 0
C18: =Empréstimos_e_Financiamento!C34 -> Renegociação de Divida | D18: =Empréstimos_e_Financiamento!A34 -> SANTANDER | F18: =Empréstimos_e_Financiamento!G34 -> 694099.92 | G18: =Empréstimos_e_Financiamento!J34 -> 24 | H18: SET/2027 | J18: =Empréstimos_e_Financiamento!M34 -> 0 | M18: =Empréstimos_e_Financiamento!H34 -> 28920.83 | N18: =Empréstimos_e_Financiamento!I34 -> 0
C19: =Empréstimos_e_Financiamento!C26 -> GARANTIA | D19: =Empréstimos_e_Financiamento!A26 -> BANCO BRASIL | F19: =Empréstimos_e_Financiamento!G26 -> 500000 | G19: 1 | H19: SET/2025 | I19: =N19/F19 -> 0.027 | J19: =Empréstimos_e_Financiamento!M26 -> 12514.82 | M19: =Empréstimos_e_Financiamento!H26 -> 0 | N19: =Empréstimos_e_Financiamento!I26 -> 13500
C20: =Empréstimos_e_Financiamento!C13 -> LIMITE C/C | D20: =Empréstimos_e_Financiamento!A13 -> BANCO ITAU | F20: =Empréstimos_e_Financiamento!G13 -> 350000 | G20: 1 | H20: JUN/2025 | I20: =N20/F20 -> 0.13895714 | J20: =Empréstimos_e_Financiamento!M13 -> 0 | M20: =Empréstimos_e_Financiamento!H13 -> 0 | N20: =Empréstimos_e_Financiamento!I13 -> 48635
C21: =Empréstimos_e_Financiamento!C15 -> GIRO | D21: =Empréstimos_e_Financiamento!A15 -> BANCO BRASIL | F21: =Empréstimos_e_Financiamento!G15 -> 347728.34 | G21: =Empréstimos_e_Financiamento!J15-Empréstimos_e_Financiamento!K15 -> 5 | H21: NOV/2025 | J21: =Empréstimos_e_Financiamento!M15 -> 175935.81 | M21: =Empréstimos_e_Financiamento!H15 -> 86868.12 | N21: =Empréstimos_e_Financiamento!I15 -> 0
C22: =Empréstimos_e_Financiamento!C24 -> Liquidação Finimp 409 | D22: =Empréstimos_e_Financiamento!A24 -> BANCO BRASIL | F22: =Empréstimos_e_Financiamento!G24 -> 278661.03 | G22: =Empréstimos_e_Financiamento!J24-Empréstimos_e_Financiamento!K24 -> 36 | H22: 22/07/2028 | J22: =Empréstimos_e_Financiamento!M24 -> 25456.82 | M22: =Empréstimos_e_Financiamento!H24 -> 12728.41 | N22: =Empréstimos_e_Financiamento!I24 -> 0
C23: =Empréstimos_e_Financiamento!C25 -> Liquidação Finimp 1166 | D23: =Empréstimos_e_Financiamento!A25 -> BANCO BRASIL | F23: =Empréstimos_e_Financiamento!G25 -> 269362.97 | G23: =Empréstimos_e_Financiamento!J25-Empréstimos_e_Financiamento!K25 -> 33 | H23: 18/06/2028 | J23: =Empréstimos_e_Financiamento!M25 -> 0 | M23: =Empréstimos_e_Financiamento!H25 -> 14045.43 | N23: =Empréstimos_e_Financiamento!I25 -> 0
C24: =Empréstimos_e_Financiamento!C35 -> LIMITE C/C | D24: =Empréstimos_e_Financiamento!A35 -> CAIXA | F24: =Empréstimos_e_Financiamento!G35 -> 100000 | G24: 1 | H24: JUN/2025 | I24: =N24/F24 -> 0.1379984 | J24: =Empréstimos_e_Financiamento!M35 -> 0 | M24: =Empréstimos_e_Financiamento!H35 -> 0 | N24: =Empréstimos_e_Financiamento!I35 -> 13799.84
C25: =Empréstimos_e_Financiamento!C27 -> LIMITE C/C | D25: =Empréstimos_e_Financiamento!A27 -> BANCO BRASIL | F25: =Empréstimos_e_Financiamento!G27 -> 24000 | G25: 1 | H25: JUN/2025 | J25: =Empréstimos_e_Financiamento!M27 -> 0 | M25: =Empréstimos_e_Financiamento!H27 -> 0 | N25: =Empréstimos_e_Financiamento!I27 -> 3768
C26: Aval Flávio/Angelo | F26: =SUM(F17:F25) -> 3513542.3 | J26: =SUM(J17:J25) -> 213907.45
C27: CDC | D27: Banco Itau | E27: Garantia Real - Carro Jeep | F27: =Empréstimos_e_Financiamento!G11 -> 40061.98 | G27: =MAX(Empréstimos_e_Financiamento!J11-Empréstimos_e_Financiamento!K11,1) -> 14 | H27: SET/2026 | M27: 4323.01 | N27: 0
C28: FINAME | D28: Banco Itau | E28: Garantia Real - Máquina Romi | F28: =Empréstimos_e_Financiamento!G8 -> 0 | G28: =MAX(Empréstimos_e_Financiamento!J8-Empréstimos_e_Financiamento!K8,1) -> 1 | H28: SET/2025 | J28: 14275.81 | M28: 14275.81 | N28: 0
C29: Garantia Real | F29: =SUM(F27:F28) -> 40061.98 | J29: =SUM(J27:J28) -> 14275.81
C30: ACC | D30: Banco Brasil | E30: Remessa exportação | F30: 1141740 | G30: =MAX(Empréstimos_e_Financiamento!J17-Empréstimos_e_Financiamento!K17,1) -> 1 | H30: DEZ/2025 | M30: 0 | N30: 0
C31: ACC | D31: Banco Brasil | F31: 719296.2 | G31: =MAX(Empréstimos_e_Financiamento!J16-Empréstimos_e_Financiamento!K16,1) -> 1 | H31: NOV/2025 | M31: 0 | N31: 0
C32: Remessa exportação | F32: =SUM(F30:F31) -> 1861036.2 | J32: =SUM(J30:J31) -> 0
C33: TOTAL | F33: =F32+F29+F26+F16+F11 -> 18550427 | J33: =J32+J29+J26+J16+J11 -> 1853181.4
B34: 2. Fornecedores | C34: A | F34: =SUMIFS(Aging_fornecedores!$D:$D,Aging_fornecedores!$G:$G,C34) -> 1529703.1 | J34: =SUMIFS(Aging_fornecedores!$P:$P,Aging_fornecedores!$G:$G,Mapa_Endividamento!C34) -> 1474383.7
C35: B | F35: =SUMIFS(Aging_fornecedores!$D:$D,Aging_fornecedores!$G:$G,C35) -> 938347.95 | J35: =SUMIFS(Aging_fornecedores!$P:$P,Aging_fornecedores!$G:$G,Mapa_Endividamento!C35) -> 907957.2
C36: C | F36: =SUMIFS(Aging_fornecedores!$D:$D,Aging_fornecedores!$G:$G,C36) -> 2174141.9 | J36: =SUMIFS(Aging_fornecedores!$P:$P,Aging_fornecedores!$G:$G,Mapa_Endividamento!C36) -> 2114034.8
C37: TOTAL | F37: =SUM(F34:F36) -> 4642192.9 | J37: =SUM(J34:J36) -> 4496375.8
B38: 3. Tributária | C38: ICMS | D38: Estado | F38: =SUMIFS('Dividas tributárias'!$I$8:$I$21,'Dividas tributárias'!$A$8:$A$21,Mapa_Endividamento!C38) -> 407232.2 | H38: JUN/2025 | J38: =F38 -> 407232.2
C39: INSS | D39: Federação | F39: =SUMIFS('Dividas tributárias'!$I$8:$I$21,'Dividas tributárias'!$A$8:$A$21,Mapa_Endividamento!C39) -> 638297.99 | H39: AGO/2025 | J39: =F39 -> 638297.99
C40: PIS | D40: Federação | F40: =SUMIFS('Dividas tributárias'!$I$8:$I$21,'Dividas tributárias'!$A$8:$A$21,Mapa_Endividamento!C40) -> 17866.02 | H40: JUL/2025 | J40: =F40 -> 17866.02
C41: COFINS | D41: Federação | F41: =SUMIFS('Dividas tributárias'!$I$8:$I$21,'Dividas tributárias'!$A$8:$A$21,Mapa_Endividamento!C41) -> 79862.84 | H41: JUL/2025 | J41: =F41 -> 79862.84
C42: IRRF | D42: Federação | F42: =SUMIFS('Dividas tributárias'!$I$8:$I$21,'Dividas tributárias'!$A$8:$A$21,Mapa_Endividamento!C42) -> 92074.93 | H42: AGO/2025 | J42: =F42 -> 92074.93
C43: IPTU | D43: Município | F43: =SUMIFS('Dividas tributárias'!$I$8:$I$21,'Dividas tributárias'!$A$8:$A$21,Mapa_Endividamento!C43) -> 152318.05 | H43: AGO/2025 | J43: =F43 -> 152318.05
C44: Não inscritos na dívida ativa | F44: =SUM(F38:F43) -> 1387652 | J44: =SUM(J38:J43) -> 1387652
C45: ICMS Parcelamento | D45: Estado | F45: =SUMIFS('Dividas tributárias'!$I:$I,'Dividas tributárias'!$A:$A,Mapa_Endividamento!C45) -> 1106775.3 | H45: AGO/2025 | J45: ='Dividas tributárias'!G25*'Dividas tributárias'!H25+'Dividas tributárias'!G26*'Dividas tributárias'!H26 -> 32172.94
C46: INSS Parcelamento | D46: Federação | F46: =SUMIFS('Dividas tributárias'!$I:$I,'Dividas tributárias'!$A:$A,Mapa_Endividamento!C46) -> 974795.34 | H46: SET/2025 | J46: ='Dividas tributárias'!G27*'Dividas tributárias'!H27 -> 16521.95
C47: Parcelamentos | F47: =SUM(F45:F46) -> 2081570.7 | J47: =SUM(J45:J46) -> 48694.89
C48: TOTAL | F48: =F47+F44 -> 3469222.7 | J48: =J47+J44 -> 1436346.9
B49: 4. Outras dívidas | C49: Provisão para rescisões trabalhistas | F49: 2165068.1
B50: GRAND TOTAL | F50: =F48+F33+F37 -> 26661842 | J50: =J48+J33+J37 -> 7785904.1

Sheet Empréstimos_e_Financiamento
A1: Data de atualização: | C1: 29/08
A2: Ref. Documento: | C2: Empréstimos_e_Financiamento | N2: Conseguir credores pequenos
A4: MACLÍNEA - MÁQUINAS E EQUIPAMENTOS LTDA
A5: FINANCIAMENTOS E EMPRÉSTIMOS
I6: =H8*2 -> 0
A7: BANCO | B7: CONTRATO | C7: MODALIDADE | D7: GARANTIA | E7: FINALIDADE | F7: VCTO. | G7: SALDO | H7: Valor Parcela | I7: Juros Mensais | J7: Parcelas Totais | K7: Parcelas Quitadas | L7: Parcelas Vencidas | M7: Valores vencidos R$ | N7: Observações | O7: Parcelas Restantes | P7: Parcelas Restantes * Valor Parcela | T7: CONCATENADO | U7: VCTO.
A8: BANCO ITAU | B8: 400613744 | C8: FINAME | D8: próprio bem | E8: IMOBILIZADO | F8: SET/2025 | G8: 0 | H8: 0 | I8: 0 | J8: 60 | K8: 60 | L8: 0 | N8: Finame da Máquina Romi | O8: 1 | P8: 14275.81 | T8: =_xlfn.CONCAT(C8,"?",A8,"?",G8) -> FINAME?BANCO ITAU?0 | U8: SET/2025
A9: BANCO ITAU | B9: 769815952 | C9: GIROPRE | D9: SBLC (stand by) | E9: CAPITAL GIRO | F9: MAI/2026 | G9: 4550000 | H9: 0 | I9: 86678.18 | O9: 1 | P9: 0 | T9: =_xlfn.CONCAT(C9,"?",A9,"?",G9) -> GIROPRE?BANCO ITAU?4550000 | U9: MAI/2026
A10: BANCO ITAU | B10: 301162475 | C10: GIROPRE | D10: SBLC (stand by) | E10: CAPITAL GIRO | F10: MAI/2026 | G10: 2890000 | H10: 0 | I10: 51499.81 | O10: 1 | P10: 0 | T10: =_xlfn.CONCAT(C10,"?",A10,"?",G10) -> GIROPRE?BANCO ITAU?2890000 | U10: MAI/2026
A11: BANCO ITAU | B11: 17818842 | C11: CDC | D11: próprio bem | E11: IMOBILIZADO | F11: SET/2026 | G11: 40061.98 | H11: 4323.01 | I11: 0 | J11: 48 | K11: 34 | L11: 0 | N11: CDC do carro Jeep | O11: 14 | P11: 60522.14 | T11: =_xlfn.CONCAT(C11,"?",A11,"?",G11) -> CDC?BANCO ITAU?40061,98 | U11: SET/2026
A12: BANCO ITAU | B12: - | C12: GARANTIA | D12: aval Marcello | E12: CAPITAL GIRO | F12: JUN/2025 | G12: 454364 | H12: 0 | I12: 14312.46 | O12: 1 | P12: 0 | T12: =_xlfn.CONCAT(C12,"?",A12,"?",G12) -> GARANTIA?BANCO ITAU?454364 | U12: JUN/2025
A13: BANCO ITAU | B13: - | C13: LIMITE C/C | D13: aval Flávio | E13: CAPITAL GIRO | F13: JUN/2025 | G13: 350000 | H13: 0 | I13: 48635 | O13: 1 | P13: 0 | T13: =_xlfn.CONCAT(C13,"?",A13,"?",G13) -> LIMITE C/C?BANCO ITAU?350000 | U13: JUN/2025
A14: BANCO BRASIL | B14: 162218235 | C14: GIRO | D14: aval Marcello/Flavio | E14: CAPITAL GIRO | F14: MAR/2028 | G14: 1609756.2 | H14: 48780.49 | J14: 41 | K14: 8 | L14: 2 | M14: 108195.19 | N14: Valor apontado no Serasa | O14: 33 | P14: 1609756.2 | Q14: Valor das Parcelas * Parcelas Remanescentes muito próximo do saldo atual + Valor vencido acima do valor parcela | T14: =_xlfn.CONCAT(C14,"?",A14,"?",G14) -> GIRO ?BANCO BRASIL?1609756,17 | U14: MAR/2028
A15: BANCO BRASIL | B15: 162218545 | C15: GIRO | D15: aval Flávio/Angelo | E15: CAPITAL GIRO | F15: NOV/2025 | G15: 347728.34 | H15: 86868.12 | J15: 12 | K15: 7 | L15: 2 | M15: 175935.81 | N15: Valor apontado no Serasa | O15: 5 | P15: 434340.6 | Q15: Valor vencido acima do valor parcela | T15: =_xlfn.CONCAT(C15,"?",A15,"?",G15) -> GIRO ?BANCO BRASIL?347728,34 | U15: NOV/2025
A16: BANCO BRASIL | B16: 382982722 | C16: ACC | D16: remessa exportação | E16: CAPITAL GIRO | F16: NOV/2025 | G16: 719296.2 | H16: 0 | I16: 0 | N16: Não tem pagamento mensal, foi prorrogado para nov/2025 | O16: 1 | P16: 0 | T16: =_xlfn.CONCAT(C16,"?",A16,"?",G16) -> ACC?BANCO BRASIL?719296,2 | U16: NOV/2025
A17: BANCO BRASIL | B17: 419812219 | C17: ACC | D17: remessa exportação | E17: CAPITAL GIRO | F17: DEZ/2025 | G17: 1141740 | H17: 0 | I17: 0 | N17: Não tem pagamento mensal, foi prorrogado para dez/2025 | O17: 1 | P17: 0 | T17: =_xlfn.CONCAT(C17,"?",A17,"?",G17) -> ACC?BANCO BRASIL?1141740 | U17: DEZ/2025
A18: BANCO BRASIL | B18: 1166 | C18: FINIMP | D18: SBLC (stand by) | E18: CAPITAL GIRO | F18: ABR/2025 | H18: 0 | N18: Liquidado com empréstimo em 33 vezes | O18: 1 | P18: 0 | T18: =_xlfn.CONCAT(C18,"?",A18,"?",G18) -> FINIMP?BANCO BRASIL? | U18: ABR/2025
A19: BANCO BRASIL | B19: 409 | C19: FINIMP | D19: SBLC (stand by) | E19: CAPITAL GIRO | F19: MAI/2025 | H19: 0 | N19: Liquidado com empréstimo em 36 vezes | O19: 1 | P19: 0 | T19: =_xlfn.CONCAT(C19,"?",A19,"?",G19) -> FINIMP?BANCO BRASIL? | U19: MAI/2025
A20: BANCO BRASIL | B20: 98 | C20: FINIMP | D20: SBLC (stand by) | E20: CAPITAL GIRO | F20: JUN/2025 | G20: 383758.38 | M20: 383758.38 | N20: Vencido não foi possível a renovação, necessário pagamento de 30% banco ainda não exigiu | O20: 1 | P20: 0 | T20: =_xlfn.CONCAT(C20,"?",A20,"?",G20) -> FINIMP?BANCO BRASIL?383758,38 | U20: JUN/2025
A21: BANCO BRASIL | B21: 154 | C21: FINIMP | D21: SBLC (stand by) | E21: CAPITAL GIRO | F21: JUL/2025 | G21: 766265.27 | M21: 766265.27 | N21: Vencido não foi possível a renovação, necessário pagamento de 30% banco ainda não exigiu | O21: 1 | P21: 0 | T21: =_xlfn.CONCAT(C21,"?",A21,"?",G21) -> FINIMP?BANCO BRASIL?766265,27 | U21: JUL/2025
A22: BANCO BRASIL | B22: 721 | C22: FINIMP | D22: SBLC (stand by) | E22: CAPITAL GIRO | F22: AGO/2025 | G22: 49372 | M22: 49372 | N22: Vencido não foi possível a renovação, necessário pagamento de 30% banco ainda não exigiu | O22: 1 | P22: 0 | T22: =_xlfn.CONCAT(C22,"?",A22,"?",G22) -> FINIMP?BANCO BRASIL?49372 | U22: AGO/2025
A23: BANCO BRASIL | B23: 1910 | C23: FINIMP | D23: SBLC (stand by) | E23: CAPITAL GIRO | F23: AGO/2025 | G23: 317407.3 | H23: 0 | M23: 317407.3 | N23: Vencido não foi possível a renovação, necessário pagamento de 30% banco ainda não exigiu | O23: 1 | P23: 0 | T23: =_xlfn.CONCAT(C23,"?",A23,"?",G23) -> FINIMP?BANCO BRASIL?317407,3 | U23: AGO/2025
A24: BANCO BRASIL | B24: 162.218.974 | C24: Liquidação Finimp 409 | D24: Flávio/Angelo | E24: CAPITAL GIRO | F24: 22/07/2028 | G24: 278661.03 | H24: 12728.41 | J24: 36 | K24: 0 | L24: 2 | M24: =12728.41*2 -> 25456.82 | N24: Primeira parcela em 22/08/2025 | O24: 36 | P24: 458222.76 | T24: =_xlfn.CONCAT(C24,"?",A24,"?",G24) -> Liquidação Finimp 409?BANCO BRASIL?278661,03 | U24: 22/07/2028
A25: BANCO BRASIL | B25: 162.218.949 | C25: Liquidação Finimp 1166 | D25: Flávio/Angelo | E25: CAPITAL GIRO | F25: 18/06/2028 | G25: 269362.97 | H25: 14045.43 | J25: 33 | K25: 0 | L25: 0 | N25: Primeira parcela em 18/10/2025 | O25: 33 | P25: 463499.19 | T25: =_xlfn.CONCAT(C25,"?",A25,"?",G25) -> Liquidação Finimp 1166?BANCO BRASIL?269362,97 | U25: 18/06/2028
A26: BANCO BRASIL | B26: - | C26: GARANTIA | D26: Flávio/Angelo | E26: CAPITAL GIRO | F26: SET/2025 | G26: 500000 | I26: 13500 | M26: 12514.82 | N26: Juros de julho não foi pago valor apontado no Serasa | O26: 1 | P26: 0 | T26: =_xlfn.CONCAT(C26,"?",A26,"?",G26) -> GARANTIA?BANCO BRASIL?500000 | U26: SET/2025
A27: BANCO BRASIL | B27: - | C27: LIMITE C/C | D27: Flávio/Angelo | E27: CAPITAL GIRO | F27: JUN/2025 | G27: 24000 | I27: 3768 | O27: 1 | P27: 0 | T27: =_xlfn.CONCAT(C27,"?",A27,"?",G27) -> LIMITE C/C?BANCO BRASIL?24000 | U27: JUN/2025
A28: BRADESCO | B28: 16631120 | C28: GIRO | D28: aval Flávio | E28: CAPITAL GIRO | F28: JUN/2026 | N28: Renegociado 216.666 + 47753,88 = 264.420,88 | O28: 0 | P28: 0 | Q28: Valor vencido acima do valor parcela | T28: =_xlfn.CONCAT(C28,"?",A28,"?",G28) -> GIRO?BRADESCO? | U28: JUN/2026
A29: BRADESCO | B29: 16808214 | C29: GIRO | D29: aval Flávio | E29: CAPITAL GIRO | F29: OUT/2026 | N29: Renegociado 233.750 + 39961,44 = 273.711,44 | O29: 0 | P29: 0 | Q29: Valor vencido acima do valor parcela | T29: =_xlfn.CONCAT(C29,"?",A29,"?",G29) -> GIRO?BRADESCO? | U29: OUT/2026
A30: BRADESCO | B30: 17283962 | C30: GIRO | D30: aval Flávio e Angelo | E30: CAPITAL GIRO | F30: OUT/2029 | G30: 949690.08 | H30: 19785.21 | J30: 48 | K30: 0 | L30: 0 | N30: Ref renegociação Carencia 3 meses - 1 parcela 21/11/2025, ultima 10/10/2025 | O30: 48 | P30: 949690.08 | T30: =_xlfn.CONCAT(C30,"?",A30,"?",G30) -> GIRO?BRADESCO?949690,08 | U30: OUT/2029
A31: SANTANDER | B31: 37180 | C31: NCE | D31: aval Marcello | E31: CAPITAL GIRO | F31: SET/2026 | G31: 742070.42 | H31: 57082.34 | J31: 36 | K31: 23 | L31: 0 | O31: 13 | P31: 742070.42 | Q31: Valor das Parcelas * Parcelas Remanescentes abaixo do saldo atual | T31: =_xlfn.CONCAT(C31,"?",A31,"?",G31) -> NCE?SANTANDER?742070,42 | U31: SET/2026
A32: SANTANDER | B32: - | C32: GARANTIA | D32: aval Flávio | E32: CAPITAL GIRO | F32: JUN/2025 | N32: Renegociado em 28/08/2025 - 24 parcelas x 28.920,83 - 1 parc 22/10/25 ultima 22/09/2027 | O32: 24 | P32: 0 | Q32: Não tem informação do juros | T32: =_xlfn.CONCAT(C32,"?",A32,"?",G32) -> GARANTIA?SANTANDER? | U32: JUN/2025
A33: SANTANDER | B33: - | C33: LIMITE C/C | D33: aval Flávio | E33: CAPITAL GIRO | F33: JUN/2025 | H33: 0 | N33: Renegociado em 28/08/2025 - 24 parcelas x 28.920,83 - 1 parc 22/10/25 ultima 22/09/2027 | O33: 1 | P33: 0 | T33: =_xlfn.CONCAT(C33,"?",A33,"?",G33) -> LIMITE C/C?SANTANDER? | U33: JUN/2025
A34: SANTANDER | B34: 00332190300000047430 | C34: Renegociação de Divida | D34: aval Flávio e Angelo | E34: CAPITAL GIRO | F34: SET/2027 | G34: 694099.92 | H34: 28920.83 | J34: 24 | K34: 0 | L34: 0 | N34: Ref renegociação do conta garantida de 400 mil e o limite de cheque especial 90 mil | O34: 1 | T34: =_xlfn.CONCAT(C34,"?",A34,"?",G34) -> Renegociação de Divida?SANTANDER?694099,92 | U34: SET/2027
A35: CAIXA | B35: - | C35: LIMITE C/C | D35: aval Flávio | E35: CAPITAL GIRO | F35: JUN/2025 | G35: 100000 | H35: 0 | I35: 13799.84 | O35: 1 | P35: 0 | T35: =_xlfn.CONCAT(C35,"?",A35,"?",G35) -> LIMITE C/C?CAIXA?100000 | U35: JUN/2025
A36: COPEL | B36: 4600022060 | C36: FINAME | D36: aval Marcello | E36: IMOBILIZADO | F36: JUL/2032 | G36: 1372792.7 | H36: 19266.64 | I36: 0 | J36: 89 | K36: 5 | L36: 0 | M36: 0 | N36: Financiamento sistema de geração de energia solar - placas solares | O36: 84 | P36: 1618397.8 | T36: =_xlfn.CONCAT(C36,"?",A36,"?",G36) -> FINAME?COPEL?1372792,67 | U36: JUL/2032
F37: TOTAL | G37: =SUM(G8:G36) -> 18550427 | H37: =SUM(H8:H36) -> 291800.48 | I37: =SUM(I8:I36) -> 232193.29 | M37: =SUM(M8:M36) -> 1838905.6 | T37: =_xlfn.CONCAT(C37,"?",A37,"?",G37) -> ??18550426,73 | U37: TOTAL
F38: TOTAL MÊS | I38: =I37+H37 -> 523993.77 | U38: TOTAL MÊS
F40: Dívida que vai ser impactada por juros ou multa | G40: =G12+G13+SUM(G20:G23)+G26+G27+G35 -> 2945167 | U40: Dívida que vai ser impactada por juros ou multa

Sheet Premissas_Receita
D1: Data de atualização: | G1: 45901
D2: Ref. Documento: | G2: 202508_Maclinea_Reorganization_Analysis_Provisório_rev03
M3: =Premissas_COGS!I3 -> 0.009
C4: Peças e Service | I4: Receita Bruta (Mensal) | J4: Impostos | K4: Receita Líquida (Mensal) | M4: Comissão | O4: Material (unitário) | P4: MOD | Q4: Instalação | R4: Custo Total | T4: MdC | U4: % | V4: 1a Margem
A5: Peças | D5: Comprados | I5: =VLOOKUP(D5,Premissas_COGS!C:E,3,0) -> 400000 | J5: =VLOOKUP(D5,Premissas_COGS!C:F,4,0) -> 0.2354 | K5: =I5*(1-J5) -> 305840 | M5: =$M$3*K5 -> 2752.56 | O5: =VLOOKUP(D5,Premissas_COGS!C:L,9,0) -> 226680 | R5: =SUM(O5:Q5) -> 226680 | T5: =K5-M5-R5 -> 76407.44 | U5: =T5/(K5-M5) -> 0.25209702 | V5: =T5+P5+Q5 -> 76407.44 | W5: =V5/(K5-M5) -> 0.25209702
A6: Peças | D6: Fabricados | I6: =VLOOKUP(D6,Premissas_COGS!C:E,3,0) -> 300000 | J6: =VLOOKUP(D6,Premissas_COGS!C:F,4,0) -> 0.2354 | K6: =I6*(1-J6) -> 229380 | M6: =$M$3*K6 -> 2064.42 | O6: =VLOOKUP(D6,Premissas_COGS!C:L,9,0) -> 102006 | P6: =VLOOKUP(D6,Premissas_COGS!C:L,10,0) -> 34002 | R6: =SUM(O6:Q6) -> 136008 | T6: =K6-M6-R6 -> 91307.58 | U6: =T6/(K6-M6) -> 0.40167761 | V6: =T6+P6+Q6 -> 125309.58 | W6: =V6/(K6-M6) -> 0.55125821
A7: Service | D7: Service | I7: =VLOOKUP(D7,Premissas_COGS!C:E,3,0) -> 150000 | J7: =VLOOKUP(D7,Premissas_COGS!C:F,4,0) -> 0.1425 | K7: =I7*(1-J7) -> 128625 | M7: =$M$3*K7 -> 1157.625 | P7: =VLOOKUP(D7,Premissas_COGS!C:L,10,0) -> 82729 | R7: =SUM(O7:Q7) -> 82729 | T7: =K7-M7-R7 -> 44738.375 | U7: =T7/(K7-M7) -> 0.35097903 | V7: =T7+P7+Q7 -> 127467.38 | W7: =V7/(K7-M7) -> 1
M9: =Premissas_COGS!I9 -> 0.05 | P9: 0.25
C10: Máquinas Pequenas | F10: Qtde (ano) | G10: Qtde (mês) | H10: Preço | I10: Receita Bruta (Mensal) | J10: Impostos | K10: Receita Líquida (Mensal) | M10: Comissão | O10: Material (unitário) | P10: MOD | Q10: Instalação | R10: Custo Total | T10: MdC | U10: % | V10: 1a Margem
A11: Máquinas Pequenas | D11: Impact | F11: 6 | G11: =F11/12 -> 0.5 | H11: 230000 | I11: =H11*G11 -> 115000 | J11: =VLOOKUP(D11,Premissas_COGS!C:F,4,0) -> 0.1724 | K11: =I11-(J11*I11) -> 95174 | M11: =$M$9*K11 -> 4758.7 | O11: =VLOOKUP(D11,Premissas_COGS!C:L,9,0)*G11 -> 60881.925 | P11: =VLOOKUP(D11,Premissas_COGS!C:L,10,0)*G11 -> 21250 | Q11: =VLOOKUP(D11,Premissas_COGS!C:M,11,0)*G11 -> 2868.075 | R11: =SUM(O11:Q11) -> 85000 | T11: =K11-R11-M11 -> 5415.3 | U11: =T11/(K11-M11) -> 0.059893624 | V11: =T11+P11+Q11 -> 29533.375 | W11: =V11/(K11-M11) -> 0.32664134
A12: Máquinas Pequenas | D12: Fast | F12: 2 | G12: =F12/12 -> 0.16666667 | H12: 130000 | I12: =H12*G12 -> 21666.667 | J12: =VLOOKUP(D12,Premissas_COGS!C:F,4,0) -> 0.1724 | K12: =I12-(J12*I12) -> 17931.333 | M12: =$M$9*K12 -> 896.56667 | O12: =VLOOKUP(D12,Premissas_COGS!C:L,9,0)*G12 -> 10840.275 | P12: =VLOOKUP(D12,Premissas_COGS!C:L,10,0)*G12 -> 3750 | Q12: =VLOOKUP(D12,Premissas_COGS!C:M,11,0)*G12 -> 409.725 | R12: =SUM(O12:Q12) -> 15000 | T12: =K12-R12-M12 -> 2034.7667 | U12: =T12/(K12-M12) -> 0.11944787 | V12: =T12+P12+Q12 -> 6194.4917 | W12: =V12/(K12-M12) -> 0.36363819
A13: Máquinas Pequenas | D13: Fast PN | F13: 4 | G13: =F13/12 -> 0.33333333 | H13: 250000 | I13: =H13*G13 -> 83333.333 | J13: =VLOOKUP(D13,Premissas_COGS!C:F,4,0) -> 0.1724 | K13: =I13-(J13*I13) -> 68966.667 | M13: =$M$9*K13 -> 3448.3333 | O13: =VLOOKUP(D13,Premissas_COGS!C:L,9,0)*G13 -> 44064.8 | P13: =VLOOKUP(D13,Premissas_COGS!C:L,10,0)*G13 -> 15416.667 | Q13: =VLOOKUP(D13,Premissas_COGS!C:M,11,0)*G13 -> 2185.2 | R13: =SUM(O13:Q13) -> 61666.667 | T13: =K13-R13-M13 -> 3851.6667 | U13: =T13/(K13-M13) -> 0.058787617 | V13: =T13+P13+Q13 -> 21453.533 | W13: =V13/(K13-M13) -> 0.32744321
A14: Máquinas Pequenas | D14: Smart | F14: 5 | G14: =F14/12 -> 0.41666667 | H14: 350000 | I14: =H14*G14 -> 145833.33 | J14: =VLOOKUP(D14,Premissas_COGS!C:F,4,0) -> 0.1724 | K14: =I14-(J14*I14) -> 120691.67 | M14: =$M$9*K14 -> 6034.5833 | O14: =VLOOKUP(D14,Premissas_COGS!C:L,9,0)*G14 -> 56131.062 | P14: =VLOOKUP(D14,Premissas_COGS!C:L,10,0)*G14 -> 19393.229 | Q14: =VLOOKUP(D14,Premissas_COGS!C:M,11,0)*G14 -> 2048.625 | R14: =SUM(O14:Q14) -> 77572.917 | T14: =K14-R14-M14 -> 37084.167 | U14: =T14/(K14-M14) -> 0.32343546 | V14: =T14+P14+Q14 -> 58526.021 | W14: =V14/(K14-M14) -> 0.51044401
M16: =Premissas_COGS!I16 -> 0.05
C17: Máquinas Grandes | F17: Qtde (ano) | G17: Qtde (mês) | H17: Preço | I17: Receita Bruta (Mensal) | J17: Impostos | K17: Receita Líquida (Mensal) | M17: Comissão | O17: Material | P17: MOD | Q17: Instalação | R17: Custo Total | T17: MdC | U17: % | V17: 1a Margem
A18: Máquinas Grandes | D18: Gemini | F18: 3 | G18: =F18/12 -> 0.25 | H18: =VLOOKUP(D18,Premissas_COGS!C:E,3,0) -> 1050000 | I18: =H18*G18 -> 262500 | J18: =VLOOKUP(D18,Premissas_COGS!C:F,4,0) -> 0.1724 | K18: =I18-(J18*I18) -> 217245 | M18: =$M$16*K18 -> 10862.25 | O18: =VLOOKUP(D18,Premissas_COGS!C:L,9,0)*G18 -> 102052.2 | P18: =VLOOKUP(D18,Premissas_COGS!C:L,10,0)*G18 -> 34427.125 | Q18: =VLOOKUP(D18,Premissas_COGS!C:M,11,0)*G18 -> 1229.175 | R18: =SUM(O18:Q18) -> 137708.5 | T18: =K18-R18-M18 -> 68674.25 | U18: =T18/(K18-M18) -> 0.33275189 | V18: =T18+P18+Q18 -> 104330.55 | W18: =V18/(K18-M18) -> 0.50551972
A19: Máquinas Grandes | D19: Europa 2G | F19: 3 | G19: =F19/12 -> 0.25 | H19: =VLOOKUP(D19,Premissas_COGS!C:E,3,0) -> 420000 | I19: =H19*G19 -> 105000 | J19: =VLOOKUP(D19,Premissas_COGS!C:F,4,0) -> 0.1724 | K19: =I19-(J19*I19) -> 86898 | M19: =$M$16*K19 -> 4344.9 | O19: =VLOOKUP(D19,Premissas_COGS!C:L,9,0)*G19 -> 45670.35 | P19: =VLOOKUP(D19,Premissas_COGS!C:L,10,0)*G19 -> 15769.75 | Q19: =VLOOKUP(D19,Premissas_COGS!C:M,11,0)*G19 -> 1638.9 | R19: =SUM(O19:Q19) -> 63079 | T19: =K19-R19-M19 -> 19474.1 | U19: =T19/(K19-M19) -> 0.23589786 | V19: =T19+P19+Q19 -> 36882.75 | W19: =V19/(K19-M19) -> 0.44677608
A20: Máquinas Grandes | D20: Europa 3G | F20: 3 | G20: =F20/12 -> 0.25 | H20: =VLOOKUP(D20,Premissas_COGS!C:E,3,0) -> 500000 | I20: =H20*G20 -> 125000 | J20: =VLOOKUP(D20,Premissas_COGS!C:F,4,0) -> 0.1724 | K20: =I20-(J20*I20) -> 103450 | M20: =$M$16*K20 -> 5172.5 | O20: =VLOOKUP(D20,Premissas_COGS!C:L,9,0)*G20 -> 54484.163 | P20: =VLOOKUP(D20,Premissas_COGS!C:L,10,0)*G20 -> 18707.688 | Q20: =VLOOKUP(D20,Premissas_COGS!C:M,11,0)*G20 -> 1638.9 | R20: =SUM(O20:Q20) -> 74830.75 | T20: =K20-R20-M20 -> 23446.75 | U20: =T20/(K20-M20) -> 0.23857699 | V20: =T20+P20+Q20 -> 43793.338 | W20: =V20/(K20-M20) -> 0.44560899
A21: Máquinas Grandes | C21: Linha de pintura
A22: Máquinas Grandes | D22: ERS 130 T | F22: 7 | G22: =F22/12 -> 0.58333333 | H22: =VLOOKUP(D22,Premissas_COGS!C:E,3,0) -> 140000 | I22: =H22*G22 -> 81666.667 | J22: =VLOOKUP(D22,Premissas_COGS!C:F,4,0) -> 0.1724 | K22: =I22-(J22*I22) -> 67587.333 | M22: =$M$16*K22 -> 3379.3667 | O22: =VLOOKUP(D22,Premissas_COGS!C:L,9,0)*G22 -> 33758.55 | P22: =VLOOKUP(D22,Premissas_COGS!C:L,10,0)*G22 -> 12208.875 | Q22: =VLOOKUP(D22,Premissas_COGS!C:M,11,0)*G22 -> 2868.075 | R22: =SUM(O22:Q22) -> 48835.5 | T22: =K22-R22-M22 -> 15372.467 | U22: =T22/(K22-M22) -> 0.23941681 | V22: =T22+P22+Q22 -> 30449.417 | W22: =V22/(K22-M22) -> 0.47423113
A23: Máquinas Grandes | D23: ERS 130 T2 | F23: 7 | G23: =F23/12 -> 0.58333333 | H23: =VLOOKUP(D23,Premissas_COGS!C:E,3,0) -> 242000 | I23: =H23*G23 -> 141166.67 | J23: =VLOOKUP(D23,Premissas_COGS!C:F,4,0) -> 0.1724 | K23: =I23-(J23*I23) -> 116829.53 | M23: =$M$16*K23 -> 5841.4767 | O23: =VLOOKUP(D23,Premissas_COGS!C:L,9,0)*G23 -> 59610.862 | P23: =VLOOKUP(D23,Premissas_COGS!C:L,10,0)*G23 -> 20826.312 | Q23: =VLOOKUP(D23,Premissas_COGS!C:M,11,0)*G23 -> 2868.075 | R23: =SUM(O23:Q23) -> 83305.25 | T23: =K23-R23-M23 -> 27682.807 | U23: =T23/(K23-M23) -> 0.24942149 | V23: =T23+P23+Q23 -> 51377.194 | W23: =V23/(K23-M23) -> 0.46290741
A24: Máquinas Grandes | D24: ALS 130 T | F24: 2 | G24: =F24/12 -> 0.16666667 | H24: =VLOOKUP(D24,Premissas_COGS!C:E,3,0) -> 220000 | I24: =H24*G24 -> 36666.667 | J24: =VLOOKUP(D24,Premissas_COGS!C:F,4,0) -> 0.1724 | K24: =I24-(J24*I24) -> 30345.333 | M24: =$M$16*K24 -> 1517.2667 | O24: =VLOOKUP(D24,Premissas_COGS!C:L,9,0)*G24 -> 15702.025 | P24: =VLOOKUP(D24,Premissas_COGS!C:L,10,0)*G24 -> 5370.5833 | Q24: =VLOOKUP(D24,Premissas_COGS!C:M,11,0)*G24 -> 409.725 | R24: =SUM(O24:Q24) -> 21482.333 | T24: =K24-R24-M24 -> 7345.7333 | U24: =T24/(K24-M24) -> 0.25481186 | V24: =T24+P24+Q24 -> 13126.042 | W24: =V24/(K24-M24) -> 0.45532161
A25: Máquinas Grandes | D25: ESP 130 | F25: 2 | G25: =F25/12 -> 0.16666667 | H25: =VLOOKUP(D25,Premissas_COGS!C:E,3,0) -> 220000 | I25: =H25*G25 -> 36666.667 | J25: =VLOOKUP(D25,Premissas_COGS!C:F,4,0) -> 0.1724 | K25: =I25-(J25*I25) -> 30345.333 | M25: =$M$16*K25 -> 1517.2667 | O25: =VLOOKUP(D25,Premissas_COGS!C:L,9,0)*G25 -> 15702.025 | P25: =VLOOKUP(D25,Premissas_COGS!C:L,10,0)*G25 -> 5370.5833 | Q25: =VLOOKUP(D25,Premissas_COGS!C:M,11,0)*G25 -> 409.725 | R25: =SUM(O25:Q25) -> 21482.333 | T25: =K25-R25-M25 -> 7345.7333 | U25: =T25/(K25-M25) -> 0.25481186 | V25: =T25+P25+Q25 -> 13126.042 | W25: =V25/(K25-M25) -> 0.45532161
A26: Máquinas Grandes | D26: TUV 2L | F26: 5 | G26: =F26/12 -> 0.41666667 | H26: =VLOOKUP(D26,Premissas_COGS!C:E,3,0) -> 113000 | I26: =H26*G26 -> 47083.333 | J26: =VLOOKUP(D26,Premissas_COGS!C:F,4,0) -> 0.1724 | K26: =I26-(J26*I26) -> 38966.167 | M26: =$M$16*K26 -> 1948.3083 | O26: =VLOOKUP(D26,Premissas_COGS!C:L,9,0)*G26 -> 19448.625 | P26: =VLOOKUP(D26,Premissas_COGS!C:L,10,0)*G26 -> 6938.125 | Q26: =VLOOKUP(D26,Premissas_COGS!C:M,11,0)*G26 -> 1365.75 | R26: =SUM(O26:Q26) -> 27752.5 | T26: =K26-R26-M26 -> 9265.3583 | U26: =T26/(K26-M26) -> 0.25029428 | V26: =T26+P26+Q26 -> 17569.233 | W26: =V26/(K26-M26) -> 0.47461507
A27: Máquinas Grandes | D27: TUV 3L | F27: 5 | G27: =F27/12 -> 0.41666667 | H27: =VLOOKUP(D27,Premissas_COGS!C:E,3,0) -> 127000 | I27: =H27*G27 -> 52916.667 | J27: =VLOOKUP(D27,Premissas_COGS!C:F,4,0) -> 0.1724 | K27: =I27-(J27*I27) -> 43793.833 | M27: =$M$16*K27 -> 2189.6917 | O27: =VLOOKUP(D27,Premissas_COGS!C:L,9,0)*G27 -> 21925.5 | P27: =VLOOKUP(D27,Premissas_COGS!C:L,10,0)*G27 -> 7763.75 | Q27: =VLOOKUP(D27,Premissas_COGS!C:M,11,0)*G27 -> 1365.75 | R27: =SUM(O27:Q27) -> 31055 | T27: =K27-R27-M27 -> 10549.142 | U27: =T27/(K27-M27) -> 0.25355989 | V27: =T27+P27+Q27 -> 19678.642 | W27: =V27/(K27-M27) -> 0.47299718
A28: Máquinas Grandes | D28: IMP 130 T | F28: 2 | G28: =F28/12 -> 0.16666667 | H28: =VLOOKUP(D28,Premissas_COGS!C:E,3,0) -> 252000 | I28: =H28*G28 -> 42000 | J28: =VLOOKUP(D28,Premissas_COGS!C:F,4,0) -> 0.1724 | K28: =I28-(J28*I28) -> 34759.2 | M28: =$M$16*K28 -> 1737.96 | O28: =VLOOKUP(D28,Premissas_COGS!C:L,9,0)*G28 -> 17255.55 | P28: =VLOOKUP(D28,Premissas_COGS!C:L,10,0)*G28 -> 6025 | Q28: =VLOOKUP(D28,Premissas_COGS!C:M,11,0)*G28 -> 819.45 | R28: =SUM(O28:Q28) -> 24100 | T28: =K28-R28-M28 -> 8921.24 | U28: =T28/(K28-M28) -> 0.27016672 | V28: =T28+P28+Q28 -> 15765.69 | W28: =V28/(K28-M28) -> 0.47744088
A29: Máquinas Grandes | D29: TRANSFER | F29: 6 | G29: =F29/12 -> 0.5 | H29: =VLOOKUP(D29,Premissas_COGS!C:E,3,0) -> 50000 | I29: =H29*G29 -> 25000 | J29: =VLOOKUP(D29,Premissas_COGS!C:F,4,0) -> 0.1724 | K29: =I29-(J29*I29) -> 20690 | M29: =$M$16*K29 -> 1034.5 | O29: =VLOOKUP(D29,Premissas_COGS!C:L,9,0)*G29 -> 10993.05 | P29: =VLOOKUP(D29,Premissas_COGS!C:L,10,0)*G29 -> 3937.5 | Q29: =VLOOKUP(D29,Premissas_COGS!C:M,11,0)*G29 -> 819.45 | R29: =SUM(O29:Q29) -> 15750 | T29: =K29-R29-M29 -> 3905.5 | U29: =T29/(K29-M29) -> 0.19869757 | V29: =T29+P29+Q29 -> 8662.45 | W29: =V29/(K29-M29) -> 0.4407138

Sheet Premissas_COGS
B1: Data de atualização: | E1: 45901
B2: Ref. Documento: | E2: Visita Agosto
I3: 0.009
B4: Peças e Service | E4: Receita Mensal | F4: Impostos | G4: Receita Líquida Mensal | I4: Comissão | K4: Material (A) | L4: MOD (B) | M4: Instalação (C) | N4: Custo total (A+B+C) | P4: MdC | Q4: (%) | R4: 1a Margem | S4: (%)
C5: Comprados | E5: 400000 | F5: 0.2354 | G5: =E5*(1-F5) -> 305840 | I5: =$I$3*G5 -> 2752.56 | K5: 226680 | N5: =SUM(K5:M5) -> 226680 | P5: =G5-I5-N5 -> 76407.44 | Q5: =P5/(G5-I5) -> 0.25209702 | R5: =P5+L5+M5 -> 76407.44 | S5: =R5/(G5-I5) -> 0.25209702
C6: Fabricados | E6: 300000 | F6: 0.2354 | G6: =E6*(1-F6) -> 229380 | I6: =$I$3*G6 -> 2064.42 | K6: 102006 | L6: 34002 | N6: =SUM(K6:M6) -> 136008 | P6: =G6-I6-N6 -> 91307.58 | Q6: =P6/(G6-I6) -> 0.40167761 | R6: =P6+L6+M6 -> 125309.58 | S6: =R6/(G6-I6) -> 0.55125821
C7: Service | E7: 150000 | F7: 0.1425 | G7: =E7*(1-F7) -> 128625 | I7: =$I$3*G7 -> 1157.625 | L7: 82729 | N7: =SUM(K7:M7) -> 82729 | P7: =G7-I7-N7 -> 44738.375 | Q7: =P7/(G7-I7) -> 0.35097903 | R7: =P7+L7+M7 -> 127467.38 | S7: =R7/(G7-I7) -> 1
I9: 0.05 | L9: 0.25
B10: Máquinas Pequenas | E10: Preço | F10: Impostos | G10: Preço líquido | I10: Comissão | K10: Material (A) | L10: MOD (B) | M10: Instalação (C) | N10: Custo total (A+B+C) | P10: MdC | Q10: (%) | R10: 1a Margem | S10: (%)
C11: Impact | E11: 230000 | F11: 0.1724 | G11: =E11*(1-F11) -> 190348 | I11: =G11*$I$9 -> 9517.4 | K11: =N11-M11-L11 -> 121763.85 | L11: =$L$9*N11 -> 42500 | M11: 5736.15 | N11: 170000 | P11: =G11-N11-I11 -> 10830.6 | Q11: =P11/(G11-I11) -> 0.059893624 | R11: =P11+L11+M11 -> 59066.75 | S11: =R11/(G11-I11) -> 0.32664134
C12: Fast | E12: 130000 | F12: 0.1724 | G12: =E12*(1-F12) -> 107588 | I12: =G12*$I$9 -> 5379.4 | K12: =N12-M12-L12 -> 65041.65 | L12: =$L$9*N12 -> 22500 | M12: 2458.35 | N12: 90000 | P12: =G12-N12-I12 -> 12208.6 | Q12: =P12/(G12-I12) -> 0.11944787 | R12: =P12+L12+M12 -> 37166.95 | S12: =R12/(G12-I12) -> 0.36363819
C13: Fast PN | E13: 250000 | F13: 0.1724 | G13: =E13*(1-F13) -> 206900 | I13: =G13*$I$9 -> 10345 | K13: =N13-M13-L13 -> 132194.4 | L13: =$L$9*N13 -> 46250 | M13: 6555.6 | N13: 185000 | P13: =G13-N13-I13 -> 11555 | Q13: =P13/(G13-I13) -> 0.058787617 | R13: =P13+L13+M13 -> 64360.6 | S13: =R13/(G13-I13) -> 0.32744321
C14: Smart | E14: 350000 | F14: 0.1724 | G14: =E14*(1-F14) -> 289660 | I14: =G14*$I$9 -> 14483 | K14: =N14-M14-L14 -> 134714.55 | L14: =$L$9*N14 -> 46543.75 | M14: 4916.7 | N14: 186175 | P14: =G14-N14-I14 -> 89002 | Q14: =P14/(G14-I14) -> 0.32343546 | R14: =P14+L14+M14 -> 140462.45 | S14: =R14/(G14-I14) -> 0.51044401
I16: 0.05 | L16: 0.25
B17: Máquinas Grandes | E17: Preço | F17: Impostos | G17: Preço líquido | I17: Comissão | K17: Material (A) | L17: MOD (B) | M17: Instalação (C) | N17: Custo total (A+B+C) | P17: MdC | Q17: (%) | R17: 1a Margem | S17: (%)
C18: Gemini | E18: 1050000 | F18: 0.1724 | G18: =E18*(1-F18) -> 868980 | I18: =$I$16*G18 -> 43449 | K18: 408208.8 | L18: 137708.5 | M18: 4916.7 | N18: 550834 | P18: =G18-N18-I18 -> 274697 | Q18: =P18/(G18-I18) -> 0.33275189 | R18: =P18+L18+M18 -> 417322.2 | S18: =R18/(G18-I18) -> 0.50551972
C19: Europa 2G | E19: 420000 | F19: 0.1724 | G19: =E19*(1-F19) -> 347592 | I19: =$I$16*G19 -> 17379.6 | K19: 182681.4 | L19: 63079 | M19: 6555.6 | N19: 252316 | P19: =G19-N19-I19 -> 77896.4 | Q19: =P19/(G19-I19) -> 0.23589786 | R19: =P19+L19+M19 -> 147531 | S19: =R19/(G19-I19) -> 0.44677608
C20: Europa 3G | E20: 500000 | F20: 0.1724 | G20: =E20*(1-F20) -> 413800 | I20: =$I$16*G20 -> 20690 | K20: 217936.65 | L20: 74830.75 | M20: 6555.6 | N20: 299323 | P20: =G20-N20-I20 -> 93787 | Q20: =P20/(G20-I20) -> 0.23857699 | R20: =P20+L20+M20 -> 175173.35 | S20: =R20/(G20-I20) -> 0.44560899
B21: Linha de pintura
C22: ERS 130 T | E22: 140000 | F22: 0.1724 | G22: =E22*(1-F22) -> 115864 | I22: =$I$16*G22 -> 5793.2 | K22: 57871.8 | L22: 20929.5 | M22: 4916.7 | N22: 83718 | P22: =G22-N22-I22 -> 26352.8 | Q22: =P22/(G22-I22) -> 0.23941681 | R22: =P22+L22+M22 -> 52199 | S22: =R22/(G22-I22) -> 0.47423113
C23: ERS 130 T2 | E23: 242000 | F23: 0.1724 | G23: =E23*(1-F23) -> 200279.2 | I23: =$I$16*G23 -> 10013.96 | K23: 102190.05 | L23: 35702.25 | M23: 4916.7 | N23: 142809 | P23: =G23-N23-I23 -> 47456.24 | Q23: =P23/(G23-I23) -> 0.24942149 | R23: =P23+L23+M23 -> 88075.19 | S23: =R23/(G23-I23) -> 0.46290741
C24: ALS 130 T | E24: 220000 | F24: 0.1724 | G24: =E24*(1-F24) -> 182072 | I24: =$I$16*G24 -> 9103.6 | K24: 94212.15 | L24: 32223.5 | M24: 2458.35 | N24: 128894 | P24: =G24-N24-I24 -> 44074.4 | Q24: =P24/(G24-I24) -> 0.25481186 | R24: =P24+L24+M24 -> 78756.25 | S24: =R24/(G24-I24) -> 0.45532161
C25: ESP 130 | E25: 220000 | F25: 0.1724 | G25: =E25*(1-F25) -> 182072 | I25: =$I$16*G25 -> 9103.6 | K25: 94212.15 | L25: 32223.5 | M25: 2458.35 | N25: 128894 | P25: =G25-N25-I25 -> 44074.4 | Q25: =P25/(G25-I25) -> 0.25481186 | R25: =P25+L25+M25 -> 78756.25 | S25: =R25/(G25-I25) -> 0.45532161
C26: TUV 2L | E26: 113000 | F26: 0.1724 | G26: =E26*(1-F26) -> 93518.8 | I26: =$I$16*G26 -> 4675.94 | K26: 46676.7 | L26: 16651.5 | M26: 3277.8 | N26: 66606 | P26: =G26-N26-I26 -> 22236.86 | Q26: =P26/(G26-I26) -> 0.25029428 | R26: =P26+L26+M26 -> 42166.16 | S26: =R26/(G26-I26) -> 0.47461507
C27: TUV 3L | E27: 127000 | F27: 0.1724 | G27: =E27*(1-F27) -> 105105.2 | I27: =$I$16*G27 -> 5255.26 | K27: 52621.2 | L27: 18633 | M27: 3277.8 | N27: 74532 | P27: =G27-N27-I27 -> 25317.94 | Q27: =P27/(G27-I27) -> 0.25355989 | R27: =P27+L27+M27 -> 47228.74 | S27: =R27/(G27-I27) -> 0.47299718
C28: IMP 130 T | E28: 252000 | F28: 0.1724 | G28: =E28*(1-F28) -> 208555.2 | I28: =$I$16*G28 -> 10427.76 | K28: 103533.3 | L28: 36150 | M28: 4916.7 | N28: 144600 | P28: =G28-N28-I28 -> 53527.44 | Q28: =P28/(G28-I28) -> 0.27016672 | R28: =P28+L28+M28 -> 94594.14 | S28: =R28/(G28-I28) -> 0.47744088
C29: TRANSFER | E29: 50000 | F29: 0.1724 | G29: =E29*(1-F29) -> 41380 | I29: =$I$16*G29 -> 2069 | K29: 21986.1 | L29: 7875 | M29: 1638.9 | N29: 31500 | P29: =G29-N29-I29 -> 7811 | Q29: =P29/(G29-I29) -> 0.19869757 | R29: =P29+L29+M29 -> 17324.9 | S29: =R29/(G29-I29) -> 0.4407138

Sheet Custos e Despesas Estrutura
C1: -1046700.3 | D1: -1067017.1 | E1: -932656.66 | F1: -836846.59 | G1: -824046.73 | H1: -983288.41 | R1: Considerar? | S1: (Multiple Items)
B2: Desc. | C2: 202501 | D2: 202502 | E2: 202503 | F2: 202504 | G2: 202505 | H2: 202506 | J2: Custo estrutura (sem faturamento) | K2: Método/Motivo | M2: Peças/Service + Máquinas Selecionadas | N2: Método/Motivo | O2: Somente Peças/Service | P2: Método/Motivo
B3: 3.03.01.004.00272 - Locação de Cilindros | C3: -1366.48 | D3: -1480.35 | E3: -1480.35 | F3: -1480.35 | G3: -1480.35 | H3: -1480.35 | J3: 0 | K3: Foi considerado que não é necessário nessa estrutura | M3: 0 | N3: Foi considerado que não é necessário nessa estrutura | O3: 0 | P3: Foi considerado que não é necessário nessa estrutura | R3: Sum of R$ | S3: Column Labels
B4: 3.03.01.004.00273 - Serviços de Terceiros | C4: -110879.33 | D4: -135307.16 | E4: -182526.41 | F4: -188405.52 | G4: -206748.21 | H4: -173938.95 | J4: 173938.95 | K4: 202506 | M4: 15000 | N4: 5 k ZI Manutencao + 5 k JMC Manutencao +5 k LM Manutencao | O4: 6000 | P4: 2 k ZI Manutencao + 2 k JMC Manutencao +2k LM Manutencao | R4: Row Labels | S4: 202501 | T4: 202502 | U4: 202503 | V4: 202504 | W4: 202505 | X4: 202506 | Y4: Grand Total
B5: 3.03.01.005.00275 - Depreciações | C5: -5430.09 | D5: -4897.18 | E5: -5401.23 | F5: -5227 | G5: -5401.23 | H5: -5226.98 | J5: 0 | K5: Não tem efeito caixa | M5: 0 | N5: Não tem efeito caixa | O5: 0 | P5: Não tem efeito caixa | R5: 3.03.01.004.00272 - Locação de Cilindros | S5: -1366.48 | T5: -1480.35 | U5: -1480.35 | V5: -1480.35 | W5: -1480.35 | X5: -1480.35 | Y5: -8768.23
B6: 3.03.01.005.00277 - Energia Elétrica | C6: -8625.41 | D6: -8740.24 | E6: -8497.99 | F6: -18313.15 | G6: -23194.81 | H6: -25070.01 | J6: 7703.4675 | K6: 50% Média do 1H2025 | M6: 4310.6067 | N6: 50% da média do 1T 2025 | O6: 1724.2427 | P6: 20% da média do 1T 2025 | R6: 3.03.01.004.00273 - Serviços de Terceiros | S6: -110879.33 | T6: -135307.16 | U6: -182526.41 | V6: -188405.52 | W6: -206748.21 | X6: -173938.95 | Y6: -997805.58
B7: 3.03.01.005.00279 - Água | C7: -6690.42 | D7: -5086.37 | E7: 0 | F7: -5170.48 | G7: -4336.59 | H7: -10476.68 | J7: 2646.7117 | K7: 50% Média do 1H2025 | M7: 2646.7117 | N7: 50% da média do 1H2025 | O7: 1058.6847 | P7: 20% da média do 1H2025 | R7: 3.03.01.005.00275 - Depreciações | S7: -5430.09 | T7: -4897.18 | U7: -5401.23 | V7: -5227 | W7: -5401.23 | X7: -5226.98 | Y7: -31583.71
B8: 3.03.01.006.00289 - Manutenção e Reparos | C8: -10745.3 | D8: -59302.17 | E8: -16744.2 | F8: -33301 | G8: -1817 | H8: -15641.15 | J8: 0 | K8: nulo | M8: 11462.568 | N8: 50% da média do 1H2025 | O8: 4585.0273 | P8: 20% da média do 1H2025 | R8: 3.03.01.005.00277 - Energia Elétrica | S8: -8625.41 | T8: -8740.24 | U8: -8497.99 | V8: -18313.15 | W8: -23194.81 | X8: -25070.01 | Y8: -92441.61
B9: 3.04.01.004.00314 - Depreciações | C9: -6138.22 | D9: -5723.77 | E9: -6422.11 | F9: -6357.86 | G9: -6680.91 | H9: -6465.45 | J9: 0 | K9: Não tem efeito caixa | M9: 0 | N9: Não tem efeito caixa | O9: 0 | P9: Não tem efeito caixa | R9: 3.03.01.005.00279 - Água | S9: -6690.42 | T9: -5086.37 | V9: -5170.48 | W9: -4336.59 | X9: -10476.68 | Y9: -31760.54
B10: 3.04.01.004.00315 - Aluguéis e Condomínios | C10: -101000 | D10: -17000 | E10: -17000 | F10: -37900 | G10: -65000 | H10: -56500 | J10: 0 | K10: nulo | M10: 12000 | N10: Valor estimado | O10: 5000 | P10: Valor estimado | R10: 3.03.01.006.00289 - Manutenção e Reparos | S10: -10745.3 | T10: -59302.17 | U10: -16744.2 | V10: -33301 | W10: -1817 | X10: -15641.15 | Y10: -137550.82
B11: 3.04.01.004.00316 - Energia Elétrica | C11: -48.46 | D11: -37.7 | E11: -118.63 | F11: -81.49 | G11: -57.56 | H11: -55.27 | J11: 0 | K11: Valor já considerado em outra linha | M11: 0 | N11: Valor já considerado em outra linha | O11: 0 | P11: Valor já considerado em outra linha | R11: 3.04.01.004.00314 - Depreciações | S11: -6138.22 | T11: -5723.77 | U11: -6422.11 | V11: -6357.86 | W11: -6680.91 | X11: -6465.45 | Y11: -37788.32
B12: 3.04.01.004.00317 - Telefone | C12: -8545.53 | D12: -3881.94 | E12: -6988.17 | F12: -4165.73 | G12: -9469.57 | H12: -6350.2 | J12: 3283.4283 | K12: 50% Média do 1H2025 | M12: 3283.4283 | N12: 25% da média do 1H2025 | O12: 656.68567 | P12: 20% da média do 1H2025 | R12: 3.04.01.004.00315 - Aluguéis e Condomínios | S12: -101000 | T12: -17000 | U12: -17000 | V12: -37900 | W12: -65000 | X12: -56500 | Y12: -294400
B13: 3.04.01.004.00319 - IPTU | C13: 0 | D13: 0 | E13: -30463.61 | F13: 0 | G13: 0 | H13: 0 | J13: 0 | K13: nulo | M13: 0 | N13: Já considerado no aluguel | O13: 0 | P13: Já considerado no aluguel | R13: 3.04.01.004.00316 - Energia Elétrica | S13: -48.46 | T13: -37.7 | U13: -118.63 | V13: -81.49 | W13: -57.56 | X13: -55.27 | Y13: -399.11
B14: 3.04.01.004.00426 - Amortizações | C14: -19108.04 | D14: -18638.72 | E14: -19457.28 | F14: -13612.69 | G14: -13512.48 | H14: -13193.52 | J14: 0 | K14: Não tem efeito caixa | M14: 0 | N14: Não tem efeito caixa | O14: 0 | P14: Não tem efeito caixa | R14: 3.04.01.004.00317 - Telefone | S14: -8545.53 | T14: -3881.94 | U14: -6988.17 | V14: -4165.73 | W14: -9469.57 | X14: -6350.2 | Y14: -39401.14
B15: 3.04.01.005.00320 - Correios | C15: -270.62 | D15: -901.11 | E15: -620.2 | F15: -262.16 | G15: -1300.35 | H15: -1254.76 | J15: 0 | K15: nulo | M15: 384.1 | N15: 50% da média do 1H2025 | O15: 153.64 | P15: 20% da média do 1H2025 | R15: 3.04.01.004.00319 - IPTU | U15: -30463.61 | Y15: -30463.61
B16: 3.04.01.005.00322 - Cursos | C16: 0 | D16: 0 | E16: 0 | F16: 0 | G16: 0 | H16: -3460 | J16: 0 | K16: nulo | M16: 0 | N16: Despesa considerada não essencial | O16: 0 | P16: Despesa considerada não essencial | R16: 3.04.01.004.00426 - Amortizações | S16: -19108.04 | T16: -18638.72 | U16: -19457.28 | V16: -13612.69 | W16: -13512.48 | X16: -13193.52 | Y16: -97522.73
B17: 3.04.01.005.00323 - Lanches e Refeições | C17: -4413.46 | D17: -6159.51 | E17: -16544.74 | F17: -12455.07 | G17: -7391.39 | H17: -9853.21 | J17: 4734.7817 | K17: 50% Média do 1H2025 | M17: 0 | N17: Despesa considerada não essencial | O17: 0 | P17: Despesa considerada não essencial | R17: 3.04.01.005.00320 - Correios | S17: -270.62 | T17: -901.11 | U17: -620.2 | V17: -262.16 | W17: -1300.35 | X17: -1254.76 | Y17: -4609.2
B18: 3.04.01.005.00324 - Manutenção e Reparos | C18: -25241.02 | D18: -21069.29 | E18: -24293.29 | F18: -22732.45 | G18: -22845.69 | H18: -27889.63 | J18: 0 | K18: nulo | M18: 12005.948 | N18: 50% da média do 1H2025 | O18: 4802.379 | P18: 20% da média do 1H2025 | R18: 3.04.01.005.00322 - Cursos | X18: -3460 | Y18: -3460
B19: 3.04.01.005.00325 - Limpeza e Conservação | C19: -233259.12 | D19: -135346.86 | E19: -178832.65 | F19: -121262.57 | G19: -80874.96 | H19: -63836.52 | J19: 67784.39 | K19: 50% Média do 1H2025 | M19: 19635.52 | N19: (202506 mas Sem J.O.F. SOLUCOES; sem AMB UNIFORMES; sem MDS INSTALACAO; sem ALVIN ALONSO FRANCIS; Sem SANREI INSTALACOES) | O19: 9817.76 | P19: 50% do outro cenário | R19: 3.04.01.005.00323 - Lanches e Refeições | S19: -4413.46 | T19: -6159.51 | U19: -16544.74 | V19: -12455.07 | W19: -7391.39 | X19: -9853.21 | Y19: -56817.38
B20: 3.04.01.005.00326 - Segurança | C20: -59720.15 | D20: -56657.15 | E20: -49925.41 | F20: -4550 | G20: -4550 | H20: -4550 | J20: 4550 | K20: Média do 2T 2025 | M20: 0 | N20: Despesa considerada não essencial | O20: 0 | P20: Despesa considerada não essencial | R20: 3.04.01.005.00324 - Manutenção e Reparos | S20: -25241.02 | T20: -21069.29 | U20: -24293.29 | V20: -22732.45 | W20: -22845.69 | X20: -27889.63 | Y20: -144071.37
B21: 3.04.01.005.00327 - Seguros | C21: -11018.13 | D21: -12275.4 | E21: -12453.6 | F21: -12420.54 | G21: -7689.23 | H21: -14944.21 | J21: 11684.66 | K21: Média do 2T 2025 | M21: 0 | N21: Despesa considerada não essencial | O21: 0 | P21: Despesa considerada não essencial | R21: 3.04.01.005.00325 - Limpeza e Conservação | S21: -233259.12 | T21: -135346.86 | U21: -178832.65 | V21: -121262.57 | W21: -80874.96 | X21: -63836.52 | Y21: -813412.68
B22: 3.04.01.005.00328 - Viagens e Estadias | C22: -73672.28 | D22: -66530.51 | E22: -47136.84 | F22: -84717.23 | G22: -97067.24 | H22: -56796.77 | J22: 0 | K22: nulo | M22: 5678.9449 | N22: 8% da média do 1H2025 | O22: 3549.3406 | P22: 5% da média do 1H2025 | R22: 3.04.01.005.00326 - Segurança | S22: -59720.15 | T22: -56657.15 | U22: -49925.41 | V22: -4550 | W22: -4550 | X22: -4550 | Y22: -179952.71
B23: 3.04.01.005.00330 - Impostos e Taxas | C23: -12738.67 | D23: -5945.3 | E23: -8468.41 | F23: -6717.89 | G23: -4746.26 | H23: -5029.53 | J23: 5497.8933 | K23: Média do 2T 2025 | M23: 1454.8687 | N23: 20% 202506 | O23: 1454.8687 | P23: 20% 202506 | R23: 3.04.01.005.00327 - Seguros | S23: -11018.13 | T23: -12275.4 | U23: -12453.6 | V23: -12420.54 | W23: -7689.23 | X23: -14944.21 | Y23: -70801.11
B24: 3.04.01.005.00467 - Fretes e Combustíveis | C24: -16295.1 | D24: -19560.69 | E24: -11877.87 | F24: -20399.51 | G24: -18859.26 | H24: -16883.09 | J24: 0 | K24: nulo | M24: 1385.0069 | N24: 8% da média do 1H2025 | O24: 865.62933 | P24: 5% da média do 1H2025 | R24: 3.04.01.005.00328 - Viagens e Estadias | S24: -73672.28 | T24: -66530.51 | U24: -47136.84 | V24: -84717.23 | W24: -97067.24 | X24: -56796.77 | Y24: -425920.87
B25: 3.04.01.005.00468 - Despesas com Exportação | C25: 0 | D25: -5157.18 | E25: -880 | F25: -5220 | G25: -1495 | H25: 0 | J25: 0 | K25: nulo | M25: 0 | N25: Nulo | O25: 0 | P25: Nulo | R25: 3.04.01.005.00330 - Impostos e Taxas | S25: -12738.67 | T25: -5945.3 | U25: -8468.41 | V25: -6717.89 | W25: -4746.26 | X25: -5029.53 | Y25: -43646.06
B26: 3.04.01.006.00332 - Feiras e Exposição | C26: -1540 | D26: -53913.89 | E26: -20839.51 | F26: -4920 | G26: 0 | H26: 0 | J26: 0 | K26: nulo | M26: 0 | N26: Despesa considerada não essencial | O26: 0 | P26: Despesa considerada não essencial | R26: 3.04.01.005.00467 - Fretes e Combustíveis | S26: -16295.1 | T26: -19560.69 | U26: -11877.87 | V26: -20399.51 | W26: -18859.26 | X26: -16883.09 | Y26: -103875.52
B27: 3.04.01.006.00333 - Propaganda e Publicidade | C27: 0 | D27: 0 | E27: 0 | F27: 0 | G27: 0 | H27: 0 | J27: 0 | K27: nulo | M27: 0 | N27: Despesa considerada não essencial | O27: 0 | P27: Despesa considerada não essencial | R27: 3.04.01.005.00468 - Despesas com Exportação | T27: -5157.18 | U27: -880 | V27: -5220 | W27: -1495 | Y27: -12752.18
B28: 3.04.01.006.00334 - Perdas de Duplicatas | C28: 0 | D28: 0 | E28: 0 | F28: 0 | G28: 0 | H28: 0 | J28: 0 | K28: nulo | M28: 0 | N28: Despesa considerada não essencial | O28: 0 | P28: Despesa considerada não essencial | R28: 3.04.01.006.00332 - Feiras e Exposição | S28: -1540 | T28: -53913.89 | U28: -20839.51 | V28: -4920 | Y28: -81213.4
B29: 3.04.01.006.00335 - Assessoria e Consultoria | C29: -203476.31 | D29: -217368.99 | E29: -186109.77 | F29: -175151.41 | G29: -175296.99 | H29: -170396.44 | J29: 34722.989 | K29: 20% Média do 2T 2025 | M29: 18796.665 | N29: 10% da média do 1H2025 | O29: 9398.3326 | P29: 5% da média do 1H2025 | R29: 3.04.01.006.00335 - Assessoria e Consultoria | S29: -203476.31 | T29: -217368.99 | U29: -186109.77 | V29: -175151.41 | W29: -175296.99 | X29: -170396.44 | Y29: -1127799.9
B30: 3.04.01.006.00336 - Auditoria | C30: -4722.29 | D30: -4722.29 | E30: -4722.29 | F30: -4722.29 | G30: -4722.29 | H30: -4722.29 | J30: 4722.29 | K30: Média do 2T 2025 | M30: 4722.29 | N30: 202506 | O30: 4722.29 | P30: 202506 | R30: 3.04.01.006.00336 - Auditoria | S30: -4722.29 | T30: -4722.29 | U30: -4722.29 | V30: -4722.29 | W30: -4722.29 | X30: -4722.29 | Y30: -28333.74
B31: 3.04.01.006.00337 - Honorários Advocatícios | C31: -10900 | D31: -10900 | E31: -10900 | F31: -10900 | G31: -10900 | H31: -10900 | J31: 10900 | K31: Média do 2T 2025 | M31: 1090 | N31: 10% da média do 1H2025 | O31: 545 | P31: 5% da média do 1H2025 | R31: 3.04.01.006.00337 - Honorários Advocatícios | S31: -10900 | T31: -10900 | U31: -10900 | V31: -10900 | W31: -10900 | X31: -10900 | Y31: -65400
B32: 3.04.01.006.00338 - Assinaturas Jornais e Revistas | C32: -513.09 | D32: -513.09 | E32: -513.09 | F32: -513.09 | G32: -524.19 | H32: -524.19 | J32: 520.49 | K32: Média do 2T 2025 | M32: 0 | N32: Despesa considerada não essencial | O32: 0 | P32: Despesa considerada não essencial | R32: 3.04.01.006.00338 - Assinaturas Jornais e Revistas | S32: -513.09 | T32: -513.09 | U32: -513.09 | V32: -513.09 | W32: -524.19 | X32: -524.19 | Y32: -3100.74
B33: 3.04.01.006.00339 - Fotocópias e Reproduções | C33: 0 | D33: 0 | E33: 0 | F33: 0 | G33: 0 | H33: 0 | J33: 0 | K33: nulo | M33: 0 | N33: Despesa considerada não essencial | O33: 0 | P33: Despesa considerada não essencial | R33: 3.04.01.006.00340 - Materiais de Escritório | S33: -14391.63 | T33: -11692.02 | U33: -13476.57 | V33: -5521.91 | W33: -5012.01 | X33: -4299.87 | Y33: -54394.01
B34: 3.04.01.006.00340 - Materiais de Escritório | C34: -14391.63 | D34: -11692.02 | E34: -13476.57 | F34: -5521.91 | G34: -5012.01 | H34: -4299.87 | J34: 4532.8342 | K34: 50% Média do 1H2025 | M34: 906.56683 | N34: 10% da média do 1H2025 | O34: 453.28342 | P34: 5% da média do 1H2025 | R34: 3.04.01.006.00341 - Donativos e Contribuições | S34: -4169.16 | T34: -4169.16 | U34: -12969.46 | V34: -2891.15 | W34: -6926.49 | X34: -9671.84 | Y34: -40797.26
B35: 3.04.01.006.00341 - Donativos e Contribuições | C35: -4169.16 | D35: -4169.16 | E35: -12969.46 | F35: -2891.15 | G35: -6926.49 | H35: -9671.84 | J35: 3399.7717 | K35: Média do 1H2025 | M35: 3399.7717 | N35: 50% da média do 1H2025 | O35: 1359.9087 | P35: 20% da média do 1H2025 | R35: 3.04.01.006.00342 - Estacionamento | S35: -15 | X35: -29 | Y35: -44
B36: 3.04.01.006.00342 - Estacionamento | C36: -15 | D36: 0 | E36: 0 | F36: 0 | G36: 0 | H36: -29 | J36: 0 | K36: nulo | M36: 0 | N36: Despesa considerada não essencial | O36: 0 | P36: Despesa considerada não essencial | R36: 3.04.01.006.00343 - Cartórios e Tabelionatos | S36: -189.44 | Y36: -189.44
B37: 3.04.01.006.00343 - Cartórios e Tabelionatos | C37: -189.44 | D37: 0 | E37: 0 | F37: 0 | G37: 0 | H37: 0 | J37: 0 | K37: nulo | M37: 0 | N37: Despesa considerada não essencial | O37: 0 | P37: Despesa considerada não essencial | R37: 3.04.01.006.00345 - Multas Fiscais | S37: -54041.93 | T37: -81815.14 | X37: -215776.07 | Y37: -351633.14
B38: 3.04.01.006.00344 - Custas Judiciais | C38: 0 | D38: 0 | E38: 0 | F38: 0 | G38: 0 | H38: 0 | J38: 0 | K38: nulo | M38: 0 | N38: Despesa considerada não essencial | O38: 0 | P38: Despesa considerada não essencial | R38: 3.04.01.006.00346 - Despesas Indedutíveis | S38: -2677.96 | T38: -2560.67 | U38: -1720.7 | V38: -2218.05 | W38: -4974.23 | X38: -1355.21 | Y38: -15506.82
B39: 3.04.01.006.00345 - Multas Fiscais | C39: -54041.93 | D39: -81815.14 | E39: 0 | F39: 0 | G39: 0 | H39: -215776.07 | J39: 0 | K39: nulo | M39: 0 | N39: Nulo | O39: 0 | P39: Nulo | R39: 3.04.01.007.00411 - Prejuízo na Venda de Bens | V39: 0 | X39: 0 | Y39: 0
B40: 3.04.01.006.00346 - Despesas Indedutíveis | C40: -2677.96 | D40: -2560.67 | E40: -1720.7 | F40: -2218.05 | G40: -4974.23 | H40: -1355.21 | J40: 0 | K40: nulo | M40: 0 | N40: Despesa considerada não essencial | O40: 0 | P40: Despesa considerada não essencial | R40: 3.04.01.007.00490 - Despesas com Indenizações | S40: -34966.65 | T40: -95599.53 | U40: -36117.37 | V40: -30627.63 | W40: -31282.3 | X40: -46717.22 | Y40: -275310.7
B41: 3.04.01.007.00411 - Prejuízo na Venda de Bens | C41: 0 | D41: 0 | E41: 0 | F41: 0 | G41: 0 | H41: 0 | J41: 0 | K41: nulo | M41: 0 | N41: Nulo | O41: 0 | P41: Nulo | R41: 3.04.02.001.00347 - Outras Receitas | S41: 109.03 | T41: 6001.57 | U41: 2346.33 | V41: 5401.63 | W41: 109.92 | Y41: 13968.48
B42: 3.04.01.007.00490 - Despesas com Indenizações | C42: -34966.65 | D42: -95599.53 | E42: -36117.37 | F42: -30627.63 | G42: -31282.3 | H42: -46717.22 | J42: 0 | K42: nulo | M42: 0 | N42: Nulo | O42: 0 | P42: Nulo | R42: 3.05.01.001.00348 - Descontos Concedidos | T42: -65.27 | U42: -1501.24 | V42: -30 | W42: -0.06 | Y42: -1596.57
B43: 3.04.02.001.00347 - Outras Receitas | C43: 109.03 | D43: 6001.57 | E43: 2346.33 | F43: 5401.63 | G43: 109.92 | H43: 0 | J43: 0 | K43: nulo | M43: 0 | N43: Nulo | O43: 0 | P43: Nulo | R43: 3.05.01.001.00349 - Juros de Mora | S43: -251.01 | T43: -2932.94 | U43: -13356.83 | V43: -30544.41 | W43: -45616.18 | X43: -50340.49 | Y43: -143041.86
B44: 3.04.02.001.00412 - Lucro na Venda de Bens | C44: 0 | D44: 0 | E44: 0 | F44: 0 | G44: 0 | H44: 0 | J44: 0 | K44: nulo | M44: 0 | N44: Nulo | O44: 0 | P44: Nulo | R44: 3.05.01.001.00350 - Juros Selic | S44: -8744.1 | T44: -15880.89 | U44: -8970.82 | V44: -9816.44 | W44: -5092.11 | X44: -52807.61 | Y44: -101311.97
B45: 3.05.01.001.00348 - Descontos Concedidos | C45: 0 | D45: -65.27 | E45: -1501.24 | F45: -30 | G45: -0.06 | H45: 0 | J45: 0 | K45: nulo | M45: 0 | N45: Nulo | O45: 0 | P45: Nulo | R45: 3.05.01.001.00358 - Tarifas Bancárias | S45: -13498.6 | T45: -31739.85 | U45: -33444.72 | V45: -40828.05 | W45: -337900.64 | X45: -32615.97 | Y45: -490027.83
B46: 3.05.01.001.00349 - Juros de Mora | C46: -251.01 | D46: -2932.94 | E46: -13356.83 | F46: -30544.41 | G46: -45616.18 | H46: -50340.49 | J46: 0 | K46: Não faz parte da análise | M46: 0 | N46: Não faz parte da análise | O46: 0 | P46: Não faz parte da análise | R46: 3.05.01.002.00360 - Correção Monetária Passiva | S46: -5394.7 | X46: -20186.9 | Y46: -25581.6
B47: 3.05.01.001.00350 - Juros Selic | C47: -8744.1 | D47: -15880.89 | E47: -8970.82 | F47: -9816.44 | G47: -5092.11 | H47: -52807.61 | J47: 0 | K47: Não faz parte da análise | M47: 0 | N47: Não faz parte da análise | O47: 0 | P47: Não faz parte da análise | R47: Grand Total | S47: -1074588.7 | T47: -1117570.8 | U47: -988429.03 | V47: -918035.49 | W47: -1212655.7 | X47: -1139239.4 | Y47: -6450519
B48: 3.05.01.001.00358 - Tarifas Bancárias | C48: -13498.6 | D48: -31739.85 | E48: -33444.72 | F48: -40828.05 | G48: -337900.64 | H48: -32615.97 | J48: 1633.4261 | K48: 2% da média do 1H2025 | M48: 4083.5653 | N48: 5% da média do 1H2025 | O48: 1633.4261 | P48: 2% da média do 1H2025
B49: 3.05.01.002.00360 - Correção Monetária Passiva | C49: -5394.7 | D49: 0 | E49: 0 | F49: 0 | G49: 0 | H49: -20186.9 | J49: 0 | K49: Não faz parte da análise | M49: 0 | N49: Nulo | O49: 0 | P49: Nulo
B50: 3.05.01.002.00484 - Correção Indedutível | C50: 0 | D50: 0 | E50: 0 | F50: 0 | G50: 0 | H50: 0 | J50: 0 | K50: Nulo | M50: 0 | N50: Nulo | O50: 0 | P50: Nulo
B51: 3.05.02.001.00361 - Descontos Auferidos | C51: 127.86 | D51: 110.59 | E51: 21.6 | F51: 243.36 | G51: 307.03 | H51: 156.95 | J51: 0 | K51: Nulo | M51: 0 | N51: Nulo | O51: 0 | P51: Nulo

Sheet Dividas tributárias
A1: Data de atualização: | E1: 45887
A2: Ref. Documento: | E2: 29 - Parcelamentos | L2: Tempo para Pagar (meses) | M2: 60 | P2: 45962 | Q2: 45962 | R2: 45962 | S2: 45962 | T2: 45962 | U2: 45962
E3: 12 - Relatório dividas tributárias | P3: =P4*1.2/$M$2 -> 8144.644 | Q3: =Q4*1.2/$M$2 -> 12765.96 | R3: =R4*1.2/$M$2 -> 357.3204 | S3: =S4*1.2/$M$2 -> 1597.2568 | T3: =T4*1.2/$M$2 -> 1841.4986 | U3: =U4*1.2/$M$2 -> 3046.361
M4: 45838 | N4: 45838 | O4: 45838 | P4: =I8 -> 407232.2 | Q4: =SUM(I9:I10)+I18 -> 638297.99 | R4: =I11 -> 17866.02 | S4: =I12 -> 79862.84 | T4: =I13+I19 -> 92074.93 | U4: =SUM(I14:I17)+I20 -> 152318.05 | V4: =SUM(Table48[Total]) -> -5176871
A5: INFORMAÇÕES DO DIA 18 | H5: Selic | I5: 0.15 | M5: Parcelamento | P5: Não inscrito na dívida ativa
L6: Data | M6: ICMS - Parcelamento | N6: ICMS - Parcelamento2 | O6: INSS - Parcelamento | P6: ICMS | Q6: INSS | R6: PIS | S6: COFINS | T6: IRRF | U6: IPTU | V6: Total | W6: Categoria | X6: Column1 | Y6: Parcelamento | Z6: Dívida não ativa
A7: Tipo | B7: Divida Ativa | C7: Competência | D7: Vencimento | I7: Valor | L7: 45901 | M7: =-$H$25*3*(1+3%) -> -94355.529 | N7: =-3642.80000000002*(1+3%) -> -3752.084 | O7: =-$H$27*3*(1+3%) -> -51052.826 | V7: =SUM(Table48[[#This Row],[ICMS - Parcelamento]:[IPTU]]) -> -149160.44 | W7: Dívida Tributária | Y7: =SUM(Table48[[#This Row],[ICMS - Parcelamento]:[INSS - Parcelamento]]) -> -149160.44 | Z7: =SUM(Table48[[#This Row],[ICMS]:[IPTU]]) -> 0
A8: ICMS | B8: Não | C8: 45839 | D8: 45881 | I8: 407232.2 | L8: =EDATE(L7,1) -> 45931 | M8: =-$H$25*(1+$I$5)^(YEARFRAC(M$4,Table48[[#This Row],[Data]])) -> -31633.842 | N8: =-$H$26*(1+$I$5)^(YEARFRAC(N$4,Table48[[#This Row],[Data]])) -> -1696.0429 | O8: =-$H$27*(1+$I$5)^(YEARFRAC(O$4,Table48[[#This Row],[Data]])) -> -17116.082 | P8: =IF(Table48[[#This Row],[Column1]]<=$M$2,-P$3,0)*((1+$I$5)^((Table48[[#This Row],[Data]]-$L$7)/365)) -> -8238.7433 | Q8: =IF(Table48[[#This Row],[Column1]]<=$M$2,-Q$3,0)*((1+$I$5)^((Table48[[#This Row],[Data]]-$L$7)/365)) -> -12913.452 | R8: =IF(Table48[[#This Row],[Column1]]<=$M$2,-R$3,0)*((1+$I$5)^((Table48[[#This Row],[Data]]-$L$7)/365)) -> -361.44871 | S8: =IF(Table48[[#This Row],[Column1]]<=$M$2,-S$3,0)*((1+$I$5)^((Table48[[#This Row],[Data]]-$L$7)/365)) -> -1615.7107 | T8: =IF(Table48[[#This Row],[Column1]]<=$M$2,-T$3,0)*((1+$I$5)^((Table48[[#This Row],[Data]]-$L$7)/365)) -> -1862.7744 | U8: =IF(Table48[[#This Row],[Column1]]<=$M$2,-U$3,0)*((1+$I$5)^((Table48[[#This Row],[Data]]-$L$7)/365)) -> -3081.5572 | V8: =SUM(Table48[[#This Row],[ICMS - Parcelamento]:[IPTU]]) -> -78519.653 | W8: Dívida Tributária | X8: 1 | Y8: =SUM(Table48[[#This Row],[ICMS - Parcelamento]:[INSS - Parcelamento]]) -> -50445.967 | Z8: =SUM(Table48[[#This Row],[ICMS]:[IPTU]]) -> -28073.686
A9: INSS | B9: Não | C9: 45778 | D9: 45828 | I9: 229449.38 | L9: =EDATE(L8,1) -> 45962 | M9: =-$H$25*(1+$I$5)^(YEARFRAC(M$4,Table48[[#This Row],[Data]])) -> -32004.43 | N9: =-$H$26*(1+$I$5)^(YEARFRAC(N$4,Table48[[#This Row],[Data]])) -> -1715.9119 | O9: =-$H$27*(1+$I$5)^(YEARFRAC(O$4,Table48[[#This Row],[Data]])) -> -17316.596 | P9: =IF(Table48[[#This Row],[Column1]]<=$M$2,-P$3,0)*((1+$I$5)^((Table48[[#This Row],[Data]]-$L$7)/365)) -> -8337.1215 | Q9: =IF(Table48[[#This Row],[Column1]]<=$M$2,-Q$3,0)*((1+$I$5)^((Table48[[#This Row],[Data]]-$L$7)/365)) -> -13067.65 | R9: =IF(Table48[[#This Row],[Column1]]<=$M$2,-R$3,0)*((1+$I$5)^((Table48[[#This Row],[Data]]-$L$7)/365)) -> -365.76474 | S9: =IF(Table48[[#This Row],[Column1]]<=$M$2,-S$3,0)*((1+$I$5)^((Table48[[#This Row],[Data]]-$L$7)/365)) -> -1635.0038 | T9: =IF(Table48[[#This Row],[Column1]]<=$M$2,-T$3,0)*((1+$I$5)^((Table48[[#This Row],[Data]]-$L$7)/365)) -> -1885.0176 | U9: =IF(Table48[[#This Row],[Column1]]<=$M$2,-U$3,0)*((1+$I$5)^((Table48[[#This Row],[Data]]-$L$7)/365)) -> -3118.3538 | V9: =SUM(Table48[[#This Row],[ICMS - Parcelamento]:[IPTU]]) -> -79445.849 | W9: Dívida Tributária | X9: =X8+1 -> 2 | Y9: =SUM(Table48[[#This Row],[ICMS - Parcelamento]:[INSS - Parcelamento]]) -> -51036.938 | Z9: =SUM(Table48[[#This Row],[ICMS]:[IPTU]]) -> -28408.911
A10: INSS | B10: Não | C10: 45809 | D10: 45856 | I10: 215774.7 | L10: =EDATE(L9,1) -> 45992 | M10: =-$H$25*(1+$I$5)^(YEARFRAC(M$4,Table48[[#This Row],[Data]])) -> -32379.359 | N10: =-$H$26*(1+$I$5)^(YEARFRAC(N$4,Table48[[#This Row],[Data]])) -> -1736.0137 | O10: =-$H$27*(1+$I$5)^(YEARFRAC(O$4,Table48[[#This Row],[Data]])) -> -17519.458 | P10: =IF(Table48[[#This Row],[Column1]]<=$M$2,-P$3,0)*((1+$I$5)^((Table48[[#This Row],[Data]]-$L$7)/365)) -> -8433.4445 | Q10: =IF(Table48[[#This Row],[Column1]]<=$M$2,-Q$3,0)*((1+$I$5)^((Table48[[#This Row],[Data]]-$L$7)/365)) -> -13218.627 | R10: =IF(Table48[[#This Row],[Column1]]<=$M$2,-R$3,0)*((1+$I$5)^((Table48[[#This Row],[Data]]-$L$7)/365)) -> -369.99061 | S10: =IF(Table48[[#This Row],[Column1]]<=$M$2,-S$3,0)*((1+$I$5)^((Table48[[#This Row],[Data]]-$L$7)/365)) -> -1653.8938 | T10: =IF(Table48[[#This Row],[Column1]]<=$M$2,-T$3,0)*((1+$I$5)^((Table48[[#This Row],[Data]]-$L$7)/365)) -> -1906.7962 | U10: =IF(Table48[[#This Row],[Column1]]<=$M$2,-U$3,0)*((1+$I$5)^((Table48[[#This Row],[Data]]-$L$7)/365)) -> -3154.3818 | V10: =SUM(Table48[[#This Row],[ICMS - Parcelamento]:[IPTU]]) -> -80371.965 | W10: Dívida Tributária | X10: =X9+1 -> 3 | Y10: =SUM(Table48[[#This Row],[ICMS - Parcelamento]:[INSS - Parcelamento]]) -> -51634.831 | Z10: =SUM(Table48[[#This Row],[ICMS]:[IPTU]]) -> -28737.134
A11: PIS | B11: Não | C11: 45809 | D11: 45863 | I11: 17866.02 | L11: =EDATE(L10,1) -> 46023 | M11: =-$H$25*(1+$I$5)^(YEARFRAC(M$4,Table48[[#This Row],[Data]])) -> -32758.681 | N11: =-$H$26*(1+$I$5)^(YEARFRAC(N$4,Table48[[#This Row],[Data]])) -> -1756.351 | O11: =-$H$27*(1+$I$5)^(YEARFRAC(O$4,Table48[[#This Row],[Data]])) -> -17724.697 | P11: =IF(Table48[[#This Row],[Column1]]<=$M$2,-P$3,0)*((1+$I$5)^((Table48[[#This Row],[Data]]-$L$7)/365)) -> -8534.1476 | Q11: =IF(Table48[[#This Row],[Column1]]<=$M$2,-Q$3,0)*((1+$I$5)^((Table48[[#This Row],[Data]]-$L$7)/365)) -> -13376.47 | R11: =IF(Table48[[#This Row],[Column1]]<=$M$2,-R$3,0)*((1+$I$5)^((Table48[[#This Row],[Data]]-$L$7)/365)) -> -374.40864 | S11: =IF(Table48[[#This Row],[Column1]]<=$M$2,-S$3,0)*((1+$I$5)^((Table48[[#This Row],[Data]]-$L$7)/365)) -> -1673.6429 | T11: =IF(Table48[[#This Row],[Column1]]<=$M$2,-T$3,0)*((1+$I$5)^((Table48[[#This Row],[Data]]-$L$7)/365)) -> -1929.5651 | U11: =IF(Table48[[#This Row],[Column1]]<=$M$2,-U$3,0)*((1+$I$5)^((Table48[[#This Row],[Data]]-$L$7)/365)) -> -3192.048 | V11: =SUM(Table48[[#This Row],[ICMS - Parcelamento]:[IPTU]]) -> -81320.011 | W11: Dívida Tributária | X11: =X10+1 -> 4 | Y11: =SUM(Table48[[#This Row],[ICMS - Parcelamento]:[INSS - Parcelamento]]) -> -52239.729 | Z11: =SUM(Table48[[#This Row],[ICMS]:[IPTU]]) -> -29080.282
A12: COFINS | B12: Não | C12: 45809 | D12: 45863 | I12: 79862.84 | L12: =EDATE(L11,1) -> 46054 | M12: =-$H$25*(1+$I$5)^(YEARFRAC(M$4,Table48[[#This Row],[Data]])) -> -33142.446 | N12: =-$H$26*(1+$I$5)^(YEARFRAC(N$4,Table48[[#This Row],[Data]])) -> -1776.9265 | O12: =-$H$27*(1+$I$5)^(YEARFRAC(O$4,Table48[[#This Row],[Data]])) -> -17932.341 | P12: =IF(Table48[[#This Row],[Column1]]<=$M$2,-P$3,0)*((1+$I$5)^((Table48[[#This Row],[Data]]-$L$7)/365)) -> -8636.0532 | Q12: =IF(Table48[[#This Row],[Column1]]<=$M$2,-Q$3,0)*((1+$I$5)^((Table48[[#This Row],[Data]]-$L$7)/365)) -> -13536.197 | R12: =IF(Table48[[#This Row],[Column1]]<=$M$2,-R$3,0)*((1+$I$5)^((Table48[[#This Row],[Data]]-$L$7)/365)) -> -378.87942 | S12: =IF(Table48[[#This Row],[Column1]]<=$M$2,-S$3,0)*((1+$I$5)^((Table48[[#This Row],[Data]]-$L$7)/365)) -> -1693.6277 | T12: =IF(Table48[[#This Row],[Column1]]<=$M$2,-T$3,0)*((1+$I$5)^((Table48[[#This Row],[Data]]-$L$7)/365)) -> -1952.6059 | U12: =IF(Table48[[#This Row],[Column1]]<=$M$2,-U$3,0)*((1+$I$5)^((Table48[[#This Row],[Data]]-$L$7)/365)) -> -3230.164 | V12: =SUM(Table48[[#This Row],[ICMS - Parcelamento]:[IPTU]]) -> -82279.241 | W12: Dívida Tributária | X12: =X11+1 -> 5 | Y12: =SUM(Table48[[#This Row],[ICMS - Parcelamento]:[INSS - Parcelamento]]) -> -52851.713 | Z12: =SUM(Table48[[#This Row],[ICMS]:[IPTU]]) -> -29427.528
A13: IRRF | B13: Não | C13: 45809 | D13: 45856 | I13: =1872.22+948.1+2570.74 -> 5391.06 | L13: =EDATE(L12,1) -> 46082 | M13: =-$H$25*(1+$I$5)^(YEARFRAC(M$4,Table48[[#This Row],[Data]])) -> -33530.707 | N13: =-$H$26*(1+$I$5)^(YEARFRAC(N$4,Table48[[#This Row],[Data]])) -> -1797.743 | O13: =-$H$27*(1+$I$5)^(YEARFRAC(O$4,Table48[[#This Row],[Data]])) -> -18142.417 | P13: =IF(Table48[[#This Row],[Column1]]<=$M$2,-P$3,0)*((1+$I$5)^((Table48[[#This Row],[Data]]-$L$7)/365)) -> -8729.1425 | Q13: =IF(Table48[[#This Row],[Column1]]<=$M$2,-Q$3,0)*((1+$I$5)^((Table48[[#This Row],[Data]]-$L$7)/365)) -> -13682.106 | R13: =IF(Table48[[#This Row],[Column1]]<=$M$2,-R$3,0)*((1+$I$5)^((Table48[[#This Row],[Data]]-$L$7)/365)) -> -382.96342 | S13: =IF(Table48[[#This Row],[Column1]]<=$M$2,-S$3,0)*((1+$I$5)^((Table48[[#This Row],[Data]]-$L$7)/365)) -> -1711.8836 | T13: =IF(Table48[[#This Row],[Column1]]<=$M$2,-T$3,0)*((1+$I$5)^((Table48[[#This Row],[Data]]-$L$7)/365)) -> -1973.6533 | U13: =IF(Table48[[#This Row],[Column1]]<=$M$2,-U$3,0)*((1+$I$5)^((Table48[[#This Row],[Data]]-$L$7)/365)) -> -3264.9824 | V13: =SUM(Table48[[#This Row],[ICMS - Parcelamento]:[IPTU]]) -> -83215.598 | W13: Dívida Tributária | X13: =X12+1 -> 6 | Y13: =SUM(Table48[[#This Row],[ICMS - Parcelamento]:[INSS - Parcelamento]]) -> -53470.866 | Z13: =SUM(Table48[[#This Row],[ICMS]:[IPTU]]) -> -29744.731
A14: IPTU | B14: Não | D14: 45767 | I14: 30463.61 | L14: =EDATE(L13,1) -> 46113 | M14: =-$H$25*(1+$I$5)^(YEARFRAC(M$4,Table48[[#This Row],[Data]])) -> -33923.516 | N14: =-$H$26*(1+$I$5)^(YEARFRAC(N$4,Table48[[#This Row],[Data]])) -> -1818.8034 | O14: =-$H$27*(1+$I$5)^(YEARFRAC(O$4,Table48[[#This Row],[Data]])) -> -18354.954 | P14: =IF(Table48[[#This Row],[Column1]]<=$M$2,-P$3,0)*((1+$I$5)^((Table48[[#This Row],[Data]]-$L$7)/365)) -> -8833.3765 | Q14: =IF(Table48[[#This Row],[Column1]]<=$M$2,-Q$3,0)*((1+$I$5)^((Table48[[#This Row],[Data]]-$L$7)/365)) -> -13845.483 | R14: =IF(Table48[[#This Row],[Column1]]<=$M$2,-R$3,0)*((1+$I$5)^((Table48[[#This Row],[Data]]-$L$7)/365)) -> -387.53635 | S14: =IF(Table48[[#This Row],[Column1]]<=$M$2,-S$3,0)*((1+$I$5)^((Table48[[#This Row],[Data]]-$L$7)/365)) -> -1732.325 | T14: =IF(Table48[[#This Row],[Column1]]<=$M$2,-T$3,0)*((1+$I$5)^((Table48[[#This Row],[Data]]-$L$7)/365)) -> -1997.2206 | U14: =IF(Table48[[#This Row],[Column1]]<=$M$2,-U$3,0)*((1+$I$5)^((Table48[[#This Row],[Data]]-$L$7)/365)) -> -3303.9693 | V14: =SUM(Table48[[#This Row],[ICMS - Parcelamento]:[IPTU]]) -> -84197.184 | W14: Dívida Tributária | X14: =X13+1 -> 7 | Y14: =SUM(Table48[[#This Row],[ICMS - Parcelamento]:[INSS - Parcelamento]]) -> -54097.273 | Z14: =SUM(Table48[[#This Row],[ICMS]:[IPTU]]) -> -30099.911
A15: IPTU | B15: Não | D15: 45797 | I15: 30463.61 | L15: =EDATE(L14,1) -> 46143 | M15: =-$H$25*(1+$I$5)^(YEARFRAC(M$4,Table48[[#This Row],[Data]])) -> -34320.927 | N15: =-$H$26*(1+$I$5)^(YEARFRAC(N$4,Table48[[#This Row],[Data]])) -> -1840.1106 | O15: =-$H$27*(1+$I$5)^(YEARFRAC(O$4,Table48[[#This Row],[Data]])) -> -18569.98 | P15: =IF(Table48[[#This Row],[Column1]]<=$M$2,-P$3,0)*((1+$I$5)^((Table48[[#This Row],[Data]]-$L$7)/365)) -> -8935.4331 | Q15: =IF(Table48[[#This Row],[Column1]]<=$M$2,-Q$3,0)*((1+$I$5)^((Table48[[#This Row],[Data]]-$L$7)/365)) -> -14005.447 | R15: =IF(Table48[[#This Row],[Column1]]<=$M$2,-R$3,0)*((1+$I$5)^((Table48[[#This Row],[Data]]-$L$7)/365)) -> -392.01376 | S15: =IF(Table48[[#This Row],[Column1]]<=$M$2,-S$3,0)*((1+$I$5)^((Table48[[#This Row],[Data]]-$L$7)/365)) -> -1752.3395 | T15: =IF(Table48[[#This Row],[Column1]]<=$M$2,-T$3,0)*((1+$I$5)^((Table48[[#This Row],[Data]]-$L$7)/365)) -> -2020.2955 | U15: =IF(Table48[[#This Row],[Column1]]<=$M$2,-U$3,0)*((1+$I$5)^((Table48[[#This Row],[Data]]-$L$7)/365)) -> -3342.1418 | V15: =SUM(Table48[[#This Row],[ICMS - Parcelamento]:[IPTU]]) -> -85178.689 | W15: Dívida Tributária | X15: =X14+1 -> 8 | Y15: =SUM(Table48[[#This Row],[ICMS - Parcelamento]:[INSS - Parcelamento]]) -> -54731.018 | Z15: =SUM(Table48[[#This Row],[ICMS]:[IPTU]]) -> -30447.67
A16: IPTU | B16: Não | D16: 45828 | I16: 30463.61 | L16: =EDATE(L15,1) -> 46174 | M16: =-$H$25*(1+$I$5)^(YEARFRAC(M$4,Table48[[#This Row],[Data]])) -> -34722.994 | N16: =-$H$26*(1+$I$5)^(YEARFRAC(N$4,Table48[[#This Row],[Data]])) -> -1861.6673 | O16: =-$H$27*(1+$I$5)^(YEARFRAC(O$4,Table48[[#This Row],[Data]])) -> -18787.526 | P16: =IF(Table48[[#This Row],[Column1]]<=$M$2,-P$3,0)*((1+$I$5)^((Table48[[#This Row],[Data]]-$L$7)/365)) -> -9042.1304 | Q16: =IF(Table48[[#This Row],[Column1]]<=$M$2,-Q$3,0)*((1+$I$5)^((Table48[[#This Row],[Data]]-$L$7)/365)) -> -14172.685 | R16: =IF(Table48[[#This Row],[Column1]]<=$M$2,-R$3,0)*((1+$I$5)^((Table48[[#This Row],[Data]]-$L$7)/365)) -> -396.69477 | S16: =IF(Table48[[#This Row],[Column1]]<=$M$2,-S$3,0)*((1+$I$5)^((Table48[[#This Row],[Data]]-$L$7)/365)) -> -1773.264 | T16: =IF(Table48[[#This Row],[Column1]]<=$M$2,-T$3,0)*((1+$I$5)^((Table48[[#This Row],[Data]]-$L$7)/365)) -> -2044.4197 | U16: =IF(Table48[[#This Row],[Column1]]<=$M$2,-U$3,0)*((1+$I$5)^((Table48[[#This Row],[Data]]-$L$7)/365)) -> -3382.05 | V16: =SUM(Table48[[#This Row],[ICMS - Parcelamento]:[IPTU]]) -> -86183.431 | W16: Dívida Tributária | X16: =X15+1 -> 9 | Y16: =SUM(Table48[[#This Row],[ICMS - Parcelamento]:[INSS - Parcelamento]]) -> -55372.188 | Z16: =SUM(Table48[[#This Row],[ICMS]:[IPTU]]) -> -30811.244
A17: IPTU | B17: Não | D17: 45858 | I17: 30463.61 | L17: =EDATE(L16,1) -> 46204 | M17: =-$H$25*(1+$I$5)^(YEARFRAC(M$4,Table48[[#This Row],[Data]])) -> -35129.771 | N17: =-$H$26*(1+$I$5)^(YEARFRAC(N$4,Table48[[#This Row],[Data]])) -> -1883.4766 | O17: =-$H$27*(1+$I$5)^(YEARFRAC(O$4,Table48[[#This Row],[Data]])) -> -19007.62 | P17: =IF(Table48[[#This Row],[Column1]]<=$M$2,-P$3,0)*((1+$I$5)^((Table48[[#This Row],[Data]]-$L$7)/365)) -> -9146.5988 | Q17: =IF(Table48[[#This Row],[Column1]]<=$M$2,-Q$3,0)*((1+$I$5)^((Table48[[#This Row],[Data]]-$L$7)/365)) -> -14336.429 | R17: =IF(Table48[[#This Row],[Column1]]<=$M$2,-R$3,0)*((1+$I$5)^((Table48[[#This Row],[Data]]-$L$7)/365)) -> -401.27798 | S17: =IF(Table48[[#This Row],[Column1]]<=$M$2,-S$3,0)*((1+$I$5)^((Table48[[#This Row],[Data]]-$L$7)/365)) -> -1793.7515 | T17: =IF(Table48[[#This Row],[Column1]]<=$M$2,-T$3,0)*((1+$I$5)^((Table48[[#This Row],[Data]]-$L$7)/365)) -> -2068.0399 | U17: =IF(Table48[[#This Row],[Column1]]<=$M$2,-U$3,0)*((1+$I$5)^((Table48[[#This Row],[Data]]-$L$7)/365)) -> -3421.1246 | V17: =SUM(Table48[[#This Row],[ICMS - Parcelamento]:[IPTU]]) -> -87188.09 | W17: Dívida Tributária | X17: =X16+1 -> 10 | Y17: =SUM(Table48[[#This Row],[ICMS - Parcelamento]:[INSS - Parcelamento]]) -> -56020.868 | Z17: =SUM(Table48[[#This Row],[ICMS]:[IPTU]]) -> -31167.222
A18: INSS | B18: Não | C18: 45839 | D18: 45889 | I18: 193073.91 | L18: =EDATE(L17,1) -> 46235 | M18: =-$H$25*(1+$I$5)^(YEARFRAC(M$4,Table48[[#This Row],[Data]])) -> -35541.314 | N18: =-$H$26*(1+$I$5)^(YEARFRAC(N$4,Table48[[#This Row],[Data]])) -> -1905.5413 | O18: =-$H$27*(1+$I$5)^(YEARFRAC(O$4,Table48[[#This Row],[Data]])) -> -19230.293 | P18: =IF(Table48[[#This Row],[Column1]]<=$M$2,-P$3,0)*((1+$I$5)^((Table48[[#This Row],[Data]]-$L$7)/365)) -> -9255.8176 | Q18: =IF(Table48[[#This Row],[Column1]]<=$M$2,-Q$3,0)*((1+$I$5)^((Table48[[#This Row],[Data]]-$L$7)/365)) -> -14507.619 | R18: =IF(Table48[[#This Row],[Column1]]<=$M$2,-R$3,0)*((1+$I$5)^((Table48[[#This Row],[Data]]-$L$7)/365)) -> -406.06961 | S18: =IF(Table48[[#This Row],[Column1]]<=$M$2,-S$3,0)*((1+$I$5)^((Table48[[#This Row],[Data]]-$L$7)/365)) -> -1815.1705 | T18: =IF(Table48[[#This Row],[Column1]]<=$M$2,-T$3,0)*((1+$I$5)^((Table48[[#This Row],[Data]]-$L$7)/365)) -> -2092.7342 | U18: =IF(Table48[[#This Row],[Column1]]<=$M$2,-U$3,0)*((1+$I$5)^((Table48[[#This Row],[Data]]-$L$7)/365)) -> -3461.976 | V18: =SUM(Table48[[#This Row],[ICMS - Parcelamento]:[IPTU]]) -> -88216.535 | W18: Dívida Tributária | X18: =X17+1 -> 11 | Y18: =SUM(Table48[[#This Row],[ICMS - Parcelamento]:[INSS - Parcelamento]]) -> -56677.148 | Z18: =SUM(Table48[[#This Row],[ICMS]:[IPTU]]) -> -31539.387
A19: IRRF | B19: Não | C19: 45839 | D19: 45889 | I19: 86683.87 | L19: =EDATE(L18,1) -> 46266 | M19: =-$H$25*(1+$I$5)^(YEARFRAC(M$4,Table48[[#This Row],[Data]])) -> -35957.677 | N19: =-$H$26*(1+$I$5)^(YEARFRAC(N$4,Table48[[#This Row],[Data]])) -> -1927.8646 | O19: =-$H$27*(1+$I$5)^(YEARFRAC(O$4,Table48[[#This Row],[Data]])) -> -19455.574 | P19: =IF(Table48[[#This Row],[Column1]]<=$M$2,-P$3,0)*((1+$I$5)^((Table48[[#This Row],[Data]]-$L$7)/365)) -> -9366.3406 | Q19: =IF(Table48[[#This Row],[Column1]]<=$M$2,-Q$3,0)*((1+$I$5)^((Table48[[#This Row],[Data]]-$L$7)/365)) -> -14680.854 | R19: =IF(Table48[[#This Row],[Column1]]<=$M$2,-R$3,0)*((1+$I$5)^((Table48[[#This Row],[Data]]-$L$7)/365)) -> -410.91846 | S19: =IF(Table48[[#This Row],[Column1]]<=$M$2,-S$3,0)*((1+$I$5)^((Table48[[#This Row],[Data]]-$L$7)/365)) -> -1836.8453 | T19: =IF(Table48[[#This Row],[Column1]]<=$M$2,-T$3,0)*((1+$I$5)^((Table48[[#This Row],[Data]]-$L$7)/365)) -> -2117.7234 | U19: =IF(Table48[[#This Row],[Column1]]<=$M$2,-U$3,0)*((1+$I$5)^((Table48[[#This Row],[Data]]-$L$7)/365)) -> -3503.3151 | V19: =SUM(Table48[[#This Row],[ICMS - Parcelamento]:[IPTU]]) -> -89257.113 | W19: Dívida Tributária | X19: =X18+1 -> 12 | Y19: =SUM(Table48[[#This Row],[ICMS - Parcelamento]:[INSS - Parcelamento]]) -> -57341.116 | Z19: =SUM(Table48[[#This Row],[ICMS]:[IPTU]]) -> -31915.997
A20: IPTU | B20: Não | D20: 45889 | I20: 30463.61 | L20: =EDATE(L19,1) -> 46296 | M20: =-$H$25*(1+$I$5)^(YEARFRAC(M$4,Table48[[#This Row],[Data]])) -> -36378.918 | N20: =-$H$26*(1+$I$5)^(YEARFRAC(N$4,Table48[[#This Row],[Data]])) -> -1950.4494 | O20: =-$H$27*(1+$I$5)^(YEARFRAC(O$4,Table48[[#This Row],[Data]])) -> -19683.495 | P20: =IF(Table48[[#This Row],[Column1]]<=$M$2,-P$3,0)*((1+$I$5)^((Table48[[#This Row],[Data]]-$L$7)/365)) -> -9474.5548 | Q20: =IF(Table48[[#This Row],[Column1]]<=$M$2,-Q$3,0)*((1+$I$5)^((Table48[[#This Row],[Data]]-$L$7)/365)) -> -14850.469 | R20: =IF(Table48[[#This Row],[Column1]]<=$M$2,-R$3,0)*((1+$I$5)^((Table48[[#This Row],[Data]]-$L$7)/365)) -> -415.66601 | S20: =IF(Table48[[#This Row],[Column1]]<=$M$2,-S$3,0)*((1+$I$5)^((Table48[[#This Row],[Data]]-$L$7)/365)) -> -1858.0673 | T20: =IF(Table48[[#This Row],[Column1]]<=$M$2,-T$3,0)*((1+$I$5)^((Table48[[#This Row],[Data]]-$L$7)/365)) -> -2142.1905 | U20: =IF(Table48[[#This Row],[Column1]]<=$M$2,-U$3,0)*((1+$I$5)^((Table48[[#This Row],[Data]]-$L$7)/365)) -> -3543.7908 | V20: =SUM(Table48[[#This Row],[ICMS - Parcelamento]:[IPTU]]) -> -90297.601 | W20: Dívida Tributária | X20: =X19+1 -> 13 | Y20: =SUM(Table48[[#This Row],[ICMS - Parcelamento]:[INSS - Parcelamento]]) -> -58012.862 | Z20: =SUM(Table48[[#This Row],[ICMS]:[IPTU]]) -> -32284.739
I21: =SUM(I8:I20) -> 1387652 | L21: =EDATE(L20,1) -> 46327 | M21: =-$H$25*(1+$I$5)^(YEARFRAC(M$4,Table48[[#This Row],[Data]])) -> -36805.094 | N21: =-$H$26*(1+$I$5)^(YEARFRAC(N$4,Table48[[#This Row],[Data]])) -> -1973.2987 | O21: =-$H$27*(1+$I$5)^(YEARFRAC(O$4,Table48[[#This Row],[Data]])) -> -19914.085 | P21: =IF(Table48[[#This Row],[Column1]]<=$M$2,-P$3,0)*((1+$I$5)^((Table48[[#This Row],[Data]]-$L$7)/365)) -> -9587.6897 | Q21: =IF(Table48[[#This Row],[Column1]]<=$M$2,-Q$3,0)*((1+$I$5)^((Table48[[#This Row],[Data]]-$L$7)/365)) -> -15027.798 | R21: =IF(Table48[[#This Row],[Column1]]<=$M$2,-R$3,0)*((1+$I$5)^((Table48[[#This Row],[Data]]-$L$7)/365)) -> -420.62945 | S21: =IF(Table48[[#This Row],[Column1]]<=$M$2,-S$3,0)*((1+$I$5)^((Table48[[#This Row],[Data]]-$L$7)/365)) -> -1880.2544 | T21: =IF(Table48[[#This Row],[Column1]]<=$M$2,-T$3,0)*((1+$I$5)^((Table48[[#This Row],[Data]]-$L$7)/365)) -> -2167.7703 | U21: =IF(Table48[[#This Row],[Column1]]<=$M$2,-U$3,0)*((1+$I$5)^((Table48[[#This Row],[Data]]-$L$7)/365)) -> -3586.1069 | V21: =SUM(Table48[[#This Row],[ICMS - Parcelamento]:[IPTU]]) -> -91362.727 | W21: Dívida Tributária | X21: =X20+1 -> 14 | Y21: =SUM(Table48[[#This Row],[ICMS - Parcelamento]:[INSS - Parcelamento]]) -> -58692.478 | Z21: =SUM(Table48[[#This Row],[ICMS]:[IPTU]]) -> -32670.248
L22: =EDATE(L21,1) -> 46357 | M22: =-$H$25*(1+$I$5)^(YEARFRAC(M$4,Table48[[#This Row],[Data]])) -> -37236.263 | N22: =-$H$26*(1+$I$5)^(YEARFRAC(N$4,Table48[[#This Row],[Data]])) -> -1996.4158 | O22: =-$H$27*(1+$I$5)^(YEARFRAC(O$4,Table48[[#This Row],[Data]])) -> -20147.377 | P22: =IF(Table48[[#This Row],[Column1]]<=$M$2,-P$3,0)*((1+$I$5)^((Table48[[#This Row],[Data]]-$L$7)/365)) -> -9698.4612 | Q22: =IF(Table48[[#This Row],[Column1]]<=$M$2,-Q$3,0)*((1+$I$5)^((Table48[[#This Row],[Data]]-$L$7)/365)) -> -15201.421 | R22: =IF(Table48[[#This Row],[Column1]]<=$M$2,-R$3,0)*((1+$I$5)^((Table48[[#This Row],[Data]]-$L$7)/365)) -> -425.4892 | S22: =IF(Table48[[#This Row],[Column1]]<=$M$2,-S$3,0)*((1+$I$5)^((Table48[[#This Row],[Data]]-$L$7)/365)) -> -1901.9779 | T22: =IF(Table48[[#This Row],[Column1]]<=$M$2,-T$3,0)*((1+$I$5)^((Table48[[#This Row],[Data]]-$L$7)/365)) -> -2192.8156 | U22: =IF(Table48[[#This Row],[Column1]]<=$M$2,-U$3,0)*((1+$I$5)^((Table48[[#This Row],[Data]]-$L$7)/365)) -> -3627.539 | V22: =SUM(Table48[[#This Row],[ICMS - Parcelamento]:[IPTU]]) -> -92427.76 | W22: Dívida Tributária | X22: =X21+1 -> 15 | Y22: =SUM(Table48[[#This Row],[ICMS - Parcelamento]:[INSS - Parcelamento]]) -> -59380.056 | Z22: =SUM(Table48[[#This Row],[ICMS]:[IPTU]]) -> -33047.704
A23: PARCELAMENTO DE TRIBUTOS | D23: =E26*H26 -> 39292.08 | L23: =EDATE(L22,1) -> 46388 | M23: =-$H$25*(1+$I$5)^(YEARFRAC(M$4,Table48[[#This Row],[Data]])) -> -37672.483 | N23: =-$H$26*(1+$I$5)^(YEARFRAC(N$4,Table48[[#This Row],[Data]])) -> -2019.8036 | O23: =-$H$27*(1+$I$5)^(YEARFRAC(O$4,Table48[[#This Row],[Data]])) -> -20383.402 | P23: =IF(Table48[[#This Row],[Column1]]<=$M$2,-P$3,0)*((1+$I$5)^((Table48[[#This Row],[Data]]-$L$7)/365)) -> -9814.2698 | Q23: =IF(Table48[[#This Row],[Column1]]<=$M$2,-Q$3,0)*((1+$I$5)^((Table48[[#This Row],[Data]]-$L$7)/365)) -> -15382.94 | R23: =IF(Table48[[#This Row],[Column1]]<=$M$2,-R$3,0)*((1+$I$5)^((Table48[[#This Row],[Data]]-$L$7)/365)) -> -430.56993 | S23: =IF(Table48[[#This Row],[Column1]]<=$M$2,-S$3,0)*((1+$I$5)^((Table48[[#This Row],[Data]]-$L$7)/365)) -> -1924.6893 | T23: =IF(Table48[[#This Row],[Column1]]<=$M$2,-T$3,0)*((1+$I$5)^((Table48[[#This Row],[Data]]-$L$7)/365)) -> -2218.9999 | U23: =IF(Table48[[#This Row],[Column1]]<=$M$2,-U$3,0)*((1+$I$5)^((Table48[[#This Row],[Data]]-$L$7)/365)) -> -3670.8552 | V23: =SUM(Table48[[#This Row],[ICMS - Parcelamento]:[IPTU]]) -> -93518.013 | W23: Dívida Tributária | X23: =X22+1 -> 16 | Y23: =SUM(Table48[[#This Row],[ICMS - Parcelamento]:[INSS - Parcelamento]]) -> -60075.688 | Z23: =SUM(Table48[[#This Row],[ICMS]:[IPTU]]) -> -33442.324
A24: Natureza | B24: Data Parc. | C24: Tipologia | D24: Valor Original | E24: Total Parcelas | F24: Quitadas | G24: Vencidas | H24: Valor da Parcela | I24: Saldo Quitação | L24: =EDATE(L23,1) -> 46419 | M24: =-$H$25*(1+$I$5)^(YEARFRAC(M$4,Table48[[#This Row],[Data]])) -> -38113.813 | N24: =-$H$26*(1+$I$5)^(YEARFRAC(N$4,Table48[[#This Row],[Data]])) -> -2043.4654 | O24: =-$H$27*(1+$I$5)^(YEARFRAC(O$4,Table48[[#This Row],[Data]])) -> -20622.192 | P24: =IF(Table48[[#This Row],[Column1]]<=$M$2,-P$3,0)*((1+$I$5)^((Table48[[#This Row],[Data]]-$L$7)/365)) -> -9931.4612 | Q24: =IF(Table48[[#This Row],[Column1]]<=$M$2,-Q$3,0)*((1+$I$5)^((Table48[[#This Row],[Data]]-$L$7)/365)) -> -15566.627 | R24: =IF(Table48[[#This Row],[Column1]]<=$M$2,-R$3,0)*((1+$I$5)^((Table48[[#This Row],[Data]]-$L$7)/365)) -> -435.71133 | S24: =IF(Table48[[#This Row],[Column1]]<=$M$2,-S$3,0)*((1+$I$5)^((Table48[[#This Row],[Data]]-$L$7)/365)) -> -1947.6719 | T24: =IF(Table48[[#This Row],[Column1]]<=$M$2,-T$3,0)*((1+$I$5)^((Table48[[#This Row],[Data]]-$L$7)/365)) -> -2245.4968 | U24: =IF(Table48[[#This Row],[Column1]]<=$M$2,-U$3,0)*((1+$I$5)^((Table48[[#This Row],[Data]]-$L$7)/365)) -> -3714.6886 | V24: =SUM(Table48[[#This Row],[ICMS - Parcelamento]:[IPTU]]) -> -94621.127 | W24: Dívida Tributária | X24: =X23+1 -> 17 | Y24: =SUM(Table48[[#This Row],[ICMS - Parcelamento]:[INSS - Parcelamento]]) -> -60779.47 | Z24: =SUM(Table48[[#This Row],[ICMS]:[IPTU]]) -> -33841.657
A25: ICMS Parcelamento | B25: 45833 | C25: Divida Ativa | D25: 1099000 | E25: 36 | F25: 1 | G25: 1 | H25: 30535.77 | I25: =D25-30248.04 -> 1068751.9 | L25: =EDATE(L24,1) -> 46447 | M25: =-$H$25*(1+$I$5)^(YEARFRAC(M$4,Table48[[#This Row],[Data]])) -> -38560.313 | N25: =-$H$26*(1+$I$5)^(YEARFRAC(N$4,Table48[[#This Row],[Data]])) -> -2067.4045 | O25: =-$H$27*(1+$I$5)^(YEARFRAC(O$4,Table48[[#This Row],[Data]])) -> -20863.779 | P25: =IF(Table48[[#This Row],[Column1]]<=$M$2,-P$3,0)*((1+$I$5)^((Table48[[#This Row],[Data]]-$L$7)/365)) -> -10038.514 | Q25: =IF(Table48[[#This Row],[Column1]]<=$M$2,-Q$3,0)*((1+$I$5)^((Table48[[#This Row],[Data]]-$L$7)/365)) -> -15734.422 | R25: =IF(Table48[[#This Row],[Column1]]<=$M$2,-R$3,0)*((1+$I$5)^((Table48[[#This Row],[Data]]-$L$7)/365)) -> -440.40793 | S25: =IF(Table48[[#This Row],[Column1]]<=$M$2,-S$3,0)*((1+$I$5)^((Table48[[#This Row],[Data]]-$L$7)/365)) -> -1968.6661 | T25: =IF(Table48[[#This Row],[Column1]]<=$M$2,-T$3,0)*((1+$I$5)^((Table48[[#This Row],[Data]]-$L$7)/365)) -> -2269.7013 | U25: =IF(Table48[[#This Row],[Column1]]<=$M$2,-U$3,0)*((1+$I$5)^((Table48[[#This Row],[Data]]-$L$7)/365)) -> -3754.7298 | V25: =SUM(Table48[[#This Row],[ICMS - Parcelamento]:[IPTU]]) -> -95697.937 | W25: Dívida Tributária | X25: =X24+1 -> 18 | Y25: =SUM(Table48[[#This Row],[ICMS - Parcelamento]:[INSS - Parcelamento]]) -> -61491.496 | Z25: =SUM(Table48[[#This Row],[ICMS]:[IPTU]]) -> -34206.441
A26: ICMS Parcelamento | B26: 45833 | C26: Normal | D26: 39660.54 | E26: 24 | F26: 1 | G26: 1 | H26: 1637.17 | I26: =D26-1637.17 -> 38023.37 | L26: =EDATE(L25,1) -> 46478 | M26: =-$H$25*(1+$I$5)^(YEARFRAC(M$4,Table48[[#This Row],[Data]])) -> -39012.044 | N26: =-$H$26*(1+$I$5)^(YEARFRAC(N$4,Table48[[#This Row],[Data]])) -> -2091.6239 | O26: =-$H$27*(1+$I$5)^(YEARFRAC(O$4,Table48[[#This Row],[Data]])) -> -21108.197 | P26: =IF(Table48[[#This Row],[Column1]]<=$M$2,-P$3,0)*((1+$I$5)^((Table48[[#This Row],[Data]]-$L$7)/365)) -> -10158.383 | Q26: =IF(Table48[[#This Row],[Column1]]<=$M$2,-Q$3,0)*((1+$I$5)^((Table48[[#This Row],[Data]]-$L$7)/365)) -> -15922.305 | R26: =IF(Table48[[#This Row],[Column1]]<=$M$2,-R$3,0)*((1+$I$5)^((Table48[[#This Row],[Data]]-$L$7)/365)) -> -445.66681 | S26: =IF(Table48[[#This Row],[Column1]]<=$M$2,-S$3,0)*((1+$I$5)^((Table48[[#This Row],[Data]]-$L$7)/365)) -> -1992.1738 | T26: =IF(Table48[[#This Row],[Column1]]<=$M$2,-T$3,0)*((1+$I$5)^((Table48[[#This Row],[Data]]-$L$7)/365)) -> -2296.8036 | U26: =IF(Table48[[#This Row],[Column1]]<=$M$2,-U$3,0)*((1+$I$5)^((Table48[[#This Row],[Data]]-$L$7)/365)) -> -3799.5647 | V26: =SUM(Table48[[#This Row],[ICMS - Parcelamento]:[IPTU]]) -> -96826.761 | W26: Dívida Tributária | X26: =X25+1 -> 19 | Y26: =SUM(Table48[[#This Row],[ICMS - Parcelamento]:[INSS - Parcelamento]]) -> -62211.864 | Z26: =SUM(Table48[[#This Row],[ICMS]:[IPTU]]) -> -34614.897
A27: INSS Parcelamento | B27: 45832 | C27: Normal | D27: 1083105.9 | E27: 60 | F27: 1 | G27: 1 | H27: 16521.95 | I27: =D27-108310.59 -> 974795.34 | L27: =EDATE(L26,1) -> 46508 | M27: =-$H$25*(1+$I$5)^(YEARFRAC(M$4,Table48[[#This Row],[Data]])) -> -39469.067 | N27: =-$H$26*(1+$I$5)^(YEARFRAC(N$4,Table48[[#This Row],[Data]])) -> -2116.1271 | O27: =-$H$27*(1+$I$5)^(YEARFRAC(O$4,Table48[[#This Row],[Data]])) -> -21355.477 | P27: =IF(Table48[[#This Row],[Column1]]<=$M$2,-P$3,0)*((1+$I$5)^((Table48[[#This Row],[Data]]-$L$7)/365)) -> -10275.748 | Q27: =IF(Table48[[#This Row],[Column1]]<=$M$2,-Q$3,0)*((1+$I$5)^((Table48[[#This Row],[Data]]-$L$7)/365)) -> -16106.264 | R27: =IF(Table48[[#This Row],[Column1]]<=$M$2,-R$3,0)*((1+$I$5)^((Table48[[#This Row],[Data]]-$L$7)/365)) -> -450.81582 | S27: =IF(Table48[[#This Row],[Column1]]<=$M$2,-S$3,0)*((1+$I$5)^((Table48[[#This Row],[Data]]-$L$7)/365)) -> -2015.1904 | T27: =IF(Table48[[#This Row],[Column1]]<=$M$2,-T$3,0)*((1+$I$5)^((Table48[[#This Row],[Data]]-$L$7)/365)) -> -2323.3398 | U27: =IF(Table48[[#This Row],[Column1]]<=$M$2,-U$3,0)*((1+$I$5)^((Table48[[#This Row],[Data]]-$L$7)/365)) -> -3843.463 | V27: =SUM(Table48[[#This Row],[ICMS - Parcelamento]:[IPTU]]) -> -97955.492 | W27: Dívida Tributária | X27: =X26+1 -> 20 | Y27: =SUM(Table48[[#This Row],[ICMS - Parcelamento]:[INSS - Parcelamento]]) -> -62940.671 | Z27: =SUM(Table48[[#This Row],[ICMS]:[IPTU]]) -> -35014.821
H28: =SUM(H25:H27) -> 48694.89 | I28: =SUM(I25:I27) -> 2081570.7 | L28: =EDATE(L27,1) -> 46539 | M28: =-$H$25*(1+$I$5)^(YEARFRAC(M$4,Table48[[#This Row],[Data]])) -> -39931.443 | N28: =-$H$26*(1+$I$5)^(YEARFRAC(N$4,Table48[[#This Row],[Data]])) -> -2140.9174 | O28: =-$H$27*(1+$I$5)^(YEARFRAC(O$4,Table48[[#This Row],[Data]])) -> -21605.655 | P28: =IF(Table48[[#This Row],[Column1]]<=$M$2,-P$3,0)*((1+$I$5)^((Table48[[#This Row],[Data]]-$L$7)/365)) -> -10398.45 | Q28: =IF(Table48[[#This Row],[Column1]]<=$M$2,-Q$3,0)*((1+$I$5)^((Table48[[#This Row],[Data]]-$L$7)/365)) -> -16298.588 | R28: =IF(Table48[[#This Row],[Column1]]<=$M$2,-R$3,0)*((1+$I$5)^((Table48[[#This Row],[Data]]-$L$7)/365)) -> -456.19898 | S28: =IF(Table48[[#This Row],[Column1]]<=$M$2,-S$3,0)*((1+$I$5)^((Table48[[#This Row],[Data]]-$L$7)/365)) -> -2039.2536 | T28: =IF(Table48[[#This Row],[Column1]]<=$M$2,-T$3,0)*((1+$I$5)^((Table48[[#This Row],[Data]]-$L$7)/365)) -> -2351.0826 | U28: =IF(Table48[[#This Row],[Column1]]<=$M$2,-U$3,0)*((1+$I$5)^((Table48[[#This Row],[Data]]-$L$7)/365)) -> -3889.3575 | V28: =SUM(Table48[[#This Row],[ICMS - Parcelamento]:[IPTU]]) -> -99110.946 | W28: Dívida Tributária | X28: =X27+1 -> 21 | Y28: =SUM(Table48[[#This Row],[ICMS - Parcelamento]:[INSS - Parcelamento]]) -> -63678.016 | Z28: =SUM(Table48[[#This Row],[ICMS]:[IPTU]]) -> -35432.93
L29: =EDATE(L28,1) -> 46569 | M29: =-$H$25*(1+$I$5)^(YEARFRAC(M$4,Table48[[#This Row],[Data]])) -> -40399.237 | O29: =-$H$27*(1+$I$5)^(YEARFRAC(O$4,Table48[[#This Row],[Data]])) -> -21858.763 | P29: =IF(Table48[[#This Row],[Column1]]<=$M$2,-P$3,0)*((1+$I$5)^((Table48[[#This Row],[Data]]-$L$7)/365)) -> -10518.589 | Q29: =IF(Table48[[#This Row],[Column1]]<=$M$2,-Q$3,0)*((1+$I$5)^((Table48[[#This Row],[Data]]-$L$7)/365)) -> -16486.894 | R29: =IF(Table48[[#This Row],[Column1]]<=$M$2,-R$3,0)*((1+$I$5)^((Table48[[#This Row],[Data]]-$L$7)/365)) -> -461.46968 | S29: =IF(Table48[[#This Row],[Column1]]<=$M$2,-S$3,0)*((1+$I$5)^((Table48[[#This Row],[Data]]-$L$7)/365)) -> -2062.8142 | T29: =IF(Table48[[#This Row],[Column1]]<=$M$2,-T$3,0)*((1+$I$5)^((Table48[[#This Row],[Data]]-$L$7)/365)) -> -2378.2459 | U29: =IF(Table48[[#This Row],[Column1]]<=$M$2,-U$3,0)*((1+$I$5)^((Table48[[#This Row],[Data]]-$L$7)/365)) -> -3934.2933 | V29: =SUM(Table48[[#This Row],[ICMS - Parcelamento]:[IPTU]]) -> -98100.305 | W29: Dívida Tributária | X29: =X28+1 -> 22 | Y29: =SUM(Table48[[#This Row],[ICMS - Parcelamento]:[INSS - Parcelamento]]) -> -62258 | Z29: =SUM(Table48[[#This Row],[ICMS]:[IPTU]]) -> -35842.305
L30: =EDATE(L29,1) -> 46600 | M30: =-$H$25*(1+$I$5)^(YEARFRAC(M$4,Table48[[#This Row],[Data]])) -> -40872.511 | O30: =-$H$27*(1+$I$5)^(YEARFRAC(O$4,Table48[[#This Row],[Data]])) -> -22114.837 | P30: =IF(Table48[[#This Row],[Column1]]<=$M$2,-P$3,0)*((1+$I$5)^((Table48[[#This Row],[Data]]-$L$7)/365)) -> -10644.19 | Q30: =IF(Table48[[#This Row],[Column1]]<=$M$2,-Q$3,0)*((1+$I$5)^((Table48[[#This Row],[Data]]-$L$7)/365)) -> -16683.762 | R30: =IF(Table48[[#This Row],[Column1]]<=$M$2,-R$3,0)*((1+$I$5)^((Table48[[#This Row],[Data]]-$L$7)/365)) -> -466.98006 | S30: =IF(Table48[[#This Row],[Column1]]<=$M$2,-S$3,0)*((1+$I$5)^((Table48[[#This Row],[Data]]-$L$7)/365)) -> -2087.4461 | T30: =IF(Table48[[#This Row],[Column1]]<=$M$2,-T$3,0)*((1+$I$5)^((Table48[[#This Row],[Data]]-$L$7)/365)) -> -2406.6443 | U30: =IF(Table48[[#This Row],[Column1]]<=$M$2,-U$3,0)*((1+$I$5)^((Table48[[#This Row],[Data]]-$L$7)/365)) -> -3981.2724 | V30: =SUM(Table48[[#This Row],[ICMS - Parcelamento]:[IPTU]]) -> -99257.643 | W30: Dívida Tributária | X30: =X29+1 -> 23 | Y30: =SUM(Table48[[#This Row],[ICMS - Parcelamento]:[INSS - Parcelamento]]) -> -62987.348 | Z30: =SUM(Table48[[#This Row],[ICMS]:[IPTU]]) -> -36270.295
L31: =EDATE(L30,1) -> 46631 | M31: =-$H$25*(1+$I$5)^(YEARFRAC(M$4,Table48[[#This Row],[Data]])) -> -41351.329 | O31: =-$H$27*(1+$I$5)^(YEARFRAC(O$4,Table48[[#This Row],[Data]])) -> -22373.91 | P31: =IF(Table48[[#This Row],[Column1]]<=$M$2,-P$3,0)*((1+$I$5)^((Table48[[#This Row],[Data]]-$L$7)/365)) -> -10771.292 | Q31: =IF(Table48[[#This Row],[Column1]]<=$M$2,-Q$3,0)*((1+$I$5)^((Table48[[#This Row],[Data]]-$L$7)/365)) -> -16882.982 | R31: =IF(Table48[[#This Row],[Column1]]<=$M$2,-R$3,0)*((1+$I$5)^((Table48[[#This Row],[Data]]-$L$7)/365)) -> -472.55623 | S31: =IF(Table48[[#This Row],[Column1]]<=$M$2,-S$3,0)*((1+$I$5)^((Table48[[#This Row],[Data]]-$L$7)/365)) -> -2112.3721 | T31: =IF(Table48[[#This Row],[Column1]]<=$M$2,-T$3,0)*((1+$I$5)^((Table48[[#This Row],[Data]]-$L$7)/365)) -> -2435.3819 | U31: =IF(Table48[[#This Row],[Column1]]<=$M$2,-U$3,0)*((1+$I$5)^((Table48[[#This Row],[Data]]-$L$7)/365)) -> -4028.8124 | V31: =SUM(Table48[[#This Row],[ICMS - Parcelamento]:[IPTU]]) -> -100428.64 | W31: Dívida Tributária | X31: =X30+1 -> 24 | Y31: =SUM(Table48[[#This Row],[ICMS - Parcelamento]:[INSS - Parcelamento]]) -> -63725.239 | Z31: =SUM(Table48[[#This Row],[ICMS]:[IPTU]]) -> -36703.396
A32: Resumo da negociação 25/06/2025 | L32: =EDATE(L31,1) -> 46661 | M32: =-$H$25*(1+$I$5)^(YEARFRAC(M$4,Table48[[#This Row],[Data]])) -> -41835.756 | O32: =-$H$27*(1+$I$5)^(YEARFRAC(O$4,Table48[[#This Row],[Data]])) -> -22636.019 | P32: =IF(Table48[[#This Row],[Column1]]<=$M$2,-P$3,0)*((1+$I$5)^((Table48[[#This Row],[Data]]-$L$7)/365)) -> -10895.738 | Q32: =IF(Table48[[#This Row],[Column1]]<=$M$2,-Q$3,0)*((1+$I$5)^((Table48[[#This Row],[Data]]-$L$7)/365)) -> -17078.04 | R32: =IF(Table48[[#This Row],[Column1]]<=$M$2,-R$3,0)*((1+$I$5)^((Table48[[#This Row],[Data]]-$L$7)/365)) -> -478.01591 | S32: =IF(Table48[[#This Row],[Column1]]<=$M$2,-S$3,0)*((1+$I$5)^((Table48[[#This Row],[Data]]-$L$7)/365)) -> -2136.7774 | T32: =IF(Table48[[#This Row],[Column1]]<=$M$2,-T$3,0)*((1+$I$5)^((Table48[[#This Row],[Data]]-$L$7)/365)) -> -2463.5191 | U32: =IF(Table48[[#This Row],[Column1]]<=$M$2,-U$3,0)*((1+$I$5)^((Table48[[#This Row],[Data]]-$L$7)/365)) -> -4075.3594 | V32: =SUM(Table48[[#This Row],[ICMS - Parcelamento]:[IPTU]]) -> -101599.22 | W32: Dívida Tributária | X32: =X31+1 -> 25 | Y32: =SUM(Table48[[#This Row],[ICMS - Parcelamento]:[INSS - Parcelamento]]) -> -64471.775 | Z32: =SUM(Table48[[#This Row],[ICMS]:[IPTU]]) -> -37127.449
C33: Entrada | D33: Parcela mensal | E33: Total parcelamento | L33: =EDATE(L32,1) -> 46692 | M33: =-$H$25*(1+$I$5)^(YEARFRAC(M$4,Table48[[#This Row],[Data]])) -> -42325.858 | O33: =-$H$27*(1+$I$5)^(YEARFRAC(O$4,Table48[[#This Row],[Data]])) -> -22901.198 | P33: =IF(Table48[[#This Row],[Column1]]<=$M$2,-P$3,0)*((1+$I$5)^((Table48[[#This Row],[Data]]-$L$7)/365)) -> -11025.843 | Q33: =IF(Table48[[#This Row],[Column1]]<=$M$2,-Q$3,0)*((1+$I$5)^((Table48[[#This Row],[Data]]-$L$7)/365)) -> -17281.967 | R33: =IF(Table48[[#This Row],[Column1]]<=$M$2,-R$3,0)*((1+$I$5)^((Table48[[#This Row],[Data]]-$L$7)/365)) -> -483.72387 | S33: =IF(Table48[[#This Row],[Column1]]<=$M$2,-S$3,0)*((1+$I$5)^((Table48[[#This Row],[Data]]-$L$7)/365)) -> -2162.2925 | T33: =IF(Table48[[#This Row],[Column1]]<=$M$2,-T$3,0)*((1+$I$5)^((Table48[[#This Row],[Data]]-$L$7)/365)) -> -2492.9358 | U33: =IF(Table48[[#This Row],[Column1]]<=$M$2,-U$3,0)*((1+$I$5)^((Table48[[#This Row],[Data]]-$L$7)/365)) -> -4124.0229 | V33: =SUM(Table48[[#This Row],[ICMS - Parcelamento]:[IPTU]]) -> -102797.84 | W33: Dívida Tributária | X33: =X32+1 -> 26 | Y33: =SUM(Table48[[#This Row],[ICMS - Parcelamento]:[INSS - Parcelamento]]) -> -65227.056 | Z33: =SUM(Table48[[#This Row],[ICMS]:[IPTU]]) -> -37570.785
A34: ICMS - DIVIDA ATIVA | B34: 36 | C34: 30248.04 | D34: 30535.77 | E34: 1099000 | L34: =EDATE(L33,1) -> 46722 | M34: =-$H$25*(1+$I$5)^(YEARFRAC(M$4,Table48[[#This Row],[Data]])) -> -42821.702 | O34: =-$H$27*(1+$I$5)^(YEARFRAC(O$4,Table48[[#This Row],[Data]])) -> -23169.484 | P34: =IF(Table48[[#This Row],[Column1]]<=$M$2,-P$3,0)*((1+$I$5)^((Table48[[#This Row],[Data]]-$L$7)/365)) -> -11153.23 | Q34: =IF(Table48[[#This Row],[Column1]]<=$M$2,-Q$3,0)*((1+$I$5)^((Table48[[#This Row],[Data]]-$L$7)/365)) -> -17481.635 | R34: =IF(Table48[[#This Row],[Column1]]<=$M$2,-R$3,0)*((1+$I$5)^((Table48[[#This Row],[Data]]-$L$7)/365)) -> -489.31258 | S34: =IF(Table48[[#This Row],[Column1]]<=$M$2,-S$3,0)*((1+$I$5)^((Table48[[#This Row],[Data]]-$L$7)/365)) -> -2187.2746 | T34: =IF(Table48[[#This Row],[Column1]]<=$M$2,-T$3,0)*((1+$I$5)^((Table48[[#This Row],[Data]]-$L$7)/365)) -> -2521.738 | U34: =IF(Table48[[#This Row],[Column1]]<=$M$2,-U$3,0)*((1+$I$5)^((Table48[[#This Row],[Data]]-$L$7)/365)) -> -4171.6699 | V34: =SUM(Table48[[#This Row],[ICMS - Parcelamento]:[IPTU]]) -> -103996.05 | W34: Dívida Tributária | X34: =X33+1 -> 27 | Y34: =SUM(Table48[[#This Row],[ICMS - Parcelamento]:[INSS - Parcelamento]]) -> -65991.186 | Z34: =SUM(Table48[[#This Row],[ICMS]:[IPTU]]) -> -38004.86
A35: ICMS - 05/2025 | B35: 24 | C35: 1637.17 | D35: 1653.19 | E35: 39660.54 | L35: =EDATE(L34,1) -> 46753 | M35: =-$H$25*(1+$I$5)^(YEARFRAC(M$4,Table48[[#This Row],[Data]])) -> -43323.355 | O35: =-$H$27*(1+$I$5)^(YEARFRAC(O$4,Table48[[#This Row],[Data]])) -> -23440.912 | P35: =IF(Table48[[#This Row],[Column1]]<=$M$2,-P$3,0)*((1+$I$5)^((Table48[[#This Row],[Data]]-$L$7)/365)) -> -11286.41 | Q35: =IF(Table48[[#This Row],[Column1]]<=$M$2,-Q$3,0)*((1+$I$5)^((Table48[[#This Row],[Data]]-$L$7)/365)) -> -17690.381 | R35: =IF(Table48[[#This Row],[Column1]]<=$M$2,-R$3,0)*((1+$I$5)^((Table48[[#This Row],[Data]]-$L$7)/365)) -> -495.15542 | S35: =IF(Table48[[#This Row],[Column1]]<=$M$2,-S$3,0)*((1+$I$5)^((Table48[[#This Row],[Data]]-$L$7)/365)) -> -2213.3927 | T35: =IF(Table48[[#This Row],[Column1]]<=$M$2,-T$3,0)*((1+$I$5)^((Table48[[#This Row],[Data]]-$L$7)/365)) -> -2551.8499 | U35: =IF(Table48[[#This Row],[Column1]]<=$M$2,-U$3,0)*((1+$I$5)^((Table48[[#This Row],[Data]]-$L$7)/365)) -> -4221.4835 | V35: =SUM(Table48[[#This Row],[ICMS - Parcelamento]:[IPTU]]) -> -105222.94 | W35: Dívida Tributária | X35: =X34+1 -> 28 | Y35: =SUM(Table48[[#This Row],[ICMS - Parcelamento]:[INSS - Parcelamento]]) -> -66764.267 | Z35: =SUM(Table48[[#This Row],[ICMS]:[IPTU]]) -> -38458.673
A36: INSS | B36: 60 | C36: 108310.59 | D36: 16521.95 | E36: 1083105.9 | L36: =EDATE(L35,1) -> 46784 | M36: =-$H$25*(1+$I$5)^(YEARFRAC(M$4,Table48[[#This Row],[Data]])) -> -43830.885 | O36: =-$H$27*(1+$I$5)^(YEARFRAC(O$4,Table48[[#This Row],[Data]])) -> -23715.521 | P36: =IF(Table48[[#This Row],[Column1]]<=$M$2,-P$3,0)*((1+$I$5)^((Table48[[#This Row],[Data]]-$L$7)/365)) -> -11421.18 | Q36: =IF(Table48[[#This Row],[Column1]]<=$M$2,-Q$3,0)*((1+$I$5)^((Table48[[#This Row],[Data]]-$L$7)/365)) -> -17901.621 | R36: =IF(Table48[[#This Row],[Column1]]<=$M$2,-R$3,0)*((1+$I$5)^((Table48[[#This Row],[Data]]-$L$7)/365)) -> -501.06803 | S36: =IF(Table48[[#This Row],[Column1]]<=$M$2,-S$3,0)*((1+$I$5)^((Table48[[#This Row],[Data]]-$L$7)/365)) -> -2239.8226 | T36: =IF(Table48[[#This Row],[Column1]]<=$M$2,-T$3,0)*((1+$I$5)^((Table48[[#This Row],[Data]]-$L$7)/365)) -> -2582.3213 | U36: =IF(Table48[[#This Row],[Column1]]<=$M$2,-U$3,0)*((1+$I$5)^((Table48[[#This Row],[Data]]-$L$7)/365)) -> -4271.8919 | V36: =SUM(Table48[[#This Row],[ICMS - Parcelamento]:[IPTU]]) -> -106464.31 | W36: Dívida Tributária | X36: =X35+1 -> 29 | Y36: =SUM(Table48[[#This Row],[ICMS - Parcelamento]:[INSS - Parcelamento]]) -> -67546.405 | Z36: =SUM(Table48[[#This Row],[ICMS]:[IPTU]]) -> -38917.905
A37: TOTAL | C37: 140195.8 | D37: 51933.152 | E37: 2411878.5 | L37: =EDATE(L36,1) -> 46813 | M37: =-$H$25*(1+$I$5)^(YEARFRAC(M$4,Table48[[#This Row],[Data]])) -> -44344.36 | O37: =-$H$27*(1+$I$5)^(YEARFRAC(O$4,Table48[[#This Row],[Data]])) -> -23993.346 | P37: =IF(Table48[[#This Row],[Column1]]<=$M$2,-P$3,0)*((1+$I$5)^((Table48[[#This Row],[Data]]-$L$7)/365)) -> -11548.712 | Q37: =IF(Table48[[#This Row],[Column1]]<=$M$2,-Q$3,0)*((1+$I$5)^((Table48[[#This Row],[Data]]-$L$7)/365)) -> -18101.515 | R37: =IF(Table48[[#This Row],[Column1]]<=$M$2,-R$3,0)*((1+$I$5)^((Table48[[#This Row],[Data]]-$L$7)/365)) -> -506.66309 | S37: =IF(Table48[[#This Row],[Column1]]<=$M$2,-S$3,0)*((1+$I$5)^((Table48[[#This Row],[Data]]-$L$7)/365)) -> -2264.8331 | T37: =IF(Table48[[#This Row],[Column1]]<=$M$2,-T$3,0)*((1+$I$5)^((Table48[[#This Row],[Data]]-$L$7)/365)) -> -2611.1562 | U37: =IF(Table48[[#This Row],[Column1]]<=$M$2,-U$3,0)*((1+$I$5)^((Table48[[#This Row],[Data]]-$L$7)/365)) -> -4319.5929 | V37: =SUM(Table48[[#This Row],[ICMS - Parcelamento]:[IPTU]]) -> -107690.18 | W37: Dívida Tributária | X37: =X36+1 -> 30 | Y37: =SUM(Table48[[#This Row],[ICMS - Parcelamento]:[INSS - Parcelamento]]) -> -68337.706 | Z37: =SUM(Table48[[#This Row],[ICMS]:[IPTU]]) -> -39352.473
L38: =EDATE(L37,1) -> 46844 | M38: =-$H$25*(1+$I$5)^(YEARFRAC(M$4,Table48[[#This Row],[Data]])) -> -44863.85 | O38: =-$H$27*(1+$I$5)^(YEARFRAC(O$4,Table48[[#This Row],[Data]])) -> -24274.426 | P38: =IF(Table48[[#This Row],[Column1]]<=$M$2,-P$3,0)*((1+$I$5)^((Table48[[#This Row],[Data]]-$L$7)/365)) -> -11686.614 | Q38: =IF(Table48[[#This Row],[Column1]]<=$M$2,-Q$3,0)*((1+$I$5)^((Table48[[#This Row],[Data]]-$L$7)/365)) -> -18317.664 | R38: =IF(Table48[[#This Row],[Column1]]<=$M$2,-R$3,0)*((1+$I$5)^((Table48[[#This Row],[Data]]-$L$7)/365)) -> -512.71311 | S38: =IF(Table48[[#This Row],[Column1]]<=$M$2,-S$3,0)*((1+$I$5)^((Table48[[#This Row],[Data]]-$L$7)/365)) -> -2291.8773 | T38: =IF(Table48[[#This Row],[Column1]]<=$M$2,-T$3,0)*((1+$I$5)^((Table48[[#This Row],[Data]]-$L$7)/365)) -> -2642.3358 | U38: =IF(Table48[[#This Row],[Column1]]<=$M$2,-U$3,0)*((1+$I$5)^((Table48[[#This Row],[Data]]-$L$7)/365)) -> -4371.1728 | V38: =SUM(Table48[[#This Row],[ICMS - Parcelamento]:[IPTU]]) -> -108960.65 | W38: Dívida Tributária | X38: =X37+1 -> 31 | Y38: =SUM(Table48[[#This Row],[ICMS - Parcelamento]:[INSS - Parcelamento]]) -> -69138.276 | Z38: =SUM(Table48[[#This Row],[ICMS]:[IPTU]]) -> -39822.377
L39: =EDATE(L38,1) -> 46874 | M39: =-$H$25*(1+$I$5)^(YEARFRAC(M$4,Table48[[#This Row],[Data]])) -> -45389.426 | O39: =-$H$27*(1+$I$5)^(YEARFRAC(O$4,Table48[[#This Row],[Data]])) -> -24558.799 | P39: =IF(Table48[[#This Row],[Column1]]<=$M$2,-P$3,0)*((1+$I$5)^((Table48[[#This Row],[Data]]-$L$7)/365)) -> -11821.636 | Q39: =IF(Table48[[#This Row],[Column1]]<=$M$2,-Q$3,0)*((1+$I$5)^((Table48[[#This Row],[Data]]-$L$7)/365)) -> -18529.297 | R39: =IF(Table48[[#This Row],[Column1]]<=$M$2,-R$3,0)*((1+$I$5)^((Table48[[#This Row],[Data]]-$L$7)/365)) -> -518.63675 | S39: =IF(Table48[[#This Row],[Column1]]<=$M$2,-S$3,0)*((1+$I$5)^((Table48[[#This Row],[Data]]-$L$7)/365)) -> -2318.3565 | T39: =IF(Table48[[#This Row],[Column1]]<=$M$2,-T$3,0)*((1+$I$5)^((Table48[[#This Row],[Data]]-$L$7)/365)) -> -2672.864 | U39: =IF(Table48[[#This Row],[Column1]]<=$M$2,-U$3,0)*((1+$I$5)^((Table48[[#This Row],[Data]]-$L$7)/365)) -> -4421.6752 | V39: =SUM(Table48[[#This Row],[ICMS - Parcelamento]:[IPTU]]) -> -110230.69 | W39: Dívida Tributária | X39: =X38+1 -> 32 | Y39: =SUM(Table48[[#This Row],[ICMS - Parcelamento]:[INSS - Parcelamento]]) -> -69948.225 | Z39: =SUM(Table48[[#This Row],[ICMS]:[IPTU]]) -> -40282.466
L40: =EDATE(L39,1) -> 46905 | O40: =-$H$27*(1+$I$5)^(YEARFRAC(O$4,Table48[[#This Row],[Data]])) -> -24846.503 | P40: =IF(Table48[[#This Row],[Column1]]<=$M$2,-P$3,0)*((1+$I$5)^((Table48[[#This Row],[Data]]-$L$7)/365)) -> -11962.797 | Q40: =IF(Table48[[#This Row],[Column1]]<=$M$2,-Q$3,0)*((1+$I$5)^((Table48[[#This Row],[Data]]-$L$7)/365)) -> -18750.554 | R40: =IF(Table48[[#This Row],[Column1]]<=$M$2,-R$3,0)*((1+$I$5)^((Table48[[#This Row],[Data]]-$L$7)/365)) -> -524.82975 | S40: =IF(Table48[[#This Row],[Column1]]<=$M$2,-S$3,0)*((1+$I$5)^((Table48[[#This Row],[Data]]-$L$7)/365)) -> -2346.0398 | T40: =IF(Table48[[#This Row],[Column1]]<=$M$2,-T$3,0)*((1+$I$5)^((Table48[[#This Row],[Data]]-$L$7)/365)) -> -2704.7805 | U40: =IF(Table48[[#This Row],[Column1]]<=$M$2,-U$3,0)*((1+$I$5)^((Table48[[#This Row],[Data]]-$L$7)/365)) -> -4474.4741 | V40: =SUM(Table48[[#This Row],[ICMS - Parcelamento]:[IPTU]]) -> -65609.979 | W40: Dívida Tributária | X40: =X39+1 -> 33 | Y40: =SUM(Table48[[#This Row],[ICMS - Parcelamento]:[INSS - Parcelamento]]) -> -24846.503 | Z40: =SUM(Table48[[#This Row],[ICMS]:[IPTU]]) -> -40763.476
L41: =EDATE(L40,1) -> 46935 | O41: =-$H$27*(1+$I$5)^(YEARFRAC(O$4,Table48[[#This Row],[Data]])) -> -25137.578 | P41: =IF(Table48[[#This Row],[Column1]]<=$M$2,-P$3,0)*((1+$I$5)^((Table48[[#This Row],[Data]]-$L$7)/365)) -> -12101.01 | Q41: =IF(Table48[[#This Row],[Column1]]<=$M$2,-Q$3,0)*((1+$I$5)^((Table48[[#This Row],[Data]]-$L$7)/365)) -> -18967.189 | R41: =IF(Table48[[#This Row],[Column1]]<=$M$2,-R$3,0)*((1+$I$5)^((Table48[[#This Row],[Data]]-$L$7)/365)) -> -530.89338 | S41: =IF(Table48[[#This Row],[Column1]]<=$M$2,-S$3,0)*((1+$I$5)^((Table48[[#This Row],[Data]]-$L$7)/365)) -> -2373.1448 | T41: =IF(Table48[[#This Row],[Column1]]<=$M$2,-T$3,0)*((1+$I$5)^((Table48[[#This Row],[Data]]-$L$7)/365)) -> -2736.0302 | U41: =IF(Table48[[#This Row],[Column1]]<=$M$2,-U$3,0)*((1+$I$5)^((Table48[[#This Row],[Data]]-$L$7)/365)) -> -4526.17 | V41: =SUM(Table48[[#This Row],[ICMS - Parcelamento]:[IPTU]]) -> -66372.015 | W41: Dívida Tributária | X41: =X40+1 -> 34 | Y41: =SUM(Table48[[#This Row],[ICMS - Parcelamento]:[INSS - Parcelamento]]) -> -25137.578 | Z41: =SUM(Table48[[#This Row],[ICMS]:[IPTU]]) -> -41234.437
L42: =EDATE(L41,1) -> 46966 | O42: =-$H$27*(1+$I$5)^(YEARFRAC(O$4,Table48[[#This Row],[Data]])) -> -25432.063 | P42: =IF(Table48[[#This Row],[Column1]]<=$M$2,-P$3,0)*((1+$I$5)^((Table48[[#This Row],[Data]]-$L$7)/365)) -> -12245.507 | Q42: =IF(Table48[[#This Row],[Column1]]<=$M$2,-Q$3,0)*((1+$I$5)^((Table48[[#This Row],[Data]]-$L$7)/365)) -> -19193.675 | R42: =IF(Table48[[#This Row],[Column1]]<=$M$2,-R$3,0)*((1+$I$5)^((Table48[[#This Row],[Data]]-$L$7)/365)) -> -537.23274 | S42: =IF(Table48[[#This Row],[Column1]]<=$M$2,-S$3,0)*((1+$I$5)^((Table48[[#This Row],[Data]]-$L$7)/365)) -> -2401.4824 | T42: =IF(Table48[[#This Row],[Column1]]<=$M$2,-T$3,0)*((1+$I$5)^((Table48[[#This Row],[Data]]-$L$7)/365)) -> -2768.701 | U42: =IF(Table48[[#This Row],[Column1]]<=$M$2,-U$3,0)*((1+$I$5)^((Table48[[#This Row],[Data]]-$L$7)/365)) -> -4580.2167 | V42: =SUM(Table48[[#This Row],[ICMS - Parcelamento]:[IPTU]]) -> -67158.877 | W42: Dívida Tributária | X42: =X41+1 -> 35 | Y42: =SUM(Table48[[#This Row],[ICMS - Parcelamento]:[INSS - Parcelamento]]) -> -25432.063 | Z42: =SUM(Table48[[#This Row],[ICMS]:[IPTU]]) -> -41726.814
L43: =EDATE(L42,1) -> 46997 | O43: =-$H$27*(1+$I$5)^(YEARFRAC(O$4,Table48[[#This Row],[Data]])) -> -25729.997 | P43: =IF(Table48[[#This Row],[Column1]]<=$M$2,-P$3,0)*((1+$I$5)^((Table48[[#This Row],[Data]]-$L$7)/365)) -> -12391.729 | Q43: =IF(Table48[[#This Row],[Column1]]<=$M$2,-Q$3,0)*((1+$I$5)^((Table48[[#This Row],[Data]]-$L$7)/365)) -> -19422.865 | R43: =IF(Table48[[#This Row],[Column1]]<=$M$2,-R$3,0)*((1+$I$5)^((Table48[[#This Row],[Data]]-$L$7)/365)) -> -543.64779 | S43: =IF(Table48[[#This Row],[Column1]]<=$M$2,-S$3,0)*((1+$I$5)^((Table48[[#This Row],[Data]]-$L$7)/365)) -> -2430.1583 | T43: =IF(Table48[[#This Row],[Column1]]<=$M$2,-T$3,0)*((1+$I$5)^((Table48[[#This Row],[Data]]-$L$7)/365)) -> -2801.7618 | U43: =IF(Table48[[#This Row],[Column1]]<=$M$2,-U$3,0)*((1+$I$5)^((Table48[[#This Row],[Data]]-$L$7)/365)) -> -4634.9087 | V43: =SUM(Table48[[#This Row],[ICMS - Parcelamento]:[IPTU]]) -> -67955.068 | W43: Dívida Tributária | X43: =X42+1 -> 36 | Y43: =SUM(Table48[[#This Row],[ICMS - Parcelamento]:[INSS - Parcelamento]]) -> -25729.997 | Z43: =SUM(Table48[[#This Row],[ICMS]:[IPTU]]) -> -42225.071
L44: =EDATE(L43,1) -> 47027 | O44: =-$H$27*(1+$I$5)^(YEARFRAC(O$4,Table48[[#This Row],[Data]])) -> -26031.422 | P44: =IF(Table48[[#This Row],[Column1]]<=$M$2,-P$3,0)*((1+$I$5)^((Table48[[#This Row],[Data]]-$L$7)/365)) -> -12534.897 | Q44: =IF(Table48[[#This Row],[Column1]]<=$M$2,-Q$3,0)*((1+$I$5)^((Table48[[#This Row],[Data]]-$L$7)/365)) -> -19647.267 | R44: =IF(Table48[[#This Row],[Column1]]<=$M$2,-R$3,0)*((1+$I$5)^((Table48[[#This Row],[Data]]-$L$7)/365)) -> -549.92883 | S44: =IF(Table48[[#This Row],[Column1]]<=$M$2,-S$3,0)*((1+$I$5)^((Table48[[#This Row],[Data]]-$L$7)/365)) -> -2458.2352 | T44: =IF(Table48[[#This Row],[Column1]]<=$M$2,-T$3,0)*((1+$I$5)^((Table48[[#This Row],[Data]]-$L$7)/365)) -> -2834.132 | U44: =IF(Table48[[#This Row],[Column1]]<=$M$2,-U$3,0)*((1+$I$5)^((Table48[[#This Row],[Data]]-$L$7)/365)) -> -4688.4582 | V44: =SUM(Table48[[#This Row],[ICMS - Parcelamento]:[IPTU]]) -> -68744.341 | W44: Dívida Tributária | X44: =X43+1 -> 37 | Y44: =SUM(Table48[[#This Row],[ICMS - Parcelamento]:[INSS - Parcelamento]]) -> -26031.422 | Z44: =SUM(Table48[[#This Row],[ICMS]:[IPTU]]) -> -42712.919
L45: =EDATE(L44,1) -> 47058 | O45: =-$H$27*(1+$I$5)^(YEARFRAC(O$4,Table48[[#This Row],[Data]])) -> -26336.378 | P45: =IF(Table48[[#This Row],[Column1]]<=$M$2,-P$3,0)*((1+$I$5)^((Table48[[#This Row],[Data]]-$L$7)/365)) -> -12684.576 | Q45: =IF(Table48[[#This Row],[Column1]]<=$M$2,-Q$3,0)*((1+$I$5)^((Table48[[#This Row],[Data]]-$L$7)/365)) -> -19881.874 | R45: =IF(Table48[[#This Row],[Column1]]<=$M$2,-R$3,0)*((1+$I$5)^((Table48[[#This Row],[Data]]-$L$7)/365)) -> -556.49549 | S45: =IF(Table48[[#This Row],[Column1]]<=$M$2,-S$3,0)*((1+$I$5)^((Table48[[#This Row],[Data]]-$L$7)/365)) -> -2487.5888 | T45: =IF(Table48[[#This Row],[Column1]]<=$M$2,-T$3,0)*((1+$I$5)^((Table48[[#This Row],[Data]]-$L$7)/365)) -> -2867.9741 | U45: =IF(Table48[[#This Row],[Column1]]<=$M$2,-U$3,0)*((1+$I$5)^((Table48[[#This Row],[Data]]-$L$7)/365)) -> -4744.4427 | V45: =SUM(Table48[[#This Row],[ICMS - Parcelamento]:[IPTU]]) -> -69559.328 | W45: Dívida Tributária | X45: =X44+1 -> 38 | Y45: =SUM(Table48[[#This Row],[ICMS - Parcelamento]:[INSS - Parcelamento]]) -> -26336.378 | Z45: =SUM(Table48[[#This Row],[ICMS]:[IPTU]]) -> -43222.951
L46: =EDATE(L45,1) -> 47088 | O46: =-$H$27*(1+$I$5)^(YEARFRAC(O$4,Table48[[#This Row],[Data]])) -> -26644.906 | P46: =IF(Table48[[#This Row],[Column1]]<=$M$2,-P$3,0)*((1+$I$5)^((Table48[[#This Row],[Data]]-$L$7)/365)) -> -12831.127 | Q46: =IF(Table48[[#This Row],[Column1]]<=$M$2,-Q$3,0)*((1+$I$5)^((Table48[[#This Row],[Data]]-$L$7)/365)) -> -20111.579 | R46: =IF(Table48[[#This Row],[Column1]]<=$M$2,-R$3,0)*((1+$I$5)^((Table48[[#This Row],[Data]]-$L$7)/365)) -> -562.92497 | S46: =IF(Table48[[#This Row],[Column1]]<=$M$2,-S$3,0)*((1+$I$5)^((Table48[[#This Row],[Data]]-$L$7)/365)) -> -2516.3291 | T46: =IF(Table48[[#This Row],[Column1]]<=$M$2,-T$3,0)*((1+$I$5)^((Table48[[#This Row],[Data]]-$L$7)/365)) -> -2901.1093 | U46: =IF(Table48[[#This Row],[Column1]]<=$M$2,-U$3,0)*((1+$I$5)^((Table48[[#This Row],[Data]]-$L$7)/365)) -> -4799.2577 | V46: =SUM(Table48[[#This Row],[ICMS - Parcelamento]:[IPTU]]) -> -70367.234 | W46: Dívida Tributária | X46: =X45+1 -> 39 | Y46: =SUM(Table48[[#This Row],[ICMS - Parcelamento]:[INSS - Parcelamento]]) -> -26644.906 | Z46: =SUM(Table48[[#This Row],[ICMS]:[IPTU]]) -> -43722.328
L47: =EDATE(L46,1) -> 47119 | O47: =-$H$27*(1+$I$5)^(YEARFRAC(O$4,Table48[[#This Row],[Data]])) -> -26957.049 | P47: =IF(Table48[[#This Row],[Column1]]<=$M$2,-P$3,0)*((1+$I$5)^((Table48[[#This Row],[Data]]-$L$7)/365)) -> -12984.343 | Q47: =IF(Table48[[#This Row],[Column1]]<=$M$2,-Q$3,0)*((1+$I$5)^((Table48[[#This Row],[Data]]-$L$7)/365)) -> -20351.73 | R47: =IF(Table48[[#This Row],[Column1]]<=$M$2,-R$3,0)*((1+$I$5)^((Table48[[#This Row],[Data]]-$L$7)/365)) -> -569.64681 | S47: =IF(Table48[[#This Row],[Column1]]<=$M$2,-S$3,0)*((1+$I$5)^((Table48[[#This Row],[Data]]-$L$7)/365)) -> -2546.3764 | T47: =IF(Table48[[#This Row],[Column1]]<=$M$2,-T$3,0)*((1+$I$5)^((Table48[[#This Row],[Data]]-$L$7)/365)) -> -2935.7513 | U47: =IF(Table48[[#This Row],[Column1]]<=$M$2,-U$3,0)*((1+$I$5)^((Table48[[#This Row],[Data]]-$L$7)/365)) -> -4856.5653 | V47: =SUM(Table48[[#This Row],[ICMS - Parcelamento]:[IPTU]]) -> -71201.462 | W47: Dívida Tributária | X47: =X46+1 -> 40 | Y47: =SUM(Table48[[#This Row],[ICMS - Parcelamento]:[INSS - Parcelamento]]) -> -26957.049 | Z47: =SUM(Table48[[#This Row],[ICMS]:[IPTU]]) -> -44244.413
L48: =EDATE(L47,1) -> 47150 | O48: =-$H$27*(1+$I$5)^(YEARFRAC(O$4,Table48[[#This Row],[Data]])) -> -27272.849 | P48: =IF(Table48[[#This Row],[Column1]]<=$M$2,-P$3,0)*((1+$I$5)^((Table48[[#This Row],[Data]]-$L$7)/365)) -> -13139.388 | Q48: =IF(Table48[[#This Row],[Column1]]<=$M$2,-Q$3,0)*((1+$I$5)^((Table48[[#This Row],[Data]]-$L$7)/365)) -> -20594.749 | R48: =IF(Table48[[#This Row],[Column1]]<=$M$2,-R$3,0)*((1+$I$5)^((Table48[[#This Row],[Data]]-$L$7)/365)) -> -576.44892 | S48: =IF(Table48[[#This Row],[Column1]]<=$M$2,-S$3,0)*((1+$I$5)^((Table48[[#This Row],[Data]]-$L$7)/365)) -> -2576.7825 | T48: =IF(Table48[[#This Row],[Column1]]<=$M$2,-T$3,0)*((1+$I$5)^((Table48[[#This Row],[Data]]-$L$7)/365)) -> -2970.8068 | U48: =IF(Table48[[#This Row],[Column1]]<=$M$2,-U$3,0)*((1+$I$5)^((Table48[[#This Row],[Data]]-$L$7)/365)) -> -4914.5571 | V48: =SUM(Table48[[#This Row],[ICMS - Parcelamento]:[IPTU]]) -> -72045.58 | W48: Dívida Tributária | X48: =X47+1 -> 41 | Y48: =SUM(Table48[[#This Row],[ICMS - Parcelamento]:[INSS - Parcelamento]]) -> -27272.849 | Z48: =SUM(Table48[[#This Row],[ICMS]:[IPTU]]) -> -44772.732
L49: =EDATE(L48,1) -> 47178 | O49: =-$H$27*(1+$I$5)^(YEARFRAC(O$4,Table48[[#This Row],[Data]])) -> -27592.348 | P49: =IF(Table48[[#This Row],[Column1]]<=$M$2,-P$3,0)*((1+$I$5)^((Table48[[#This Row],[Data]]-$L$7)/365)) -> -13281.019 | Q49: =IF(Table48[[#This Row],[Column1]]<=$M$2,-Q$3,0)*((1+$I$5)^((Table48[[#This Row],[Data]]-$L$7)/365)) -> -20816.742 | R49: =IF(Table48[[#This Row],[Column1]]<=$M$2,-R$3,0)*((1+$I$5)^((Table48[[#This Row],[Data]]-$L$7)/365)) -> -582.66255 | S49: =IF(Table48[[#This Row],[Column1]]<=$M$2,-S$3,0)*((1+$I$5)^((Table48[[#This Row],[Data]]-$L$7)/365)) -> -2604.558 | T49: =IF(Table48[[#This Row],[Column1]]<=$M$2,-T$3,0)*((1+$I$5)^((Table48[[#This Row],[Data]]-$L$7)/365)) -> -3002.8296 | U49: =IF(Table48[[#This Row],[Column1]]<=$M$2,-U$3,0)*((1+$I$5)^((Table48[[#This Row],[Data]]-$L$7)/365)) -> -4967.5319 | V49: =SUM(Table48[[#This Row],[ICMS - Parcelamento]:[IPTU]]) -> -72847.691 | W49: Dívida Tributária | X49: =X48+1 -> 42 | Y49: =SUM(Table48[[#This Row],[ICMS - Parcelamento]:[INSS - Parcelamento]]) -> -27592.348 | Z49: =SUM(Table48[[#This Row],[ICMS]:[IPTU]]) -> -45255.343
L50: =EDATE(L49,1) -> 47209 | O50: =-$H$27*(1+$I$5)^(YEARFRAC(O$4,Table48[[#This Row],[Data]])) -> -27915.59 | P50: =IF(Table48[[#This Row],[Column1]]<=$M$2,-P$3,0)*((1+$I$5)^((Table48[[#This Row],[Data]]-$L$7)/365)) -> -13439.607 | Q50: =IF(Table48[[#This Row],[Column1]]<=$M$2,-Q$3,0)*((1+$I$5)^((Table48[[#This Row],[Data]]-$L$7)/365)) -> -21065.313 | R50: =IF(Table48[[#This Row],[Column1]]<=$M$2,-R$3,0)*((1+$I$5)^((Table48[[#This Row],[Data]]-$L$7)/365)) -> -589.62008 | S50: =IF(Table48[[#This Row],[Column1]]<=$M$2,-S$3,0)*((1+$I$5)^((Table48[[#This Row],[Data]]-$L$7)/365)) -> -2635.6589 | T50: =IF(Table48[[#This Row],[Column1]]<=$M$2,-T$3,0)*((1+$I$5)^((Table48[[#This Row],[Data]]-$L$7)/365)) -> -3038.6861 | U50: =IF(Table48[[#This Row],[Column1]]<=$M$2,-U$3,0)*((1+$I$5)^((Table48[[#This Row],[Data]]-$L$7)/365)) -> -5026.8488 | V50: =SUM(Table48[[#This Row],[ICMS - Parcelamento]:[IPTU]]) -> -73711.324 | W50: Dívida Tributária | X50: =X49+1 -> 43 | Y50: =SUM(Table48[[#This Row],[ICMS - Parcelamento]:[INSS - Parcelamento]]) -> -27915.59 | Z50: =SUM(Table48[[#This Row],[ICMS]:[IPTU]]) -> -45795.734
L51: =EDATE(L50,1) -> 47239 | O51: =-$H$27*(1+$I$5)^(YEARFRAC(O$4,Table48[[#This Row],[Data]])) -> -28242.619 | P51: =IF(Table48[[#This Row],[Column1]]<=$M$2,-P$3,0)*((1+$I$5)^((Table48[[#This Row],[Data]]-$L$7)/365)) -> -13594.881 | Q51: =IF(Table48[[#This Row],[Column1]]<=$M$2,-Q$3,0)*((1+$I$5)^((Table48[[#This Row],[Data]]-$L$7)/365)) -> -21308.692 | R51: =IF(Table48[[#This Row],[Column1]]<=$M$2,-R$3,0)*((1+$I$5)^((Table48[[#This Row],[Data]]-$L$7)/365)) -> -596.43226 | S51: =IF(Table48[[#This Row],[Column1]]<=$M$2,-S$3,0)*((1+$I$5)^((Table48[[#This Row],[Data]]-$L$7)/365)) -> -2666.11 | T51: =IF(Table48[[#This Row],[Column1]]<=$M$2,-T$3,0)*((1+$I$5)^((Table48[[#This Row],[Data]]-$L$7)/365)) -> -3073.7937 | U51: =IF(Table48[[#This Row],[Column1]]<=$M$2,-U$3,0)*((1+$I$5)^((Table48[[#This Row],[Data]]-$L$7)/365)) -> -5084.9265 | V51: =SUM(Table48[[#This Row],[ICMS - Parcelamento]:[IPTU]]) -> -74567.454 | W51: Dívida Tributária | X51: =X50+1 -> 44 | Y51: =SUM(Table48[[#This Row],[ICMS - Parcelamento]:[INSS - Parcelamento]]) -> -28242.619 | Z51: =SUM(Table48[[#This Row],[ICMS]:[IPTU]]) -> -46324.836
... L63: =EDATE(L62,1) -> 47604 | O63: =-$H$27*(1+$I$5)^(YEARFRAC(O$4,Table48[[#This Row],[Data]])) -> -32479.012 | P63: =IF(Table48[[#This Row],[Column1]]<=$M$2,-P$3,0)*((1+$I$5)^((Table48[[#This Row],[Data]]-$L$7)/365)) -> -15634.114 | Q63: =IF(Table48[[#This Row],[Column1]]<=$M$2,-Q$3,0)*((1+$I$5)^((Table48[[#This Row],[Data]]-$L$7)/365)) -> -24504.996 | R63: =IF(Table48[[#This Row],[Column1]]<=$M$2,-R$3,0)*((1+$I$5)^((Table48[[#This Row],[Data]]-$L$7)/365)) -> -685.8971 | S63: =IF(Table48[[#This Row],[Column1]]<=$M$2,-S$3,0)*((1+$I$5)^((Table48[[#This Row],[Data]]-$L$7)/365)) -> -3066.0265 | T63: =IF(Table48[[#This Row],[Column1]]<=$M$2,-T$3,0)*((1+$I$5)^((Table48[[#This Row],[Data]]-$L$7)/365)) -> -3534.8627 | U63: =IF(Table48[[#This Row],[Column1]]<=$M$2,-U$3,0)*((1+$I$5)^((Table48[[#This Row],[Data]]-$L$7)/365)) -> -5847.6655 | V63: =SUM(Table48[[#This Row],[ICMS - Parcelamento]:[IPTU]]) -> -85752.573 | W63: Dívida Tributária | X63: =X62+1 -> 56 | Y63: =SUM(Table48[[#This Row],[ICMS - Parcelamento]:[INSS - Parcelamento]]) -> -32479.012 | Z63: =SUM(Table48[[#This Row],[ICMS]:[IPTU]]) -> -53273.561
L64: =EDATE(L63,1) -> 47635 | P64: =IF(Table48[[#This Row],[Column1]]<=$M$2,-P$3,0)*((1+$I$5)^((Table48[[#This Row],[Data]]-$L$7)/365)) -> -15820.799 | Q64: =IF(Table48[[#This Row],[Column1]]<=$M$2,-Q$3,0)*((1+$I$5)^((Table48[[#This Row],[Data]]-$L$7)/365)) -> -24797.608 | R64: =IF(Table48[[#This Row],[Column1]]<=$M$2,-R$3,0)*((1+$I$5)^((Table48[[#This Row],[Data]]-$L$7)/365)) -> -694.08735 | S64: =IF(Table48[[#This Row],[Column1]]<=$M$2,-S$3,0)*((1+$I$5)^((Table48[[#This Row],[Data]]-$L$7)/365)) -> -3102.6377 | T64: =IF(Table48[[#This Row],[Column1]]<=$M$2,-T$3,0)*((1+$I$5)^((Table48[[#This Row],[Data]]-$L$7)/365)) -> -3577.0722 | U64: =IF(Table48[[#This Row],[Column1]]<=$M$2,-U$3,0)*((1+$I$5)^((Table48[[#This Row],[Data]]-$L$7)/365)) -> -5917.492 | V64: =SUM(Table48[[#This Row],[ICMS - Parcelamento]:[IPTU]]) -> -53909.696 | W64: Dívida Tributária | X64: =X63+1 -> 57 | Y64: =SUM(Table48[[#This Row],[ICMS - Parcelamento]:[INSS - Parcelamento]]) -> 0 | Z64: =SUM(Table48[[#This Row],[ICMS]:[IPTU]]) -> -53909.696
L65: =EDATE(L64,1) -> 47665 | P65: =IF(Table48[[#This Row],[Column1]]<=$M$2,-P$3,0)*((1+$I$5)^((Table48[[#This Row],[Data]]-$L$7)/365)) -> -16003.585 | Q65: =IF(Table48[[#This Row],[Column1]]<=$M$2,-Q$3,0)*((1+$I$5)^((Table48[[#This Row],[Data]]-$L$7)/365)) -> -25084.107 | R65: =IF(Table48[[#This Row],[Column1]]<=$M$2,-R$3,0)*((1+$I$5)^((Table48[[#This Row],[Data]]-$L$7)/365)) -> -702.1065 | S65: =IF(Table48[[#This Row],[Column1]]<=$M$2,-S$3,0)*((1+$I$5)^((Table48[[#This Row],[Data]]-$L$7)/365)) -> -3138.484 | T65: =IF(Table48[[#This Row],[Column1]]<=$M$2,-T$3,0)*((1+$I$5)^((Table48[[#This Row],[Data]]-$L$7)/365)) -> -3618.4 | U65: =IF(Table48[[#This Row],[Column1]]<=$M$2,-U$3,0)*((1+$I$5)^((Table48[[#This Row],[Data]]-$L$7)/365)) -> -5985.8599 | V65: =SUM(Table48[[#This Row],[ICMS - Parcelamento]:[IPTU]]) -> -54532.543 | W65: Dívida Tributária | X65: =X64+1 -> 58 | Y65: =SUM(Table48[[#This Row],[ICMS - Parcelamento]:[INSS - Parcelamento]]) -> 0 | Z65: =SUM(Table48[[#This Row],[ICMS]:[IPTU]]) -> -54532.543
L66: =EDATE(L65,1) -> 47696 | P66: =IF(Table48[[#This Row],[Column1]]<=$M$2,-P$3,0)*((1+$I$5)^((Table48[[#This Row],[Data]]-$L$7)/365)) -> -16194.683 | Q66: =IF(Table48[[#This Row],[Column1]]<=$M$2,-Q$3,0)*((1+$I$5)^((Table48[[#This Row],[Data]]-$L$7)/365)) -> -25383.635 | R66: =IF(Table48[[#This Row],[Column1]]<=$M$2,-R$3,0)*((1+$I$5)^((Table48[[#This Row],[Data]]-$L$7)/365)) -> -710.49029 | S66: =IF(Table48[[#This Row],[Column1]]<=$M$2,-S$3,0)*((1+$I$5)^((Table48[[#This Row],[Data]]-$L$7)/365)) -> -3175.9604 | T66: =IF(Table48[[#This Row],[Column1]]<=$M$2,-T$3,0)*((1+$I$5)^((Table48[[#This Row],[Data]]-$L$7)/365)) -> -3661.607 | U66: =IF(Table48[[#This Row],[Column1]]<=$M$2,-U$3,0)*((1+$I$5)^((Table48[[#This Row],[Data]]-$L$7)/365)) -> -6057.3366 | V66: =SUM(Table48[[#This Row],[ICMS - Parcelamento]:[IPTU]]) -> -55183.712 | W66: Dívida Tributária | X66: =X65+1 -> 59 | Y66: =SUM(Table48[[#This Row],[ICMS - Parcelamento]:[INSS - Parcelamento]]) -> 0 | Z66: =SUM(Table48[[#This Row],[ICMS]:[IPTU]]) -> -55183.712
L67: =EDATE(L66,1) -> 47727 | P67: =IF(Table48[[#This Row],[Column1]]<=$M$2,-P$3,0)*((1+$I$5)^((Table48[[#This Row],[Data]]-$L$7)/365)) -> -16388.062 | Q67: =IF(Table48[[#This Row],[Column1]]<=$M$2,-Q$3,0)*((1+$I$5)^((Table48[[#This Row],[Data]]-$L$7)/365)) -> -25686.739 | R67: =IF(Table48[[#This Row],[Column1]]<=$M$2,-R$3,0)*((1+$I$5)^((Table48[[#This Row],[Data]]-$L$7)/365)) -> -718.9742 | S67: =IF(Table48[[#This Row],[Column1]]<=$M$2,-S$3,0)*((1+$I$5)^((Table48[[#This Row],[Data]]-$L$7)/365)) -> -3213.8843 | T67: =IF(Table48[[#This Row],[Column1]]<=$M$2,-T$3,0)*((1+$I$5)^((Table48[[#This Row],[Data]]-$L$7)/365)) -> -3705.33 | U67: =IF(Table48[[#This Row],[Column1]]<=$M$2,-U$3,0)*((1+$I$5)^((Table48[[#This Row],[Data]]-$L$7)/365)) -> -6129.6668 | V67: =SUM(Table48[[#This Row],[ICMS - Parcelamento]:[IPTU]]) -> -55842.656 | W67: Dívida Tributária | X67: =X66+1 -> 60 | Y67: =SUM(Table48[[#This Row],[ICMS - Parcelamento]:[INSS - Parcelamento]]) -> 0 | Z67: =SUM(Table48[[#This Row],[ICMS]:[IPTU]]) -> -55842.656
L68: =EDATE(L67,1) -> 47757 | P68: =IF(Table48[[#This Row],[Column1]]<=$M$2,-P$3,0)*((1+$I$5)^((Table48[[#This Row],[Data]]-$L$7)/365)) -> 0 | Q68: =IF(Table48[[#This Row],[Column1]]<=$M$2,-Q$3,0)*((1+$I$5)^((Table48[[#This Row],[Data]]-$L$7)/365)) -> 0 | R68: =IF(Table48[[#This Row],[Column1]]<=$M$2,-R$3,0)*((1+$I$5)^((Table48[[#This Row],[Data]]-$L$7)/365)) -> 0 | S68: =IF(Table48[[#This Row],[Column1]]<=$M$2,-S$3,0)*((1+$I$5)^((Table48[[#This Row],[Data]]-$L$7)/365)) -> 0 | T68: =IF(Table48[[#This Row],[Column1]]<=$M$2,-T$3,0)*((1+$I$5)^((Table48[[#This Row],[Data]]-$L$7)/365)) -> 0 | U68: =IF(Table48[[#This Row],[Column1]]<=$M$2,-U$3,0)*((1+$I$5)^((Table48[[#This Row],[Data]]-$L$7)/365)) -> 0 | V68: =SUM(Table48[[#This Row],[ICMS - Parcelamento]:[IPTU]]) -> 0 | W68: Dívida Tributária | X68: =X67+1 -> 61 | Y68: =SUM(Table48[[#This Row],[ICMS - Parcelamento]:[INSS - Parcelamento]]) -> 0 | Z68: =SUM(Table48[[#This Row],[ICMS]:[IPTU]]) -> 0

Sheet Aging_fornecedores
B1: Data de atualização: | D1: 45887 | BM1: SCHNEIDER ELECTRIC
B3: Ref. Documento: | D3: 27 - Fornecedores vencidos até 15_08_2025 | BM3: ELETROPOLL PAINEIS IND C LTDA
B4: Ref. Documento: | D4: 27A - Fornecedores a vencer 17_08_2025 a 31_12_2026 | W4: Fornecedores Vencidos
W5: Fornecedores a Vencer | BM5: ALVIN ALONSO FRANCIS LOPEZ 012
AB6: Análises dos valores a pagar aos fornecedores
H7: =SUBTOTAL(9,H10:H408) -> 0 | I7: =SUBTOTAL(9,I10:I408) -> 2222705.7 | J7: =SUBTOTAL(9,J10:J408) -> 1862580.3 | K7: =SUBTOTAL(9,K10:K408) -> 411089.82 | L7: =SUBTOTAL(9,L10:L408) -> 104028.69 | M7: =SUBTOTAL(9,M10:M408) -> 25039.46 | N7: =SUBTOTAL(9,N10:N408) -> 3930.96 | O7: =SUBTOTAL(9,O10:O408) -> 10661.54 | AB7: 64% das dívidas dos fornecedores vão vencer em até 30 dias ou já venceram até 2 meses | BM7: ACOTUBO INDUSTRIA E COMERCIO L
C8: Referência | D8: 45938 | AB8: 80% das dívidas dos fornecedores estão estão em 101 de 398 fornecedores (25%) | AQ8: Fornecedores Tóxicos | BM8: OPERA FUNDO DE INVESTIMENTOS E
H9: Vencidos | L9: A vencer | AQ9: VITAL INDUSTRIA C ACO LTDA | BM9: WEG EQUIPAMENTOS ELETRICOS SA
B10: # | C10: Fornecedores | D10: Valor Pendente | E10: % | F10: % Acum. | G10: Grupo | H10: >180 | I10: 60-180 | J10: 30-60 | K10: 0-30 | L10: 0-30 | M10: 30-60 | N10: 60-90 | O10: >90 | P10: Vencidos | R10: Valor Pendente | S10: DataVcto | T10: Classificação | U10: Classificação2 | V10: Nome | W10: Categoria Título | X10: Nova Data | Y10: Título Protestado? | Z10: Grupo | AB10: Períodos | AC10: Sum of Valor Pendente | AG10: # | AH10: Fornecedores | AM10: Intervalo | AO10: Nomeclatura | AQ10: UVW COMPUTACAO GRAFICA LTDA ME | BM10: ACSO CENTRAL DE SERVICO DO A
B11: 1 | C11: RONAFER INDUSTRIA E COMERCIO D | D11: =SUMIFS(R:R,V:V,C11) -> 242999.88 | E11: =D11/SUM(D:D) -> 0.051330579 | F11: =E11 -> 0.051330579 | G11: A | H11: =SUMIFS(R:R,V:V,C11,U:U,$AO$18) -> 0 | I11: =SUMIFS(R:R,V:V,C11,U:U,$AO$17) -> 215126.38 | J11: =SUMIFS(R:R,V:V,C11,U:U,$AO$16) -> 27873.5 | K11: =SUMIFS(R:R,V:V,C11,U:U,$AO$15) -> 0 | L11: =SUMIFS(R:R,V:V,C11,U:U,$AO$14) -> 0 | M11: =SUMIFS(R:R,V:V,C11,U:U,$AO$13) -> 0 | N11: =SUMIFS(R:R,V:V,C11,U:U,$AO$12) -> 0 | O11: =SUMIFS(R:R,V:V,C11,U:U,$AO$11) -> 0 | P11: =SUM(H11:K11) -> 242999.88 | R11: 435 | S11: 45911 | T11: -27 | U11: 4. Vencido: 0-30 | V11: MVA | W11: Fornecedores Vencidos | X11: 45938 | Y11: Não | Z11: C | AB11: 2. Vencido: 60-180 | AC11: 725513.22 | AG11: 1 | AH11: 5 TABELIONATO DE PROTESTOS DA | AM11: 90 | AN11: 99999 | AO11: 8. A vencer: >90 | AQ11: WEG EQUIPAMENTOS ELETRICOS SA | BM11: UVW COMPUTACAO GRAFICA LTDA ME
B12: =B11+1 -> 2 | C12: SCHNEIDER - CAJAMAR | D12: =SUMIFS(R:R,V:V,C12) -> 205322.66 | E12: =D12/SUM(D:D) -> 0.043371754 | F12: =E12+F11 -> 0.094702333 | G12: A | H12: =SUMIFS(R:R,V:V,C12,U:U,$AO$18) -> 0 | I12: =SUMIFS(R:R,V:V,C12,U:U,$AO$17) -> 0 | J12: =SUMIFS(R:R,V:V,C12,U:U,$AO$16) -> 109686.21 | K12: =SUMIFS(R:R,V:V,C12,U:U,$AO$15) -> 74787.2 | L12: =SUMIFS(R:R,V:V,C12,U:U,$AO$14) -> 20849.25 | M12: =SUMIFS(R:R,V:V,C12,U:U,$AO$13) -> 0 | N12: =SUMIFS(R:R,V:V,C12,U:U,$AO$12) -> 0 | O12: =SUMIFS(R:R,V:V,C12,U:U,$AO$11) -> 0 | P12: =SUM(H12:K12) -> 184473.41 | R12: 435 | S12: 45941 | T12: 3 | U12: 5. A vencer: 0-30 | V12: MVA | W12: Fornecedores a Vencer | X12: 45941 | Y12: Não | Z12: C | AB12: 3. Vencido: 30-60 | AC12: 1335343.2 | AG12: 2 | AH12: 6. TABELIONATO DE PROTESTO DE | AM12: 60 | AN12: =AM11 -> 90 | AO12: 7. A vencer: 60-90 | AQ12: SCHNEIDER ELECTRIC | BM12: WFM SECURITIZADORA S.A.
B13: =B12+1 -> 3 | C13: BC INDUSTRIAL L SOLUTIONS LTDA | D13: =SUMIFS(R:R,V:V,C13) -> 193114.21 | E13: =D13/SUM(D:D) -> 0.040792877 | F13: =E13+F12 -> 0.13549521 | G13: A | H13: =SUMIFS(R:R,V:V,C13,U:U,$AO$18) -> 0 | I13: =SUMIFS(R:R,V:V,C13,U:U,$AO$17) -> 143302.72 | J13: =SUMIFS(R:R,V:V,C13,U:U,$AO$16) -> 49811.49 | K13: =SUMIFS(R:R,V:V,C13,U:U,$AO$15) -> 0 | L13: =SUMIFS(R:R,V:V,C13,U:U,$AO$14) -> 0 | M13: =SUMIFS(R:R,V:V,C13,U:U,$AO$13) -> 0 | N13: =SUMIFS(R:R,V:V,C13,U:U,$AO$12) -> 0 | O13: =SUMIFS(R:R,V:V,C13,U:U,$AO$11) -> 0 | P13: =SUM(H13:K13) -> 193114.21 | R13: 706.14 | S13: 45888 | T13: -50 | U13: 3. Vencido: 30-60 | V13: FG - CURITIBA | W13: Fornecedores Vencidos | X13: 45938 | Y13: Não | Z13: C | AB13: 4. Vencido: 0-30 | AC13: 2195209.3 | AG13: 3 | AH13: A Bettega | AM13: 30 | AN13: =AM12 -> 60 | AO13: 6. A vencer: 30-60 | AQ13: CONTINENTAL FERRAMENTAS | BM13: A M B UNIFORMES EIRELI ME
B14: =B13+1 -> 4 | C14: PNEUMAX- ITALSERVICE | D14: =SUMIFS(R:R,V:V,C14) -> 157009.65 | E14: =D14/SUM(D:D) -> 0.033166256 | F14: =E14+F13 -> 0.16866147 | G14: A | H14: =SUMIFS(R:R,V:V,C14,U:U,$AO$18) -> 0 | I14: =SUMIFS(R:R,V:V,C14,U:U,$AO$17) -> 0 | J14: =SUMIFS(R:R,V:V,C14,U:U,$AO$16) -> 75139.96 | K14: =SUMIFS(R:R,V:V,C14,U:U,$AO$15) -> 55920.56 | L14: =SUMIFS(R:R,V:V,C14,U:U,$AO$14) -> 24155.65 | M14: =SUMIFS(R:R,V:V,C14,U:U,$AO$13) -> 1793.48 | N14: =SUMIFS(R:R,V:V,C14,U:U,$AO$12) -> 0 | O14: =SUMIFS(R:R,V:V,C14,U:U,$AO$11) -> 0 | P14: =SUM(H14:K14) -> 131060.52 | R14: 4048.81 | S14: 45887 | T14: -51 | U14: 3. Vencido: 30-60 | V14: OURO PRETO | W14: Fornecedores Vencidos | X14: 45938 | Y14: Não | Z14: C | AB14: 5. A vencer: 0-30 | AC14: 610996.54 | AG14: 4 | AH14: A CONCEPT CAR | AM14: 0 | AN14: =AM13 -> 30 | AO14: 5. A vencer: 0-30 | AQ14: ELETROPOLL PAINEIS IND C LTDA | BM14: ACOTUBO IND COM LTDA
B15: =B14+1 -> 5 | C15: BC INDUSTRIAL | D15: =SUMIFS(R:R,V:V,C15) -> 156208.55 | E15: =D15/SUM(D:D) -> 0.032997034 | F15: =E15+F14 -> 0.2016585 | G15: A | H15: =SUMIFS(R:R,V:V,C15,U:U,$AO$18) -> 0 | I15: =SUMIFS(R:R,V:V,C15,U:U,$AO$17) -> 0 | J15: =SUMIFS(R:R,V:V,C15,U:U,$AO$16) -> 81240.33 | K15: =SUMIFS(R:R,V:V,C15,U:U,$AO$15) -> 66447.23 | L15: =SUMIFS(R:R,V:V,C15,U:U,$AO$14) -> 8520.99 | M15: =SUMIFS(R:R,V:V,C15,U:U,$AO$13) -> 0 | N15: =SUMIFS(R:R,V:V,C15,U:U,$AO$12) -> 0 | O15: =SUMIFS(R:R,V:V,C15,U:U,$AO$11) -> 0 | P15: =SUM(H15:K15) -> 147687.56 | R15: 1320.5 | S15: 45891 | T15: -47 | U15: 3. Vencido: 30-60 | V15: OURO PRETO | W15: Fornecedores Vencidos | X15: 45938 | Y15: Não | Z15: C | AB15: 6. A vencer: 30-60 | AC15: 152919.53 | AG15: 5 | AH15: A M B UNIFORMES EIRELI ME | AM15: -30 | AN15: =AM14 -> 0 | AO15: 4. Vencido: 0-30 | AQ15: MEH PRODUTOS INDUSTRIAIS LTDA | BM15: SAMI ACOS ESPECIAIS EIRELI
B16: =B15+1 -> 6 | C16: SCHNEIDER ELECTRIC | D16: =SUMIFS(R:R,V:V,C16) -> 145712.4 | E16: =D16/SUM(D:D) -> 0.030779858 | F16: =E16+F15 -> 0.23243836 | G16: A | H16: =SUMIFS(R:R,V:V,C16,U:U,$AO$18) -> 0 | I16: =SUMIFS(R:R,V:V,C16,U:U,$AO$17) -> 107543.06 | J16: =SUMIFS(R:R,V:V,C16,U:U,$AO$16) -> 38169.34 | K16: =SUMIFS(R:R,V:V,C16,U:U,$AO$15) -> 0 | L16: =SUMIFS(R:R,V:V,C16,U:U,$AO$14) -> 0 | M16: =SUMIFS(R:R,V:V,C16,U:U,$AO$13) -> 0 | N16: =SUMIFS(R:R,V:V,C16,U:U,$AO$12) -> 0 | O16: =SUMIFS(R:R,V:V,C16,U:U,$AO$11) -> 0 | P16: =SUM(H16:K16) -> 145712.4 | R16: 4048.81 | S16: 45894 | T16: -44 | U16: 3. Vencido: 30-60 | V16: OURO PRETO | W16: Fornecedores Vencidos | X16: 45938 | Y16: Não | Z16: C | AB16: 7. A vencer: 60-90 | AC16: 25039.46 | AG16: 6 | AH16: A ROLEMIX C I ROL RET LTDA EPP | AM16: -60 | AN16: =AM15 -> -30 | AO16: 3. Vencido: 30-60 | AQ16: NEW COMPANY PINTURA ELETROSTAT | BM16: A.T.I BRASIL
B17: =B16+1 -> 7 | C17: RONAFER | D17: =SUMIFS(R:R,V:V,C17) -> 130732.39 | E17: =D17/SUM(D:D) -> 0.027615525 | F17: =E17+F16 -> 0.26005388 | G17: A | H17: =SUMIFS(R:R,V:V,C17,U:U,$AO$18) -> 0 | I17: =SUMIFS(R:R,V:V,C17,U:U,$AO$17) -> 0 | J17: =SUMIFS(R:R,V:V,C17,U:U,$AO$16) -> 114975.81 | K17: =SUMIFS(R:R,V:V,C17,U:U,$AO$15) -> 15756.58 | L17: =SUMIFS(R:R,V:V,C17,U:U,$AO$14) -> 0 | M17: =SUMIFS(R:R,V:V,C17,U:U,$AO$13) -> 0 | N17: =SUMIFS(R:R,V:V,C17,U:U,$AO$12) -> 0 | O17: =SUMIFS(R:R,V:V,C17,U:U,$AO$11) -> 0 | P17: =SUM(H17:K17) -> 130732.39 | R17: 4897.1 | S17: 45894 | T17: -44 | U17: 3. Vencido: 30-60 | V17: OURO PRETO | W17: Fornecedores Vencidos | X17: 45938 | Y17: Não | Z17: C | AB17: 8. A vencer: >90 | AC17: 14592.5 | AG17: 7 | AH17: A. BETTEGA | AM17: -180 | AN17: =AM16 -> -60 | AO17: 2. Vencido: 60-180 | AQ17: ALVIN ALONSO FRANCIS LOPEZ 012 | BM17: MAX INDUSTRIA E COMERCIO DE AL
B18: =B17+1 -> 8 | C18: COFACO FABRICADORA DE CORREIAS | D18: =SUMIFS(R:R,V:V,C18) -> 117220.76 | E18: =D18/SUM(D:D) -> 0.024761368 | F18: =E18+F17 -> 0.28481525 | G18: A | H18: =SUMIFS(R:R,V:V,C18,U:U,$AO$18) -> 0 | I18: =SUMIFS(R:R,V:V,C18,U:U,$AO$17) -> 109767.46 | J18: =SUMIFS(R:R,V:V,C18,U:U,$AO$16) -> 7453.3 | K18: =SUMIFS(R:R,V:V,C18,U:U,$AO$15) -> 0 | L18: =SUMIFS(R:R,V:V,C18,U:U,$AO$14) -> 0 | M18: =SUMIFS(R:R,V:V,C18,U:U,$AO$13) -> 0 | N18: =SUMIFS(R:R,V:V,C18,U:U,$AO$12) -> 0 | O18: =SUMIFS(R:R,V:V,C18,U:U,$AO$11) -> 0 | P18: =SUM(H18:K18) -> 117220.76 | R18: 4897.1 | S18: 45908 | T18: -30 | U18: 3. Vencido: 30-60 | V18: OURO PRETO | W18: Fornecedores Vencidos | X18: 45938 | Y18: Não | Z18: C | AB18: 9. N informado | AC18: 2156.49 | AG18: 8 | AH18: A. SILVA FERRAGENS LTDA | AN18: =AM17 -> -180 | AO18: 1. Vencido: >180 | AQ18: DM-COMERCIAL DE ENGRENAGENS E | BM18: ARTEFATOS DE BORRACHA PCR LTDA
B19: =B18+1 -> 9 | C19: MDS INSTALACAO | D19: =SUMIFS(R:R,V:V,C19) -> 94343.5 | E19: =D19/SUM(D:D) -> 0.019928843 | F19: =E19+F18 -> 0.30474409 | G19: A | H19: =SUMIFS(R:R,V:V,C19,U:U,$AO$18) -> 0 | I19: =SUMIFS(R:R,V:V,C19,U:U,$AO$17) -> 24300 | J19: =SUMIFS(R:R,V:V,C19,U:U,$AO$16) -> 70043.5 | K19: =SUMIFS(R:R,V:V,C19,U:U,$AO$15) -> 0 | L19: =SUMIFS(R:R,V:V,C19,U:U,$AO$14) -> 0 | M19: =SUMIFS(R:R,V:V,C19,U:U,$AO$13) -> 0 | N19: =SUMIFS(R:R,V:V,C19,U:U,$AO$12) -> 0 | O19: =SUMIFS(R:R,V:V,C19,U:U,$AO$11) -> 0 | P19: =SUM(H19:K19) -> 94343.5 | R19: 864 | S19: 45894 | T19: -44 | U19: 3. Vencido: 30-60 | V19: PAG | W19: Fornecedores Vencidos | X19: 45938 | Y19: Não | Z19: C | AB19: 1. Vencido: >180 | AC19: 5493.0939 | AG19: 9 | AH19: A.T.I BRASIL | AQ19: WFM SECURITIZADORA S.A. | BM19: FAISTEEL CENTRAL
B20: =B19+1 -> 10 | C20: ITAU UNIBANCO HOLDING S.A. | D20: =SUMIFS(R:R,V:V,C20) -> 87039.1 | E20: =D20/SUM(D:D) -> 0.018385883 | F20: =E20+F19 -> 0.32312998 | G20: A | H20: =SUMIFS(R:R,V:V,C20,U:U,$AO$18) -> 0 | I20: =SUMIFS(R:R,V:V,C20,U:U,$AO$17) -> 0 | J20: =SUMIFS(R:R,V:V,C20,U:U,$AO$16) -> 87039.1 | K20: =SUMIFS(R:R,V:V,C20,U:U,$AO$15) -> 0 | L20: =SUMIFS(R:R,V:V,C20,U:U,$AO$14) -> 0 | M20: =SUMIFS(R:R,V:V,C20,U:U,$AO$13) -> 0 | N20: =SUMIFS(R:R,V:V,C20,U:U,$AO$12) -> 0 | O20: =SUMIFS(R:R,V:V,C20,U:U,$AO$11) -> 0 | P20: =SUM(H20:K20) -> 87039.1 | R20: 110 | S20: 45894 | T20: -44 | U20: 3. Vencido: 30-60 | V20: PAG | W20: Fornecedores Vencidos | X20: 45938 | Y20: Não | Z20: C | AB20: VD SRL | AC20: 5493.0939 | AG20: 10 | AH20: ABIMOVEL ASSOCIACAO BRASILEIRA | AQ20: A M B UNIFORMES EIRELI ME | BM20: TUBOS OLIVEIRA LTDA
B21: =B20+1 -> 11 | C21: BELVEDERE | D21: =SUMIFS(R:R,V:V,C21) -> 71525.73 | E21: =D21/SUM(D:D) -> 0.015108885 | F21: =E21+F20 -> 0.33823886 | G21: B | H21: =SUMIFS(R:R,V:V,C21,U:U,$AO$18) -> 0 | I21: =SUMIFS(R:R,V:V,C21,U:U,$AO$17) -> 0 | J21: =SUMIFS(R:R,V:V,C21,U:U,$AO$16) -> 62526.39 | K21: =SUMIFS(R:R,V:V,C21,U:U,$AO$15) -> 8999.34 | L21: =SUMIFS(R:R,V:V,C21,U:U,$AO$14) -> 0 | M21: =SUMIFS(R:R,V:V,C21,U:U,$AO$13) -> 0 | N21: =SUMIFS(R:R,V:V,C21,U:U,$AO$12) -> 0 | O21: =SUMIFS(R:R,V:V,C21,U:U,$AO$11) -> 0 | P21: =SUM(H21:K21) -> 71525.73 | R21: 596.66 | S21: 45895 | T21: -43 | U21: 3. Vencido: 30-60 | V21: METALPAR | W21: Fornecedores Vencidos | X21: 45938 | Y21: Não | Z21: C | AB21: Grand Total | AC21: 5067263.4 | AG21: 11 | AH21: ACO IDEAL LTDA | AQ21: ACOTUBO IND COM LTDA | BM21: AXIAL EQUIPAMENTOS INDUSTRIAIS
B22: =B21+1 -> 12 | C22: SEW EURODRIVE BRASIL LTDA | D22: =SUMIFS(R:R,V:V,C22) -> 70297.18 | E22: =D22/SUM(D:D) -> 0.014849369 | F22: =E22+F21 -> 0.35308823 | G22: B | H22: =SUMIFS(R:R,V:V,C22,U:U,$AO$18) -> 0 | I22: =SUMIFS(R:R,V:V,C22,U:U,$AO$17) -> 65869.62 | J22: =SUMIFS(R:R,V:V,C22,U:U,$AO$16) -> 4427.56 | K22: =SUMIFS(R:R,V:V,C22,U:U,$AO$15) -> 0 | L22: =SUMIFS(R:R,V:V,C22,U:U,$AO$14) -> 0 | M22: =SUMIFS(R:R,V:V,C22,U:U,$AO$13) -> 0 | N22: =SUMIFS(R:R,V:V,C22,U:U,$AO$12) -> 0 | O22: =SUMIFS(R:R,V:V,C22,U:U,$AO$11) -> 0 | P22: =SUM(H22:K22) -> 70297.18 | R22: 612 | S22: 45901 | T22: -37 | U22: 3. Vencido: 30-60 | V22: METALPAR | W22: Fornecedores Vencidos | X22: 45938 | Y22: Não | Z22: C | AG22: 12 | AH22: ACOS FAVORIT - CTBA | AQ22: ACOTUBO INDUSTRIA E COMERCIO L | BM22: ACOS TREFITA LTDA
B23: =B22+1 -> 13 | C23: AUGE DO BRASIL LTDA | D23: =SUMIFS(R:R,V:V,C23) -> 67351.08 | E23: =D23/SUM(D:D) -> 0.014227044 | F23: =E23+F22 -> 0.36731527 | G23: B | H23: =SUMIFS(R:R,V:V,C23,U:U,$AO$18) -> 0 | I23: =SUMIFS(R:R,V:V,C23,U:U,$AO$17) -> 66117.86 | J23: =SUMIFS(R:R,V:V,C23,U:U,$AO$16) -> 1233.22 | K23: =SUMIFS(R:R,V:V,C23,U:U,$AO$15) -> 0 | L23: =SUMIFS(R:R,V:V,C23,U:U,$AO$14) -> 0 | M23: =SUMIFS(R:R,V:V,C23,U:U,$AO$13) -> 0 | N23: =SUMIFS(R:R,V:V,C23,U:U,$AO$12) -> 0 | O23: =SUMIFS(R:R,V:V,C23,U:U,$AO$11) -> 0 | P23: =SUM(H23:K23) -> 67351.08 | R23: 3948 | S23: 45912 | T23: -26 | U23: 4. Vencido: 0-30 | V23: METALPAR | W23: Fornecedores Vencidos | X23: 45938 | Y23: Não | Z23: C | AG23: 13 | AH23: ACOS FAVORIT DISTRIBUIDORA LTD | AQ23: OPERA FUNDO DE INVESTIMENTOS E | BM23: QUALITAS INDUSTRIA ELETROMECAN
B24: =B23+1 -> 14 | C24: BRAVOLUZ COMERCIAL LTDA | D24: =SUMIFS(R:R,V:V,C24) -> 63669.29 | E24: =D24/SUM(D:D) -> 0.013449313 | F24: =E24+F23 -> 0.38076459 | G24: B | H24: =SUMIFS(R:R,V:V,C24,U:U,$AO$18) -> 0 | I24: =SUMIFS(R:R,V:V,C24,U:U,$AO$17) -> 56186.35 | J24: =SUMIFS(R:R,V:V,C24,U:U,$AO$16) -> 7482.94 | K24: =SUMIFS(R:R,V:V,C24,U:U,$AO$15) -> 0 | L24: =SUMIFS(R:R,V:V,C24,U:U,$AO$14) -> 0 | M24: =SUMIFS(R:R,V:V,C24,U:U,$AO$13) -> 0 | N24: =SUMIFS(R:R,V:V,C24,U:U,$AO$12) -> 0 | O24: =SUMIFS(R:R,V:V,C24,U:U,$AO$11) -> 0 | P24: =SUM(H24:K24) -> 63669.29 | R24: 2157.46 | S24: 45890 | T24: -48 | U24: 3. Vencido: 30-60 | V24: MUNDIAL PRINT | W24: Fornecedores Vencidos | X24: 45938 | Y24: Não | Z24: C | AG24: 14 | AH24: ACOS ROMAN | AQ24: TUBOS IPIRANGA IND E COM LTDA | BM24: TUBOS IPIRANGA IND E COM LTDA
B25: =B24+1 -> 15 | C25: WEG EQUIPAMENTOS ELETRICOS SA | D25: =SUMIFS(R:R,V:V,C25) -> 61126.84 | E25: =D25/SUM(D:D) -> 0.012912254 | F25: =E25+F24 -> 0.39367684 | G25: B | H25: =SUMIFS(R:R,V:V,C25,U:U,$AO$18) -> 0 | I25: =SUMIFS(R:R,V:V,C25,U:U,$AO$17) -> 54936.98 | J25: =SUMIFS(R:R,V:V,C25,U:U,$AO$16) -> 6189.86 | K25: =SUMIFS(R:R,V:V,C25,U:U,$AO$15) -> 0 | L25: =SUMIFS(R:R,V:V,C25,U:U,$AO$14) -> 0 | M25: =SUMIFS(R:R,V:V,C25,U:U,$AO$13) -> 0 | N25: =SUMIFS(R:R,V:V,C25,U:U,$AO$12) -> 0 | O25: =SUMIFS(R:R,V:V,C25,U:U,$AO$11) -> 0 | P25: =SUM(H25:K25) -> 61126.84 | R25: 2157.5 | S25: 45902 | T25: -36 | U25: 3. Vencido: 30-60 | V25: MUNDIAL PRINT | W25: Fornecedores Vencidos | X25: 45938 | Y25: Não | Z25: C | AG25: 15 | AH25: ACOS ROMAN LTDA | AQ25: ACSO CENTRAL DE SERVICO DO A | BM25: ACOTUBO IND E COM LTDA
B26: =B25+1 -> 16 | C26: TRADEMASTER SERVICOS E PARTICI | D26: =SUMIFS(R:R,V:V,C26) -> 61030.34 | E26: =D26/SUM(D:D) -> 0.012891869 | F26: =E26+F25 -> 0.40656871 | G26: B | H26: =SUMIFS(R:R,V:V,C26,U:U,$AO$18) -> 0 | I26: =SUMIFS(R:R,V:V,C26,U:U,$AO$17) -> 51610.24 | J26: =SUMIFS(R:R,V:V,C26,U:U,$AO$16) -> 9420.1 | K26: =SUMIFS(R:R,V:V,C26,U:U,$AO$15) -> 0 | L26: =SUMIFS(R:R,V:V,C26,U:U,$AO$14) -> 0 | M26: =SUMIFS(R:R,V:V,C26,U:U,$AO$13) -> 0 | N26: =SUMIFS(R:R,V:V,C26,U:U,$AO$12) -> 0 | O26: =SUMIFS(R:R,V:V,C26,U:U,$AO$11) -> 0 | P26: =SUM(H26:K26) -> 61030.34 | R26: 2157.5 | S26: 45909 | T26: -29 | U26: 4. Vencido: 0-30 | V26: MUNDIAL PRINT | W26: Fornecedores Vencidos | X26: 45938 | Y26: Não | Z26: C | AG26: 16 | AH26: ACOS TREFITA LTDA | AQ26: POCOL CORREIAS MANGUEIRAS LTDA | BM26: MKRAFT COMERCIO DE METAIS LTDA
B27: =B26+1 -> 17 | C27: ACOS FAVORIT - CTBA | D27: =SUMIFS(R:R,V:V,C27) -> 52325.85 | E27: =D27/SUM(D:D) -> 0.011053158 | F27: =E27+F26 -> 0.41762187 | G27: B | H27: =SUMIFS(R:R,V:V,C27,U:U,$AO$18) -> 0 | I27: =SUMIFS(R:R,V:V,C27,U:U,$AO$17) -> 0 | J27: =SUMIFS(R:R,V:V,C27,U:U,$AO$16) -> 26548.02 | K27: =SUMIFS(R:R,V:V,C27,U:U,$AO$15) -> 19187.08 | L27: =SUMIFS(R:R,V:V,C27,U:U,$AO$14) -> 6590.75 | M27: =SUMIFS(R:R,V:V,C27,U:U,$AO$13) -> 0 | N27: =SUMIFS(R:R,V:V,C27,U:U,$AO$12) -> 0 | O27: =SUMIFS(R:R,V:V,C27,U:U,$AO$11) -> 0 | P27: =SUM(H27:K27) -> 45735.1 | R27: 1831.8 | S27: 45888 | T27: -50 | U27: 3. Vencido: 30-60 | V27: RUBBERMAX | W27: Fornecedores Vencidos | X27: 45938 | Y27: Não | Z27: C | AG27: 17 | AH27: ACOTUBO IND COM LTDA | AQ27: PROAUTO ELECTRIC LTDA | BM27: METALURGICA BENGAZZI LTDA ME
B28: =B27+1 -> 18 | C28: Sogest | D28: =SUMIFS(R:R,V:V,C28) -> 49440.75 | E28: =D28/SUM(D:D) -> 0.010443718 | F28: =E28+F27 -> 0.42806559 | G28: B | H28: =SUMIFS(R:R,V:V,C28,U:U,$AO$18) -> 0 | I28: =SUMIFS(R:R,V:V,C28,U:U,$AO$17) -> 49440.75 | J28: =SUMIFS(R:R,V:V,C28,U:U,$AO$16) -> 0 | K28: =SUMIFS(R:R,V:V,C28,U:U,$AO$15) -> 0 | L28: =SUMIFS(R:R,V:V,C28,U:U,$AO$14) -> 0 | M28: =SUMIFS(R:R,V:V,C28,U:U,$AO$13) -> 0 | N28: =SUMIFS(R:R,V:V,C28,U:U,$AO$12) -> 0 | O28: =SUMIFS(R:R,V:V,C28,U:U,$AO$11) -> 0 | P28: =SUM(H28:K28) -> 49440.75 | R28: 971.28 | S28: 45888 | T28: -50 | U28: 3. Vencido: 30-60 | V28: RUBBERMAX | W28: Fornecedores Vencidos | X28: 45938 | Y28: Não | Z28: C | AG28: 18 | AH28: ACOTUBO IND E COM LTDA | AQ28: ACOTUBO IND E COM LTDA | BM28: TRAMAR INDUSTRIAL LTDA
B29: =B28+1 -> 19 | C29: NECTECH | D29: =SUMIFS(R:R,V:V,C29) -> 45844.08 | E29: =D29/SUM(D:D) -> 0.0096839684 | F29: =E29+F28 -> 0.43774956 | G29: B | H29: =SUMIFS(R:R,V:V,C29,U:U,$AO$18) -> 0 | I29: =SUMIFS(R:R,V:V,C29,U:U,$AO$17) -> 0 | J29: =SUMIFS(R:R,V:V,C29,U:U,$AO$16) -> 45844.08 | K29: =SUMIFS(R:R,V:V,C29,U:U,$AO$15) -> 0 | L29: =SUMIFS(R:R,V:V,C29,U:U,$AO$14) -> 0 | M29: =SUMIFS(R:R,V:V,C29,U:U,$AO$13) -> 0 | N29: =SUMIFS(R:R,V:V,C29,U:U,$AO$12) -> 0 | O29: =SUMIFS(R:R,V:V,C29,U:U,$AO$11) -> 0 | P29: =SUM(H29:K29) -> 45844.08 | R29: 1831.8 | S29: 45895 | T29: -43 | U29: 3. Vencido: 30-60 | V29: RUBBERMAX | W29: Fornecedores Vencidos | X29: 45938 | Y29: Não | Z29: C | AG29: 19 | AH29: ACOTUBO INDUSTRIA E COMERCIO L | AQ29: MAX INDUSTRIA E COMERCIO DE AL | BM29: IBG CRYO INDUSTRIA DE GASES LT
B30: =B29+1 -> 20 | C30: Sofka Seguranca Ltda | D30: =SUMIFS(R:R,V:V,C30) -> 43945.55 | E30: =D30/SUM(D:D) -> 0.0092829285 | F30: =E30+F29 -> 0.44703248 | G30: B | H30: =SUMIFS(R:R,V:V,C30,U:U,$AO$18) -> 0 | I30: =SUMIFS(R:R,V:V,C30,U:U,$AO$17) -> 22645.55 | J30: =SUMIFS(R:R,V:V,C30,U:U,$AO$16) -> 21300 | K30: =SUMIFS(R:R,V:V,C30,U:U,$AO$15) -> 0 | L30: =SUMIFS(R:R,V:V,C30,U:U,$AO$14) -> 0 | M30: =SUMIFS(R:R,V:V,C30,U:U,$AO$13) -> 0 | N30: =SUMIFS(R:R,V:V,C30,U:U,$AO$12) -> 0 | O30: =SUMIFS(R:R,V:V,C30,U:U,$AO$11) -> 0 | P30: =SUM(H30:K30) -> 43945.55 | R30: 2115.8 | S30: 45896 | T30: -42 | U30: 3. Vencido: 30-60 | V30: RUBBERMAX | W30: Fornecedores Vencidos | X30: 45938 | Y30: Não | Z30: C | AG30: 20 | AH30: ACRE CAXIAS | AQ30: ARTEFATOS DE BORRACHA PCR LTDA | BM30: MUNDIAL PRINT LTDA
B31: =B30+1 -> 21 | C31: PHOENIX CONTACT IND COM LTDA | D31: =SUMIFS(R:R,V:V,C31) -> 42817.79 | E31: =D31/SUM(D:D) -> 0.0090447038 | F31: =E31+F30 -> 0.45607719 | G31: B | H31: =SUMIFS(R:R,V:V,C31,U:U,$AO$18) -> 0 | I31: =SUMIFS(R:R,V:V,C31,U:U,$AO$17) -> 42817.79 | J31: =SUMIFS(R:R,V:V,C31,U:U,$AO$16) -> 0 | K31: =SUMIFS(R:R,V:V,C31,U:U,$AO$15) -> 0 | L31: =SUMIFS(R:R,V:V,C31,U:U,$AO$14) -> 0 | M31: =SUMIFS(R:R,V:V,C31,U:U,$AO$13) -> 0 | N31: =SUMIFS(R:R,V:V,C31,U:U,$AO$12) -> 0 | O31: =SUMIFS(R:R,V:V,C31,U:U,$AO$11) -> 0 | P31: =SUM(H31:K31) -> 42817.79 | R31: 1831.8 | S31: 45902 | T31: -36 | U31: 3. Vencido: 30-60 | V31: RUBBERMAX | W31: Fornecedores Vencidos | X31: 45938 | Y31: Não | Z31: C | AG31: 21 | AH31: ACRE CAXIAS IND. E COM. DE ABR | AQ31: FAISTEEL CENTRAL | BM31: PCR
B32: =B31+1 -> 22 | C32: ROLPASA ROLAMENTOS PARANA LTDA | D32: =SUMIFS(R:R,V:V,C32) -> 42380.25 | E32: =D32/SUM(D:D) -> 0.0089522792 | F32: =E32+F31 -> 0.46502947 | G32: B | H32: =SUMIFS(R:R,V:V,C32,U:U,$AO$18) -> 0 | I32: =SUMIFS(R:R,V:V,C32,U:U,$AO$17) -> 38284.53 | J32: =SUMIFS(R:R,V:V,C32,U:U,$AO$16) -> 4095.72 | K32: =SUMIFS(R:R,V:V,C32,U:U,$AO$15) -> 0 | L32: =SUMIFS(R:R,V:V,C32,U:U,$AO$14) -> 0 | M32: =SUMIFS(R:R,V:V,C32,U:U,$AO$13) -> 0 | N32: =SUMIFS(R:R,V:V,C32,U:U,$AO$12) -> 0 | O32: =SUMIFS(R:R,V:V,C32,U:U,$AO$11) -> 0 | P32: =SUM(H32:K32) -> 42380.25 | R32: 2115.8 | S32: 45903 | T32: -35 | U32: 3. Vencido: 30-60 | V32: RUBBERMAX | W32: Fornecedores Vencidos | X32: 45938 | Y32: Não | Z32: C | AG32: 22 | AH32: ACSO | AQ32: SAMI ACOS ESPECIAIS EIRELI | BM32: WEG - MOTORES
B33: =B32+1 -> 23 | C33: Azanha e Azanha | D33: =SUMIFS(R:R,V:V,C33) -> 38036 | E33: =D33/SUM(D:D) -> 0.0080346126 | F33: =E33+F32 -> 0.47306408 | G33: B | H33: =SUMIFS(R:R,V:V,C33,U:U,$AO$18) -> 0 | I33: =SUMIFS(R:R,V:V,C33,U:U,$AO$17) -> 38036 | J33: =SUMIFS(R:R,V:V,C33,U:U,$AO$16) -> 0 | K33: =SUMIFS(R:R,V:V,C33,U:U,$AO$15) -> 0 | L33: =SUMIFS(R:R,V:V,C33,U:U,$AO$14) -> 0 | M33: =SUMIFS(R:R,V:V,C33,U:U,$AO$13) -> 0 | N33: =SUMIFS(R:R,V:V,C33,U:U,$AO$12) -> 0 | O33: =SUMIFS(R:R,V:V,C33,U:U,$AO$11) -> 0 | P33: =SUM(H33:K33) -> 38036 | R33: 2115.8 | S33: 45910 | T33: -28 | U33: 4. Vencido: 0-30 | V33: RUBBERMAX | W33: Fornecedores Vencidos | X33: 45938 | Y33: Não | Z33: C | AG33: 23 | AH33: ACSO - CENTRAL DE SERVICO DO A | AQ33: MKRAFT COMERCIO DE METAIS LTDA
B34: =B33+1 -> 24 | C34: PARANA CLINICAS - PLANOS DE SA | D34: =SUMIFS(R:R,V:V,C34) -> 36023.15 | E34: =D34/SUM(D:D) -> 0.0076094241 | F34: =E34+F33 -> 0.4806735 | G34: B | H34: =SUMIFS(R:R,V:V,C34,U:U,$AO$18) -> 0 | I34: =SUMIFS(R:R,V:V,C34,U:U,$AO$17) -> 0 | J34: =SUMIFS(R:R,V:V,C34,U:U,$AO$16) -> 36023.15 | K34: =SUMIFS(R:R,V:V,C34,U:U,$AO$15) -> 0 | L34: =SUMIFS(R:R,V:V,C34,U:U,$AO$14) -> 0 | M34: =SUMIFS(R:R,V:V,C34,U:U,$AO$13) -> 0 | N34: =SUMIFS(R:R,V:V,C34,U:U,$AO$12) -> 0 | O34: =SUMIFS(R:R,V:V,C34,U:U,$AO$11) -> 0 | P34: =SUM(H34:K34) -> 36023.15 | R34: 1481.77 | S34: 45890 | T34: -48 | U34: 3. Vencido: 30-60 | V34: A. BETTEGA | W34: Fornecedores Vencidos | X34: 45938 | Y34: Não | Z34: C | AG34: 24 | AH34: ACSO CENTRAL DE SERVICO DO A | AQ34: METALURGICA BENGAZZI LTDA ME
B35: =B34+1 -> 25 | C35: HPE - BRASIL | D35: =SUMIFS(R:R,V:V,C35) -> 35700 | E35: =D35/SUM(D:D) -> 0.0075411629 | F35: =E35+F34 -> 0.48821467 | G35: B | H35: =SUMIFS(R:R,V:V,C35,U:U,$AO$18) -> 0 | I35: =SUMIFS(R:R,V:V,C35,U:U,$AO$17) -> 0 | J35: =SUMIFS(R:R,V:V,C35,U:U,$AO$16) -> 0 | K35: =SUMIFS(R:R,V:V,C35,U:U,$AO$15) -> 11900 | L35: =SUMIFS(R:R,V:V,C35,U:U,$AO$14) -> 11900 | M35: =SUMIFS(R:R,V:V,C35,U:U,$AO$13) -> 11900 | N35: =SUMIFS(R:R,V:V,C35,U:U,$AO$12) -> 0 | O35: =SUMIFS(R:R,V:V,C35,U:U,$AO$11) -> 0 | P35: =SUM(H35:K35) -> 11900 | R35: 36.7 | S35: 45894 | T35: -44 | U35: 3. Vencido: 30-60 | V35: A. BETTEGA | W35: Fornecedores Vencidos | X35: 45938 | Y35: Não | Z35: C | AG35: 25 | AH35: ALADDIN LAMPADAS | AQ35: TUBOS OLIVEIRA LTDA
B36: =B35+1 -> 26 | C36: VITAL INDUSTRIA C ACO LTDA | D36: =SUMIFS(R:R,V:V,C36) -> 32003.26 | E36: =D36/SUM(D:D) -> 0.0067602744 | F36: =E36+F35 -> 0.49497494 | G36: B | H36: =SUMIFS(R:R,V:V,C36,U:U,$AO$18) -> 0 | I36: =SUMIFS(R:R,V:V,C36,U:U,$AO$17) -> 32003.26 | J36: =SUMIFS(R:R,V:V,C36,U:U,$AO$16) -> 0 | K36: =SUMIFS(R:R,V:V,C36,U:U,$AO$15) -> 0 | L36: =SUMIFS(R:R,V:V,C36,U:U,$AO$14) -> 0 | M36: =SUMIFS(R:R,V:V,C36,U:U,$AO$13) -> 0 | N36: =SUMIFS(R:R,V:V,C36,U:U,$AO$12) -> 0 | O36: =SUMIFS(R:R,V:V,C36,U:U,$AO$11) -> 0 | P36: =SUM(H36:K36) -> 32003.26 | R36: 143.23 | S36: 45905 | T36: -33 | U36: 3. Vencido: 30-60 | V36: A. BETTEGA | W36: Fornecedores Vencidos | X36: 45938 | Y36: Não | Z36: C | AG36: 26 | AH36: ALFA COMERCIO DE POLIAS E CORR | AQ36: BENAFER SA COMERCIO INDUSTRIA
B37: =B36+1 -> 27 | C37: ITALSERVICE AUTOMACAO INDUSTRI | D37: =SUMIFS(R:R,V:V,C37) -> 31374.39 | E37: =D37/SUM(D:D) -> 0.0066274337 | F37: =E37+F36 -> 0.50160238 | G37: B | H37: =SUMIFS(R:R,V:V,C37,U:U,$AO$18) -> 0 | I37: =SUMIFS(R:R,V:V,C37,U:U,$AO$17) -> 0 | J37: =SUMIFS(R:R,V:V,C37,U:U,$AO$16) -> 31374.39 | K37: =SUMIFS(R:R,V:V,C37,U:U,$AO$15) -> 0 | L37: =SUMIFS(R:R,V:V,C37,U:U,$AO$14) -> 0 | M37: =SUMIFS(R:R,V:V,C37,U:U,$AO$13) -> 0 | N37: =SUMIFS(R:R,V:V,C37,U:U,$AO$12) -> 0 | O37: =SUMIFS(R:R,V:V,C37,U:U,$AO$11) -> 0 | P37: =SUM(H37:K37) -> 31374.39 | R37: 600.3 | S37: 45908 | T37: -30 | U37: 3. Vencido: 30-60 | V37: A. BETTEGA | W37: Fornecedores Vencidos | X37: 45938 | Y37: Não | Z37: C | AG37: 27 | AH37: ALPES AUTOMACAO COMERCIO DE CO | AQ37: TRAMAR INDUSTRIAL LTDA
B38: =B37+1 -> 28 | C38: METALURGICA BENGAZZI LTDA ME | D38: =SUMIFS(R:R,V:V,C38) -> 31190.02 | E38: =D38/SUM(D:D) -> 0.006588488 | F38: =E38+F37 -> 0.50819086 | G38: B | H38: =SUMIFS(R:R,V:V,C38,U:U,$AO$18) -> 0 | I38: =SUMIFS(R:R,V:V,C38,U:U,$AO$17) -> 23378.54 | J38: =SUMIFS(R:R,V:V,C38,U:U,$AO$16) -> 7811.48 | K38: =SUMIFS(R:R,V:V,C38,U:U,$AO$15) -> 0 | L38: =SUMIFS(R:R,V:V,C38,U:U,$AO$14) -> 0 | M38: =SUMIFS(R:R,V:V,C38,U:U,$AO$13) -> 0 | N38: =SUMIFS(R:R,V:V,C38,U:U,$AO$12) -> 0 | O38: =SUMIFS(R:R,V:V,C38,U:U,$AO$11) -> 0 | P38: =SUM(H38:K38) -> 31190.02 | R38: 431.19 | S38: 45908 | T38: -30 | U38: 3. Vencido: 30-60 | V38: A. BETTEGA | W38: Fornecedores Vencidos | X38: 45938 | Y38: Não | Z38: C | AG38: 28 | AH38: ALSCO BRASIL | AQ38: A.T.I BRASIL
B39: =B38+1 -> 29 | C39: SPRAYFLOW MAQUINAS E EQUIPAMEN | D39: =SUMIFS(R:R,V:V,C39) -> 31173.35 | E39: =D39/SUM(D:D) -> 0.0065849666 | F39: =E39+F38 -> 0.51477583 | G39: B | H39: =SUMIFS(R:R,V:V,C39,U:U,$AO$18) -> 0 | I39: =SUMIFS(R:R,V:V,C39,U:U,$AO$17) -> 31173.35 | J39: =SUMIFS(R:R,V:V,C39,U:U,$AO$16) -> 0 | K39: =SUMIFS(R:R,V:V,C39,U:U,$AO$15) -> 0 | L39: =SUMIFS(R:R,V:V,C39,U:U,$AO$14) -> 0 | M39: =SUMIFS(R:R,V:V,C39,U:U,$AO$13) -> 0 | N39: =SUMIFS(R:R,V:V,C39,U:U,$AO$12) -> 0 | O39: =SUMIFS(R:R,V:V,C39,U:U,$AO$11) -> 0 | P39: =SUM(H39:K39) -> 31173.35 | R39: 1820.43 | S39: 45908 | T39: -30 | U39: 3. Vencido: 30-60 | V39: A. BETTEGA | W39: Fornecedores Vencidos | X39: 45938 | Y39: Não | Z39: C | AG39: 29 | AH39: ALSCO TOALHEIRO BRASIL LTDA | AQ39: AXIAL EQUIPAMENTOS INDUSTRIAIS
B40: =B39+1 -> 30 | C40: UVW COMPUTACAO GRAFICA LTDA ME | D40: =SUMIFS(R:R,V:V,C40) -> 31093.05 | E40: =D40/SUM(D:D) -> 0.0065680043 | F40: =E40+F39 -> 0.52134383 | G40: B | H40: =SUMIFS(R:R,V:V,C40,U:U,$AO$18) -> 0 | I40: =SUMIFS(R:R,V:V,C40,U:U,$AO$17) -> 20414.11 | J40: =SUMIFS(R:R,V:V,C40,U:U,$AO$16) -> 10678.94 | K40: =SUMIFS(R:R,V:V,C40,U:U,$AO$15) -> 0 | L40: =SUMIFS(R:R,V:V,C40,U:U,$AO$14) -> 0 | M40: =SUMIFS(R:R,V:V,C40,U:U,$AO$13) -> 0 | N40: =SUMIFS(R:R,V:V,C40,U:U,$AO$12) -> 0 | O40: =SUMIFS(R:R,V:V,C40,U:U,$AO$11) -> 0 | P40: =SUM(H40:K40) -> 31093.05 | R40: 163.6 | S40: 45908 | T40: -30 | U40: 3. Vencido: 30-60 | V40: A. BETTEGA | W40: Fornecedores Vencidos | X40: 45938 | Y40: Não | Z40: C | AG40: 30 | AH40: ALVIN ALONSO FRANCIS | AQ40: IBG CRYO INDUSTRIA DE GASES LT
B41: =B40+1 -> 31 | C41: WEG - MOTORES | D41: =SUMIFS(R:R,V:V,C41) -> 29508.53 | E41: =D41/SUM(D:D) -> 0.006233295 | F41: =E41+F40 -> 0.52757713 | G41: C | H41: =SUMIFS(R:R,V:V,C41,U:U,$AO$18) -> 0 | I41: =SUMIFS(R:R,V:V,C41,U:U,$AO$17) -> 0 | J41: =SUMIFS(R:R,V:V,C41,U:U,$AO$16) -> 25225.15 | K41: =SUMIFS(R:R,V:V,C41,U:U,$AO$15) -> 4283.38 | L41: =SUMIFS(R:R,V:V,C41,U:U,$AO$14) -> 0 | M41: =SUMIFS(R:R,V:V,C41,U:U,$AO$13) -> 0 | N41: =SUMIFS(R:R,V:V,C41,U:U,$AO$12) -> 0 | O41: =SUMIFS(R:R,V:V,C41,U:U,$AO$11) -> 0 | P41: =SUM(H41:K41) -> 29508.53 | R41: 36.7 | S41: 45908 | T41: -30 | U41: 3. Vencido: 30-60 | V41: A. BETTEGA | W41: Fornecedores Vencidos | X41: 45938 | Y41: Não | Z41: C | AG41: 31 | AH41: ALVIN ALONSO FRANCIS LOPEZ 012 | AQ41: ACOS TREFITA LTDA
B42: =B41+1 -> 32 | C42: SEW - JOINVILLE | D42: =SUMIFS(R:R,V:V,C42) -> 29397.6 | E42: =D42/SUM(D:D) -> 0.0062098624 | F42: =E42+F41 -> 0.53378699 | G42: C | H42: =SUMIFS(R:R,V:V,C42,U:U,$AO$18) -> 0 | I42: =SUMIFS(R:R,V:V,C42,U:U,$AO$17) -> 0 | J42: =SUMIFS(R:R,V:V,C42,U:U,$AO$16) -> 29397.6 | K42: =SUMIFS(R:R,V:V,C42,U:U,$AO$15) -> 0 | L42: =SUMIFS(R:R,V:V,C42,U:U,$AO$14) -> 0 | M42: =SUMIFS(R:R,V:V,C42,U:U,$AO$13) -> 0 | N42: =SUMIFS(R:R,V:V,C42,U:U,$AO$12) -> 0 | O42: =SUMIFS(R:R,V:V,C42,U:U,$AO$11) -> 0 | P42: =SUM(H42:K42) -> 29397.6 | R42: 387.5 | S42: 45908 | T42: -30 | U42: 3. Vencido: 30-60 | V42: A. BETTEGA | W42: Fornecedores Vencidos | X42: 45938 | Y42: Não | Z42: C | AG42: 32 | AH42: AMB UNIFORMES | AQ42: QUALITAS INDUSTRIA ELETROMECAN
B43: =B42+1 -> 33 | C43: ROLPASA | D43: =SUMIFS(R:R,V:V,C43) -> 29379.19 | E43: =D43/SUM(D:D) -> 0.0062059736 | F43: =E43+F42 -> 0.53999297 | G43: C | H43: =SUMIFS(R:R,V:V,C43,U:U,$AO$18) -> 0 | I43: =SUMIFS(R:R,V:V,C43,U:U,$AO$17) -> 0 | J43: =SUMIFS(R:R,V:V,C43,U:U,$AO$16) -> 11927.67 | K43: =SUMIFS(R:R,V:V,C43,U:U,$AO$15) -> 11528.78 | L43: =SUMIFS(R:R,V:V,C43,U:U,$AO$14) -> 5922.74 | M43: =SUMIFS(R:R,V:V,C43,U:U,$AO$13) -> 0 | N43: =SUMIFS(R:R,V:V,C43,U:U,$AO$12) -> 0 | O43: =SUMIFS(R:R,V:V,C43,U:U,$AO$11) -> 0 | P43: =SUM(H43:K43) -> 23456.45 | R43: 11.4 | S43: 45909 | T43: -29 | U43: 4. Vencido: 0-30 | V43: A. BETTEGA | W43: Fornecedores Vencidos | X43: 45938 | Y43: Não | Z43: C | AG43: 33 | AH43: AMERICAN CARBON I C C ELETROME | AQ43: ELETRONOR - DISTRIBUIDORA DE M
B44: =B43+1 -> 34 | C44: Copel | D44: =SUMIFS(R:R,V:V,C44) -> 28723.64 | E44: =D44/SUM(D:D) -> 0.0060674971 | F44: =E44+F43 -> 0.54606046 | G44: C | H44: =SUMIFS(R:R,V:V,C44,U:U,$AO$18) -> 0 | I44: =SUMIFS(R:R,V:V,C44,U:U,$AO$17) -> 28723.64 | J44: =SUMIFS(R:R,V:V,C44,U:U,$AO$16) -> 0 | K44: =SUMIFS(R:R,V:V,C44,U:U,$AO$15) -> 0 | L44: =SUMIFS(R:R,V:V,C44,U:U,$AO$14) -> 0 | M44: =SUMIFS(R:R,V:V,C44,U:U,$AO$13) -> 0 | N44: =SUMIFS(R:R,V:V,C44,U:U,$AO$12) -> 0 | O44: =SUMIFS(R:R,V:V,C44,U:U,$AO$11) -> 0 | P44: =SUM(H44:K44) -> 28723.64 | R44: 19.06 | S44: 45911 | T44: -27 | U44: 4. Vencido: 0-30 | V44: A. BETTEGA | W44: Fornecedores Vencidos | X44: 45938 | Y44: Não | Z44: C | AG44: 34 | AH44: AMIL ASSISTENCIA ME | AQ44: MUNDIAL PRINT LTDA
... B50: =B49+1 -> 40 | C50: LEITZ FERRAMENTAS PARA MADEIRA | D50: =SUMIFS(R:R,V:V,C50) -> 25728.56 | E50: =D50/SUM(D:D) -> 0.0054348252 | F50: =E50+F49 -> 0.57978583 | G50: C | H50: =SUMIFS(R:R,V:V,C50,U:U,$AO$18) -> 0 | I50: =SUMIFS(R:R,V:V,C50,U:U,$AO$17) -> 25728.56 | J50: =SUMIFS(R:R,V:V,C50,U:U,$AO$16) -> 0 | K50: =SUMIFS(R:R,V:V,C50,U:U,$AO$15) -> 0 | L50: =SUMIFS(R:R,V:V,C50,U:U,$AO$14) -> 0 | M50: =SUMIFS(R:R,V:V,C50,U:U,$AO$13) -> 0 | N50: =SUMIFS(R:R,V:V,C50,U:U,$AO$12) -> 0 | O50: =SUMIFS(R:R,V:V,C50,U:U,$AO$11) -> 0 | P50: =SUM(H50:K50) -> 25728.56 | R50: 7018.41 | S50: 45888 | T50: -50 | U50: 3. Vencido: 30-60 | V50: COFACO | W50: Fornecedores Vencidos | X50: 45938 | Y50: Não | Z50: C | AG50: 40 | AH50: AODD BOMBAS | AQ50: PAESE - COMERCIO DE FERRAGENS
B51: =B50+1 -> 41 | C51: IANCO INDUSTRIA MET EIRELI ME | D51: =SUMIFS(R:R,V:V,C51) -> 24511.99 | E51: =D51/SUM(D:D) -> 0.0051778406 | F51: =E51+F50 -> 0.58496367 | G51: C | H51: =SUMIFS(R:R,V:V,C51,U:U,$AO$18) -> 0 | I51: =SUMIFS(R:R,V:V,C51,U:U,$AO$17) -> 18533.68 | J51: =SUMIFS(R:R,V:V,C51,U:U,$AO$16) -> 5978.31 | K51: =SUMIFS(R:R,V:V,C51,U:U,$AO$15) -> 0 | L51: =SUMIFS(R:R,V:V,C51,U:U,$AO$14) -> 0 | M51: =SUMIFS(R:R,V:V,C51,U:U,$AO$13) -> 0 | N51: =SUMIFS(R:R,V:V,C51,U:U,$AO$12) -> 0 | O51: =SUMIFS(R:R,V:V,C51,U:U,$AO$11) -> 0 | P51: =SUM(H51:K51) -> 24511.99 | R51: 4517.41 | S51: 45890 | T51: -48 | U51: 3. Vencido: 30-60 | V51: COFACO | W51: Fornecedores Vencidos | X51: 45938 | Y51: Não | Z51: C | AG51: 41 | AH51: ARCELORMITTAL - PR
B52: =B51+1 -> 42 | C52: NEW COMPANY PINTURA ELETROSTAT | D52: =SUMIFS(R:R,V:V,C52) -> 24496.8 | E52: =D52/SUM(D:D) -> 0.0051746319 | F52: =E52+F51 -> 0.59013831 | G52: C | H52: =SUMIFS(R:R,V:V,C52,U:U,$AO$18) -> 0 | I52: =SUMIFS(R:R,V:V,C52,U:U,$AO$17) -> 22957.94 | J52: =SUMIFS(R:R,V:V,C52,U:U,$AO$16) -> 1538.86 | K52: =SUMIFS(R:R,V:V,C52,U:U,$AO$15) -> 0 | L52: =SUMIFS(R:R,V:V,C52,U:U,$AO$14) -> 0 | M52: =SUMIFS(R:R,V:V,C52,U:U,$AO$13) -> 0 | N52: =SUMIFS(R:R,V:V,C52,U:U,$AO$12) -> 0 | O52: =SUMIFS(R:R,V:V,C52,U:U,$AO$11) -> 0 | P52: =SUM(H52:K52) -> 24496.8 | R52: 4219.94 | S52: 45891 | T52: -47 | U52: 3. Vencido: 30-60 | V52: COFACO | W52: Fornecedores Vencidos | X52: 45938 | Y52: Não | Z52: C | AG52: 42 | AH52: ARCLIM AR CONDICIONADO LTDA
B53: =B52+1 -> 43 | C53: GUNTER METALL | D53: =SUMIFS(R:R,V:V,C53) -> 24418.47 | E53: =D53/SUM(D:D) -> 0.0051580857 | F53: =E53+F52 -> 0.59529639 | G53: C | H53: =SUMIFS(R:R,V:V,C53,U:U,$AO$18) -> 0 | I53: =SUMIFS(R:R,V:V,C53,U:U,$AO$17) -> 0 | J53: =SUMIFS(R:R,V:V,C53,U:U,$AO$16) -> 12209.24 | K53: =SUMIFS(R:R,V:V,C53,U:U,$AO$15) -> 12209.23 | L53: =SUMIFS(R:R,V:V,C53,U:U,$AO$14) -> 0 | M53: =SUMIFS(R:R,V:V,C53,U:U,$AO$13) -> 0 | N53: =SUMIFS(R:R,V:V,C53,U:U,$AO$12) -> 0 | O53: =SUMIFS(R:R,V:V,C53,U:U,$AO$11) -> 0 | P53: =SUM(H53:K53) -> 24418.47 | R53: 7018.41 | S53: 45895 | T53: -43 | U53: 3. Vencido: 30-60 | V53: COFACO | W53: Fornecedores Vencidos | X53: 45938 | Y53: Não | Z53: C | AG53: 43 | AH53: ARJIRE - SP
B54: =B53+1 -> 44 | C54: Casillo | D54: =SUMIFS(R:R,V:V,C54) -> 24401 | E54: =D54/SUM(D:D) -> 0.0051543954 | F54: =E54+F53 -> 0.60045079 | G54: C | H54: =SUMIFS(R:R,V:V,C54,U:U,$AO$18) -> 0 | I54: =SUMIFS(R:R,V:V,C54,U:U,$AO$17) -> 18300.75 | J54: =SUMIFS(R:R,V:V,C54,U:U,$AO$16) -> 6100.25 | K54: =SUMIFS(R:R,V:V,C54,U:U,$AO$15) -> 0 | L54: =SUMIFS(R:R,V:V,C54,U:U,$AO$14) -> 0 | M54: =SUMIFS(R:R,V:V,C54,U:U,$AO$13) -> 0 | N54: =SUMIFS(R:R,V:V,C54,U:U,$AO$12) -> 0 | O54: =SUMIFS(R:R,V:V,C54,U:U,$AO$11) -> 0 | P54: =SUM(H54:K54) -> 24401 | R54: 4517.41 | S54: 45904 | T54: -34 | U54: 3. Vencido: 30-60 | V54: COFACO | W54: Fornecedores Vencidos | X54: 45938 | Y54: Não | Z54: C | AG54: 44 | AH54: ARTEFATOS DE BORRACHA PCR LTDA
B55: =B54+1 -> 45 | C55: USIPRINT | D55: =SUMIFS(R:R,V:V,C55) -> 24103.86 | E55: =D55/SUM(D:D) -> 0.0050916284 | F55: =E55+F54 -> 0.60554242 | G55: C | H55: =SUMIFS(R:R,V:V,C55,U:U,$AO$18) -> 0 | I55: =SUMIFS(R:R,V:V,C55,U:U,$AO$17) -> 5271.93 | J55: =SUMIFS(R:R,V:V,C55,U:U,$AO$16) -> 15069.43 | K55: =SUMIFS(R:R,V:V,C55,U:U,$AO$15) -> 3762.5 | L55: =SUMIFS(R:R,V:V,C55,U:U,$AO$14) -> 0 | M55: =SUMIFS(R:R,V:V,C55,U:U,$AO$13) -> 0 | N55: =SUMIFS(R:R,V:V,C55,U:U,$AO$12) -> 0 | O55: =SUMIFS(R:R,V:V,C55,U:U,$AO$11) -> 0 | P55: =SUM(H55:K55) -> 24103.86 | R55: 924.08 | S55: 45885 | T55: -53 | U55: 3. Vencido: 30-60 | V55: FESTO | W55: Fornecedores Vencidos | X55: 45938 | Y55: Não | Z55: C | AG55: 45 | AH55: ASSOCIACAO BRASILEIRA DA IND D
B56: =B55+1 -> 46 | C56: BERLINERLUFT DO BRASIL LTDA | D56: =SUMIFS(R:R,V:V,C56) -> 24054 | E56: =D56/SUM(D:D) -> 0.0050810961 | F56: =E56+F55 -> 0.61062351 | G56: C | H56: =SUMIFS(R:R,V:V,C56,U:U,$AO$18) -> 0 | I56: =SUMIFS(R:R,V:V,C56,U:U,$AO$17) -> 24054 | J56: =SUMIFS(R:R,V:V,C56,U:U,$AO$16) -> 0 | K56: =SUMIFS(R:R,V:V,C56,U:U,$AO$15) -> 0 | L56: =SUMIFS(R:R,V:V,C56,U:U,$AO$14) -> 0 | M56: =SUMIFS(R:R,V:V,C56,U:U,$AO$13) -> 0 | N56: =SUMIFS(R:R,V:V,C56,U:U,$AO$12) -> 0 | O56: =SUMIFS(R:R,V:V,C56,U:U,$AO$11) -> 0 | P56: =SUM(H56:K56) -> 24054 | R56: 230.88 | S56: 45930 | T56: -8 | U56: 4. Vencido: 0-30 | V56: FESTO | W56: Fornecedores Vencidos | X56: 45938 | Y56: Não | Z56: C | AG56: 46 | AH56: ASSOCIACAO COMERCIAL DO PARANA
B57: =B56+1 -> 47 | C57: WFM SECURITIZADORA S.A. | D57: =SUMIFS(R:R,V:V,C57) -> 23497.13 | E57: =D57/SUM(D:D) -> 0.0049634645 | F57: =E57+F56 -> 0.61558698 | G57: C | H57: =SUMIFS(R:R,V:V,C57,U:U,$AO$18) -> 0 | I57: =SUMIFS(R:R,V:V,C57,U:U,$AO$17) -> 23497.13 | J57: =SUMIFS(R:R,V:V,C57,U:U,$AO$16) -> 0 | K57: =SUMIFS(R:R,V:V,C57,U:U,$AO$15) -> 0 | L57: =SUMIFS(R:R,V:V,C57,U:U,$AO$14) -> 0 | M57: =SUMIFS(R:R,V:V,C57,U:U,$AO$13) -> 0 | N57: =SUMIFS(R:R,V:V,C57,U:U,$AO$12) -> 0 | O57: =SUMIFS(R:R,V:V,C57,U:U,$AO$11) -> 0 | P57: =SUM(H57:K57) -> 23497.13 | R57: 3097.85 | S57: 45891 | T57: -47 | U57: 3. Vencido: 30-60 | V57: KRAUS NAIMER | W57: Fornecedores Vencidos | X57: 45938 | Y57: Não | Z57: C | AG57: 47 | AH57: ASSOCIACAO DAS EMPRESAS DA CID
B58: =B57+1 -> 48 | C58: AXIAL EQUIPAMENTOS INDUSTRIAIS | D58: =SUMIFS(R:R,V:V,C58) -> 21841.41 | E58: =D58/SUM(D:D) -> 0.0046137151 | F58: =E58+F57 -> 0.62020069 | G58: C | H58: =SUMIFS(R:R,V:V,C58,U:U,$AO$18) -> 0 | I58: =SUMIFS(R:R,V:V,C58,U:U,$AO$17) -> 11056.49 | J58: =SUMIFS(R:R,V:V,C58,U:U,$AO$16) -> 10784.92 | K58: =SUMIFS(R:R,V:V,C58,U:U,$AO$15) -> 0 | L58: =SUMIFS(R:R,V:V,C58,U:U,$AO$14) -> 0 | M58: =SUMIFS(R:R,V:V,C58,U:U,$AO$13) -> 0 | N58: =SUMIFS(R:R,V:V,C58,U:U,$AO$12) -> 0 | O58: =SUMIFS(R:R,V:V,C58,U:U,$AO$11) -> 0 | P58: =SUM(H58:K58) -> 21841.41 | R58: 724.9 | S58: 45894 | T58: -44 | U58: 3. Vencido: 30-60 | V58: PARINOX | W58: Fornecedores Vencidos | X58: 45938 | Y58: Não | Z58: C | AG58: 48 | AH58: ASTEN
B59: =B58+1 -> 49 | C59: RESTAURANTE E LANCHONETE BUHRE | D59: =SUMIFS(R:R,V:V,C59) -> 20190 | E59: =D59/SUM(D:D) -> 0.0042648761 | F59: =E59+F58 -> 0.62446557 | G59: C | H59: =SUMIFS(R:R,V:V,C59,U:U,$AO$18) -> 0 | I59: =SUMIFS(R:R,V:V,C59,U:U,$AO$17) -> 20190 | J59: =SUMIFS(R:R,V:V,C59,U:U,$AO$16) -> 0 | K59: =SUMIFS(R:R,V:V,C59,U:U,$AO$15) -> 0 | L59: =SUMIFS(R:R,V:V,C59,U:U,$AO$14) -> 0 | M59: =SUMIFS(R:R,V:V,C59,U:U,$AO$13) -> 0 | N59: =SUMIFS(R:R,V:V,C59,U:U,$AO$12) -> 0 | O59: =SUMIFS(R:R,V:V,C59,U:U,$AO$11) -> 0 | P59: =SUM(H59:K59) -> 20190 | R59: 2980 | S59: 45898 | T59: -40 | U59: 3. Vencido: 30-60 | V59: SAPIENS | W59: Fornecedores Vencidos | X59: 45938 | Y59: Não | Z59: C | AG59: 49 | AH59: ASTEN E CIA LTD
B60: =B59+1 -> 50 | C60: SANREI INSTALACOES DE EQUIPAME | D60: =SUMIFS(R:R,V:V,C60) -> 20000 | E60: =D60/SUM(D:D) -> 0.0042247411 | F60: =E60+F59 -> 0.62869031 | G60: C | H60: =SUMIFS(R:R,V:V,C60,U:U,$AO$18) -> 0 | I60: =SUMIFS(R:R,V:V,C60,U:U,$AO$17) -> 20000 | J60: =SUMIFS(R:R,V:V,C60,U:U,$AO$16) -> 0 | K60: =SUMIFS(R:R,V:V,C60,U:U,$AO$15) -> 0 | L60: =SUMIFS(R:R,V:V,C60,U:U,$AO$14) -> 0 | M60: =SUMIFS(R:R,V:V,C60,U:U,$AO$13) -> 0 | N60: =SUMIFS(R:R,V:V,C60,U:U,$AO$12) -> 0 | O60: =SUMIFS(R:R,V:V,C60,U:U,$AO$11) -> 0 | P60: =SUM(H60:K60) -> 20000 | R60: 2980 | S60: 45912 | T60: -26 | U60: 4. Vencido: 0-30 | V60: SAPIENS | W60: Fornecedores Vencidos | X60: 45938 | Y60: Não | Z60: C | AG60: 50 | AH60: ATI BRASIL
B61: =B60+1 -> 51 | C61: GUNTER METALL LTDA | D61: =SUMIFS(R:R,V:V,C61) -> 19519.53 | E61: =D61/SUM(D:D) -> 0.004123248 | F61: =E61+F60 -> 0.63281356 | G61: C | H61: =SUMIFS(R:R,V:V,C61,U:U,$AO$18) -> 0 | I61: =SUMIFS(R:R,V:V,C61,U:U,$AO$17) -> 19519.53 | J61: =SUMIFS(R:R,V:V,C61,U:U,$AO$16) -> 0 | K61: =SUMIFS(R:R,V:V,C61,U:U,$AO$15) -> 0 | L61: =SUMIFS(R:R,V:V,C61,U:U,$AO$14) -> 0 | M61: =SUMIFS(R:R,V:V,C61,U:U,$AO$13) -> 0 | N61: =SUMIFS(R:R,V:V,C61,U:U,$AO$12) -> 0 | O61: =SUMIFS(R:R,V:V,C61,U:U,$AO$11) -> 0 | P61: =SUM(H61:K61) -> 19519.53 | R61: 1961.75 | S61: 45898 | T61: -40 | U61: 3. Vencido: 30-60 | V61: STEELALLOY | W61: Fornecedores Vencidos | X61: 45938 | Y61: Não | Z61: C | AG61: 51 | AH61: AUGE BRASIL
B62: =B61+1 -> 52 | C62: OURO PRETO | D62: =SUMIFS(R:R,V:V,C62) -> 19212.32 | E62: =D62/SUM(D:D) -> 0.0040583539 | F62: =E62+F61 -> 0.63687191 | G62: C | H62: =SUMIFS(R:R,V:V,C62,U:U,$AO$18) -> 0 | I62: =SUMIFS(R:R,V:V,C62,U:U,$AO$17) -> 0 | J62: =SUMIFS(R:R,V:V,C62,U:U,$AO$16) -> 19212.32 | K62: =SUMIFS(R:R,V:V,C62,U:U,$AO$15) -> 0 | L62: =SUMIFS(R:R,V:V,C62,U:U,$AO$14) -> 0 | M62: =SUMIFS(R:R,V:V,C62,U:U,$AO$13) -> 0 | N62: =SUMIFS(R:R,V:V,C62,U:U,$AO$12) -> 0 | O62: =SUMIFS(R:R,V:V,C62,U:U,$AO$11) -> 0 | P62: =SUM(H62:K62) -> 19212.32 | R62: 413 | S62: 45898 | T62: -40 | U62: 3. Vencido: 30-60 | V62: STEELALLOY | W62: Fornecedores Vencidos | X62: 45938 | Y62: Não | Z62: C | AG62: 52 | AH62: AUGE DO BRASIL LTDA
... B408: =B407+1 -> 398 | C408: KS VARIEDADES | D408: =SUMIFS(R:R,V:V,C408) -> 66.89 | E408: =D408/SUM(D:D) -> 1.4129647e-05 | F408: =E408+F407 -> 0.98060316 | G408: C | H408: =SUMIFS(R:R,V:V,C408,U:U,$AO$18) -> 0 | I408: =SUMIFS(R:R,V:V,C408,U:U,$AO$17) -> 0 | J408: =SUMIFS(R:R,V:V,C408,U:U,$AO$16) -> 0 | K408: =SUMIFS(R:R,V:V,C408,U:U,$AO$15) -> 66.89 | L408: =SUMIFS(R:R,V:V,C408,U:U,$AO$14) -> 0 | M408: =SUMIFS(R:R,V:V,C408,U:U,$AO$13) -> 0 | N408: =SUMIFS(R:R,V:V,C408,U:U,$AO$12) -> 0 | O408: =SUMIFS(R:R,V:V,C408,U:U,$AO$11) -> 0 | P408: =SUM(H408:K408) -> 66.89 | R408: 2420.62 | S408: 45894 | T408: -44 | U408: 3. Vencido: 30-60 | V408: NOVA ERA - CUNHA | W408: Fornecedores Vencidos | X408: 45938 | Y408: Não | Z408: C | AG408: 398 | AH408: YAPAY PAGAMENTOS ONLINE LTDA
R409: 2012.14 | S409: 45896 | T409: -42 | U409: 3. Vencido: 30-60 | V409: NOVA ERA - CUNHA | W409: Fornecedores Vencidos | X409: 45938 | Y409: Não | Z409: C | AH409: HPE - Itália
R410: 232.5 | S410: 45889 | T410: -49 | U410: 3. Vencido: 30-60 | V410: RBS TOOLS | W410: Fornecedores Vencidos | X410: 45938 | Y410: Não | Z410: C | AH410: AWF
R411: 680 | S411: 45892 | T411: -46 | U411: 3. Vencido: 30-60 | V411: RBS TOOLS | W411: Fornecedores Vencidos | X411: 45938 | Y411: Não | Z411: C | AH411: VD SRL
R412: 3762.5 | S412: 45889 | T412: -49 | U412: 3. Vencido: 30-60 | V412: USIPRINT | W412: Fornecedores Vencidos | X412: 45938 | Y412: Não | Z412: C | AH412: Teknomotor
R413: 3762.5 | S413: 45903 | T413: -35 | U413: 3. Vencido: 30-60 | V413: USIPRINT | W413: Fornecedores Vencidos | X413: 45938 | Y413: Não | Z413: C | AH413: Win Win
R414: 3762.5 | S414: 45917 | T414: -21 | U414: 4. Vencido: 0-30 | V414: USIPRINT | W414: Fornecedores Vencidos | X414: 45938 | Y414: Não | Z414: C | AH414: Motovario
R415: 1308.75 | S415: 45911 | T415: -27 | U415: 4. Vencido: 0-30 | V415: ARCELORMITTAL - PR | W415: Fornecedores Vencidos | X415: 45938 | Y415: Não | Z415: C | AH415: Costa Levigatrici
R416: 1308.75 | S416: 45941 | T416: 3 | U416: 5. A vencer: 0-30 | V416: ARCELORMITTAL - PR | W416: Fornecedores a Vencer | X416: 45941 | Y416: Não | Z416: C | AH416: Fiama
R417: 1309.14 | S417: 45972 | T417: 34 | U417: 6. A vencer: 30-60 | V417: ARCELORMITTAL - PR | W417: Fornecedores a Vencer | X417: 45972 | Y417: Não | Z417: C | AH417: Elco
R418: 5413.33 | S418: 45889 | T418: -49 | U418: 3. Vencido: 30-60 | V418: FLEXOPOL POLIURETANO | W418: Fornecedores Vencidos | X418: 45938 | Y418: Não | Z418: C | AH418: Wuxi Wanda
R419: 5413.33 | S419: 45904 | T419: -34 | U419: 3. Vencido: 30-60 | V419: FLEXOPOL POLIURETANO | W419: Fornecedores Vencidos | X419: 45938 | Y419: Não | Z419: C | AH419: Fir Fulda
R420: 5413.34 | S420: 45919 | T420: -19 | U420: 4. Vencido: 0-30 | V420: FLEXOPOL POLIURETANO | W420: Fornecedores Vencidos | X420: 45938 | Y420: Não | Z420: C | AH420: RIVA RENZO
... R422: 2651.74 | S422: 45887 | T422: -51 | U422: 3. Vencido: 30-60 | V422: BC INDUSTRIAL | W422: Fornecedores Vencidos | X422: 45938 | Y422: Não | Z422: A | AH422: Grand Total
R423: 130.24 | S423: 45887 | T423: -51 | U423: 3. Vencido: 30-60 | V423: BC INDUSTRIAL | W423: Fornecedores Vencidos | X423: 45938 | Y423: Não | Z423: A
R424: 2670.71 | S424: 45888 | T424: -50 | U424: 3. Vencido: 30-60 | V424: BC INDUSTRIAL | W424: Fornecedores Vencidos | X424: 45938 | Y424: Não | Z424: A
R425: 4416.76 | S425: 45888 | T425: -50 | U425: 3. Vencido: 30-60 | V425: BC INDUSTRIAL | W425: Fornecedores Vencidos | X425: 45938 | Y425: Não | Z425: A
R426: 2026.66 | S426: 45888 | T426: -50 | U426: 3. Vencido: 30-60 | V426: BC INDUSTRIAL | W426: Fornecedores Vencidos | X426: 45938 | Y426: Não | Z426: A
R427: 2025.32 | S427: 45888 | T427: -50 | U427: 3. Vencido: 30-60 | V427: BC INDUSTRIAL | W427: Fornecedores Vencidos | X427: 45938 | Y427: Não | Z427: A
R428: 24.8 | S428: 45888 | T428: -50 | U428: 3. Vencido: 30-60 | V428: BC INDUSTRIAL | W428: Fornecedores Vencidos | X428: 45938 | Y428: Não | Z428: A
R429: 240.28 | S429: 45888 | T429: -50 | U429: 3. Vencido: 30-60 | V429: BC INDUSTRIAL | W429: Fornecedores Vencidos | X429: 45938 | Y429: Não | Z429: A
R430: 34.14 | S430: 45888 | T430: -50 | U430: 3. Vencido: 30-60 | V430: BC INDUSTRIAL | W430: Fornecedores Vencidos | X430: 45938 | Y430: Não | Z430: A
R431: 3308.04 | S431: 45889 | T431: -49 | U431: 3. Vencido: 30-60 | V431: BC INDUSTRIAL | W431: Fornecedores Vencidos | X431: 45938 | Y431: Não | Z431: A
R432: 3757.04 | S432: 45889 | T432: -49 | U432: 3. Vencido: 30-60 | V432: BC INDUSTRIAL | W432: Fornecedores Vencidos | X432: 45938 | Y432: Não | Z432: A
R433: 1954.86 | S433: 45889 | T433: -49 | U433: 3. Vencido: 30-60 | V433: BC INDUSTRIAL | W433: Fornecedores Vencidos | X433: 45938 | Y433: Não | Z433: A
R434: 4082.35 | S434: 45889 | T434: -49 | U434: 3. Vencido: 30-60 | V434: BC INDUSTRIAL | W434: Fornecedores Vencidos | X434: 45938 | Y434: Não | Z434: A
... R908: 1923.74 | S908: 45829 | T908: -109 | U908: 2. Vencido: 60-180 | V908: TESE ELECTRIC BRASIL LTDA | W908: Fornecedores Vencidos | X908: 45938 | Y908: Não | Z908: C
R909: 2156.49 | S909: A vista | T909: 7. N informado | U909: 7. N informado | V909: PARANA METALIZACOES LTDA | W909: Fornecedores a Vencer | X909: 45938 | Y909: Não | Z909: C
R910: 2937.22 | S910: 45828 | T910: -110 | U910: 2. Vencido: 60-180 | V910: COFACO FABRICADORA DE CORREIAS | W910: Fornecedores Vencidos | X910: 45938 | Y910: Não | Z910: A
R911: 4204.47 | S911: 45831 | T911: -107 | U911: 2. Vencido: 60-180 | V911: EIKON ENERGIA LTDA | W911: Fornecedores Vencidos | X911: 45938 | Y911: Não | Z911: C
R912: 1552 | S912: 45832 | T912: -106 | U912: 2. Vencido: 60-180 | V912: SENSORVILLE | W912: Fornecedores Vencidos | X912: 45938 | Y912: Não | Z912: C
R913: 2282.39 | S913: 45832 | T913: -106 | U913: 2. Vencido: 60-180 | V913: EPLAN BRASIL LTDA | W913: Fornecedores Vencidos | X913: 45938 | Y913: Não | Z913: C
R914: 2317.74 | S914: 45832 | T914: -106 | U914: 2. Vencido: 60-180 | V914: EIKON ENERGIA LTDA | W914: Fornecedores Vencidos | X914: 45938 | Y914: Não | Z914: C
R915: 7530.75 | S915: 45832 | T915: -106 | U915: 2. Vencido: 60-180 | V915: COFACO FABRICADORA DE CORREIAS | W915: Fornecedores Vencidos | X915: 45938 | Y915: Não | Z915: A
R916: 6855.88 | S916: 45832 | T916: -106 | U916: 2. Vencido: 60-180 | V916: SCHNEIDER ELECTRIC | W916: Fornecedores Vencidos | X916: 45938 | Y916: Protestado | Z916: A
R917: 3066.31 | S917: 45833 | T917: -105 | U917: 2. Vencido: 60-180 | V917: IVEMA | W917: Fornecedores Vencidos | X917: 45938 | Y917: Não | Z917: C
R918: 4119.07 | S918: 45833 | T918: -105 | U918: 2. Vencido: 60-180 | V918: SCHNEIDER ELECTRIC | W918: Fornecedores Vencidos | X918: 45938 | Y918: Protestado | Z918: A
R919: 8115.89 | S919: 45833 | T919: -105 | U919: 2. Vencido: 60-180 | V919: SCHNEIDER ELECTRIC | W919: Fornecedores Vencidos | X919: 45938 | Y919: Protestado | Z919: A
R920: 13213.11 | S920: 45833 | T920: -105 | U920: 2. Vencido: 60-180 | V920: PHOENIX CONTACT IND COM LTDA | W920: Fornecedores Vencidos | X920: 45938 | Y920: Não | Z920: B
R921: 4501.37 | S921: 45834 | T921: -104 | U921: 2. Vencido: 60-180 | V921: WEG EQUIPAMENTOS ELETRICOS SA | W921: Fornecedores Vencidos | X921: 45938 | Y921: Protestado | Z921: B
... R1660: 10161.586 | S1660: 45838 | T1660: -100 | U1660: 2. Vencido: 60-180 | V1660: VD SRL | W1660: Fornecedores Vencidos | X1660: 45938 | Y1660: Não | Z1660: C

Sheet Análise_Rescisões_Estrutura
A1: Data de atualização: | C1: 45944
A2: Ref. Documento: | C2: Quadro de Pessoal com Encargos para analise estrutura_Lucas
G4: =SUMIF(G6:G85,G16,$I$6:$I$84) -> 458211.92 | H4: =SUMIF(H6:H85,H16,$I$6:$I$84) -> 301399.04 | K4: =SUM(K6:K84) -> 3647052.2 | L4: =SUM(L6:L84) -> 1095132.8 | M4: =SUM(M6:M84) -> 1733585.8
A5: Tipo | B5: Profissional | C5: Cargo | D5: Tipo | E5: Setor | F5: Valor Base | G5: Corte Maq + Peças | H5: Corte Peças | I5: Total Mensal | J5: Total Anual | K5: Valor Rescisão | L5: Soma Rescisão | M5: Soma Rescisão | O5: Comentários
A6: CLT | B6: ANA PAULA DE OLIVEIRA MARCELINO | C6: RH | D6: Administracao | E6: ADM | F6: 4200 | G6: TRUE | H6: TRUE | I6: 6543.3214 | J6: 78519.857 | K6: 14266 | L6: 0 | M6: 0
A7: CLT | B7: ANGELO PIPITONE | C7: Diretor Geral | D7: Administracao | E7: ADM | F7: 42219.8 | G7: TRUE | H7: TRUE | I7: 50663.76 | J7: 607965.12 | K7: 0 | L7: 0 | M7: 0
A8: CLT | B8: CINTIA BARBARA DA CUNHA GRESCZYSZIN | C8: RH | D8: Administracao | E8: ADM | F8: 11220.1 | G8: FALSE | H8: FALSE | I8: 17480.172 | J8: 209762.06 | K8: 61673.15 | L8: 0 | M8: 0
A9: CLT | B9: MAGDA LUCIA GIACOMELLI | C9: Sup(a)Financeiro(a) | D9: Administracao | E9: ADM | F9: 9895.68 | G9: FALSE | H9: FALSE | I9: 15416.813 | J9: 185001.76 | K9: 128610.85 | L9: 0 | M9: 0
A10: CLT | B10: MARIA EDUARDA DRUZYK | C10: Auxiliar Contabil | D10: Administracao | E10: ADM | F10: 2700 | G10: TRUE | H10: TRUE | I10: 4206.4209 | J10: 50477.051 | K10: 9441 | L10: 0 | M10: 0 | O10: Pediu demissão mas estava no MVO
A11: CLT | B11: NILTON CESAR DE ARAUJO | C11: Contador | D11: Administracao | E11: ADM | F11: 13616.99 | G11: TRUE | H11: TRUE | I11: 21214.367 | J11: 254572.41 | K11: 131439.4 | L11: 131439.4 | M11: 131439.4 | O11: Não está mais na empresa
A12: CLT | B12: PATRICIA CRISTINA ZORZI | C12: Analis. Comercial Sr | D12: Administracao | E12: ADM | F12: 8500 | G12: TRUE | H12: TRUE | I12: 13242.436 | J12: 158909.23 | K12: 28871.667 | L12: 28871.667 | M12: 28871.667
A13: CLT | B13: RICARDO DE OLIVEIRA FERNANDES | C13: Vendedor comercial | D13: Administracao | E13: ADM | F13: 8234.54 | G13: TRUE | H13: TRUE | I13: 12828.867 | J13: 153946.41 | K13: 136665.92 | L13: 136665.92 | M13: 136665.92
A14: PJ | B14: FLAVIO AZANHA | C14: Diretor Geral | D14: Administracao | E14: ADM | F14: 38036 | G14: TRUE | H14: TRUE | I14: 38036 | J14: 456432 | K14: 0 | L14: 0 | M14: 0
A15: PJ | B15: SANITO MORETTI | C15: Diretor Comercial | D15: Administracao | E15: ADM | F15: 30253.75 | G15: FALSE | H15: FALSE | I15: 30253.75 | J15: 363045 | K15: 0 | L15: 0 | M15: 0
A16: PJ | B16: LUCAS LICHTBLAU | C16: Diretor Industrial | D16: Administracao | E16: ADM | F16: 30680 | G16: FALSE | H16: FALSE | I16: 30680 | J16: 368160 | K16: 0 | L16: 0 | M16: 0
A17: PJ | B17: KLEBER | C17: Supervisor TI | D17: Administracao | E17: ADM | F17: 14894 | G17: TRUE | H17: TRUE | I17: 14894 | J17: 178728 | K17: 0 | L17: 0 | M17: 0
A18: CLT | B18: EDSON DE OLIVEIRA BRASIL | C18: Supervisor | D18: MOI | E18: ADM Produção | F18: 11482.9 | G18: TRUE | H18: TRUE | I18: 17889.597 | J18: 214675.16 | K18: 64826.38 | L18: 64826.38 | M18: 64826.38
A19: CLT | B19: LUIZ FERNANDO MACHADO | C19: Gerente de Logistica | D19: MOI | E19: ADM Produção | F19: 18034.11 | G19: TRUE | H19: TRUE | I19: 28095.947 | J19: 337151.37 | K19: 229490.76 | L19: 0 | M19: 229490.76
A20: CLT | B20: SUEMAR JOSE DA COSTA | C20: Supervisor | D20: MOI | E20: ADM Produção | F20: 10000 | G20: FALSE | H20: FALSE | I20: 15579.337 | J20: 186952.04 | K20: 33966.667 | L20: 0 | M20: 0
A21: PJ | B21: JOSÉ MELO - ZEZINHO | C21: Supervisor | D21: MOI | E21: ADM Produção | F21: 20583 | G21: TRUE | H21: TRUE | I21: 20583 | J21: 246996 | K21: 0 | L21: 0 | M21: 0
A22: PJ | B22: JONAS KAHL | C22: Gerente Industrial | D22: MOI | E22: ADM Produção | F22: 20610.53 | G22: FALSE | H22: FALSE | I22: 20610.53 | J22: 247326.36 | K22: 0 | L22: 0 | M22: 0
A23: CLT | B23: ANA BEATRIZ NASCIMENTO BORGES | C23: Menor aprendiz | D23: MOI | E23: Almoxarifado | F23: 1545.84 | G23: TRUE | H23: TRUE | I23: 2408.3162 | J23: 28899.794 | K23: 5250.7032 | L23: 0 | M23: 0
A24: CLT | B24: CLEITON PEREIRA DE FREITAS | C24: Almoxarife | D24: MOI | E24: Almoxarifado | F24: 3201 | G24: TRUE | H24: TRUE | I24: 4986.9457 | J24: 59843.348 | K24: 10872.73 | L24: 0 | M24: 0 | O24: Pediu demissão mas estava no MVO
A25: CLT | B25: JORGE LUIS DOS SANTOS | C25: Almoxarife | D25: MOI | E25: Almoxarifado | F25: 3247.2 | G25: TRUE | H25: TRUE | I25: 5058.9222 | J25: 60707.066 | K25: 11029.656 | L25: 0 | M25: 11029.656 | O25: Pediu demissão
A26: CLT | B26: VITOR HUGO AZEVEDO BRUNETTI | C26: Almoxarife | D26: MOI | E26: Almoxarifado | F26: 3247.2 | G26: TRUE | H26: TRUE | I26: 5058.9222 | J26: 60707.066 | K26: 11029.656 | L26: 11029.656 | M26: 11029.656 | O26: Pediu demissão
A27: CLT | B27: WALDEMIR BUZARELO FARIAS | C27: Almoxarife | D27: MOI | E27: Almoxarifado | F27: 3388 | G27: FALSE | H27: FALSE | I27: 5278.2793 | J27: 63339.351 | K27: 13540.707 | L27: 0 | M27: 0 | O27: Pediu demissão mas estava no MVO
A28: CLT | B28: ANDERSON JUNIO DA SILVA | C28: Tecnico externo | D28: Assistencia Tecnica | E28: Assist.Tecnica | F28: 9317 | G28: TRUE | H28: TRUE | I28: 14515.268 | J28: 174183.22 | K28: 93138.943 | L28: 0 | M28: 0
A29: CLT | B29: EDSON DOMINGOS DE MORAES | C29: Tecnico externo | D29: Assistencia Tecnica | E29: Assist.Tecnica | F29: 9317 | G29: TRUE | H29: TRUE | I29: 14515.268 | J29: 174183.22 | K29: 102455.94 | L29: 102455.94 | M29: 102455.94
A30: CLT | B30: FABIO ALEXANDRE DA SILVA OLIVEIRA | C30: Tecnico externo | D30: Assistencia Tecnica | E30: Assist.Tecnica | F30: 9317 | G30: FALSE | H30: TRUE | I30: 14515.268 | J30: 174183.22 | K30: 97797.443 | L30: 0 | M30: 0
A31: CLT | B31: FRANCISCO QUEIROZ VIEIRA | C31: Tecnico interno | D31: Assistencia Tecnica | E31: Assist.Tecnica | F31: 6725.4 | G31: TRUE | H31: TRUE | I31: 10477.727 | J31: 125732.72 | K31: 23516.482 | L31: 0 | M31: 23516.482
A32: CLT | B32: JOSE ALEXANDRE COELHO | C32: Vendedor Assistência | D32: Assistencia Tecnica | E32: Assist.Tecnica | F32: 8000 | G32: TRUE | H32: TRUE | I32: 12463.469 | J32: 149561.63 | K32: 43973.333 | L32: 0 | M32: 0
A33: CLT | B33: JOSOEL DE CAMARGO SILVA | C33: Vendedor Assistência | D33: Assistencia Tecnica | E33: Assist.Tecnica | F33: 5000 | G33: TRUE | H33: TRUE | I33: 7789.6683 | J33: 93476.02 | K33: 16983.333 | L33: 16983.333 | M33: 16983.333
A34: CLT | B34: GERSON ANTONIO LABRES | C34: Tecnico interno | D34: Assistencia Tecnica | E34: Assist.Tecnica | F34: 16185.4 | G34: FALSE | H34: FALSE | I34: 25215.78 | J34: 302589.36 | K34: 236252.89 | L34: 0 | M34: 236252.89
A35: CLT | B35: LUCIANO DE CAMPOS SILVA | C35: Tecnico externo | D35: Assistencia Tecnica | E35: Assist.Tecnica | F35: 13448.6 | G35: FALSE | H35: FALSE | I35: 20952.027 | J35: 251424.32 | K35: 180166.41 | L35: 0 | M35: 0
A36: CLT | B36: TATIANE APARECIDA FARIAS | C36: Analista Assistência | D36: Assistencia Tecnica | E36: Assist.Tecnica | F36: 4822.74 | G36: TRUE | H36: TRUE | I36: 7513.509 | J36: 90162.108 | K36: 66537.736 | L36: 0 | M36: 0
A37: CLT | B37: TIAGO FIOREZE | C37: Tecnico externo | D37: Assistencia Tecnica | E37: Assist.Tecnica | F37: 9317 | G37: FALSE | H37: TRUE | I37: 14515.268 | J37: 174183.22 | K37: 93138.943 | L37: 0 | M37: 0
A38: PJ | B38: JOÃO GINO | C38: Gerente Assistência técnica | D38: Assistencia Tecnica | E38: Assist.Tecnica | F38: 23332 | G38: FALSE | H38: FALSE | I38: 23332 | J38: 279984 | K38: 0 | L38: 0 | M38: 0
A39: PJ | B39: ZENIR FIOREZI | C39: Tecnico externo | D39: Assistencia Tecnica | E39: Assist.Tecnica | F39: 13195.64 | G39: TRUE | H39: TRUE | I39: 13195.64 | J39: 158347.68 | K39: 0 | L39: 0 | M39: 0
... A44: CLT | B44: FELIPE DE LIMA PINTO | C44: Projetista Elétrico | D44: P&D | E44: Engenharia | F44: 8001.4 | G44: FALSE | H44: TRUE | I44: 12465.65 | J44: 149587.81 | K44: 79987.329 | L44: 0 | M44: 0
A45: CLT | B45: HENRIQUE GRYBOSI NETO | C45: Projetista Software | D45: P&D | E45: Engenharia | F45: 11323.4 | G45: TRUE | H45: TRUE | I45: 17641.106 | J45: 211693.27 | K45: 39594.155 | L45: 0 | M45: 0 | O45: Pediu demissão
A46: CLT | B46: JOAO OCTAVIO DE LIMA | C46: Gerente Engenharia | D46: P&D | E46: Engenharia | F46: 15292.5 | G46: FALSE | H46: FALSE | I46: 23824.701 | J46: 285896.41 | K46: 53472.775 | L46: 53472.775 | M46: 53472.775
A47: CLT | B47: LUIS PAULO DE OLIVEIRA VELASQUEZ | C47: Projetista Mecânico | D47: P&D | E47: Engenharia | F47: 9000.2 | G47: FALSE | H47: TRUE | I47: 14021.715 | J47: 168260.58 | K47: 30570.679 | L47: 30570.679 | M47: 30570.679
A48: CLT | B48: ROBERTSON DO NASCIMENTO | C48: Projetista Mecânico | D48: P&D | E48: Engenharia | F48: 8268.27 | G48: TRUE | H48: TRUE | I48: 12881.416 | J48: 154576.99 | K48: 120689.18 | L48: 0 | M48: 0
A49: CLT | B49: THIAGO JOSE PIANOWSKI | C49: Projetista Mecânico | D49: P&D | E49: Engenharia | F49: 10146.4 | G49: TRUE | H49: TRUE | I49: 15807.418 | J49: 189689.02 | K49: 34463.939 | L49: 0 | M49: 0
A50: CLT | B50: VINICIUS DE LARA BELEM | C50: Projetista Mecânico | D50: P&D | E50: Engenharia | F50: 9044.2 | G50: TRUE | H50: TRUE | I50: 14090.264 | J50: 169083.16 | K50: 30720.133 | L50: 30720.133 | M50: 30720.133
A51: PJ | B51: EDELCIO JOSÉ DA SILVA | C51: Projetista Mecânico | D51: P&D | E51: Engenharia | F51: 15783 | G51: TRUE | H51: TRUE | I51: 15783 | J51: 189396 | K51: 0 | L51: 0 | M51: 0
A52: CLT | B52: ADRIANO APARECIDO LOPES | C52: Montador | D52: MOD | E52: Montagem | F52: 5293.2 | G52: FALSE | H52: TRUE | I52: 8246.4545 | J52: 98957.454 | K52: 60854.156 | L52: 0 | M52: 0
A53: CLT | B53: ANTONIO CARLOS DE SOUZA | C53: Montador | D53: MOD | E53: Montagem | F53: 6754 | G53: FALSE | H53: FALSE | I53: 10522.284 | J53: 126267.41 | K53: 101287.49 | L53: 0 | M53: 0
A54: CLT | B54: EDSON VALERIO NASILOWSKI | C54: Montador | D54: MOD | E54: Montagem | F54: 4749.8 | G54: FALSE | H54: FALSE | I54: 7399.8733 | J54: 88798.48 | K54: 26108.067 | L54: 0 | M54: 0
A55: CLT | B55: JOAO ALEXANDRE MANOSSO | C55: Montador | D55: MOD | E55: Montagem | F55: 4232.8 | G55: TRUE | H55: TRUE | I55: 6594.4216 | J55: 79133.059 | K55: 14800.691 | L55: 14800.691 | M55: 14800.691
A56: CLT | B56: JORGE ANTONIO SIQUEIRA | C56: Montador | D56: MOD | E56: Montagem | F56: 6542.8 | G56: FALSE | H56: TRUE | I56: 10193.248 | J56: 122318.98 | K56: 98120.191 | L56: 0 | M56: 0
A57: CLT | B57: MAURICIO MASSARIN | C57: Montador | D57: MOD | E57: Montagem | F57: 6754 | G57: FALSE | H57: TRUE | I57: 10522.284 | J57: 126267.41 | K57: 87779.487 | L57: 0 | M57: 0
... A77: CLT | B77: MARCOS ROBERTO MELO DO COUTO | C77: Retifica plana / Fresa convencional | D77: MOD | E77: Usinagem | F77: 4763 | G77: TRUE | H77: TRUE | I77: 7420.4381 | J77: 89045.257 | K77: 59521.623 | L77: 0 | M77: 0
A78: CLT | B78: PAULO SERGIO DA SILVA SANTOS | C78: Centro de Usinagem CNC | D78: MOD | E78: Usinagem | F78: 6201.8 | G78: FALSE | H78: FALSE | I78: 9661.993 | J78: 115943.92 | K78: 21065.447 | L78: 0 | M78: 0 | O78: Pediu demissão
A79: CLT | B79: RODRIGO DE CARVALHO JONAS | C79: Plaina grande | D79: MOD | E79: Usinagem | F79: 6875 | G79: FALSE | H79: TRUE | I79: 10710.794 | J79: 128529.53 | K79: 58414.583 | L79: 0 | M79: 58414.583
A80: CLT | B80: SERGIO DE OLIVEIRA SANTOS | C80: Soldador | D80: MOD | E80: Usinagem | F80: 4897.2 | G80: TRUE | H80: TRUE | I80: 7629.5128 | J80: 91554.153 | K80: 53852.876 | L80: 53852.876 | M80: 53852.876
A81: CLT | B81: VALTONIR DA COSTA | C81: Mandriladora CNC / Furadeira CNC | D81: MOD | E81: Usinagem | F81: 7491 | G81: TRUE | H81: TRUE | I81: 11670.481 | J81: 140045.77 | K81: 37430.03 | L81: 0 | M81: 37430.03
A82: CLT | B82: VANDERLEY JONAS | C82: Serra / Furação | D82: MOD | E82: Usinagem | F82: 3280.2 | G82: FALSE | H82: TRUE | I82: 5110.334 | J82: 61324.008 | K82: 18030.166 | L82: 0 | M82: 0
A83: PJ | B83: MARCO ANTONIO ROCHA | C83: Mandrilador CNC | D83: MOD | E83: Usinagem | F83: 16782.45 | G83: TRUE | H83: TRUE | I83: 16782.45 | J83: 201389.4 | K83: 0 | L83: 0 | M83: 0 | O83: Pediu demissão
A84: PJ | B84: LUCIANO KAHL | C84: Manutenção | D84: MOI | E84: Usinagem | F84: 11081.18 | G84: FALSE | H84: FALSE | I84: 11081.18 | J84: 132974.16 | K84: 0 | L84: 0 | M84: 0
B85: 79 | I85: =SUM(I6:I84) -> 1022332.3 | J85: =SUM(J6:J84) -> 12267988 | L85: 1095132.8 | M85: 1733585.8
F87: Redução | G87: =COUNTIFS(G6:G84,TRUE) -> 45 | H87: =COUNTIFS(H6:H84,TRUE) -> 60 | K87: Redução | L87: 313740.48 | M87: 434374.2
F88: New | G88: =$B$85-G87 -> 34 | H88: =$B$85-H87 -> 19 | K88: New | L88: 708591.87 | M88: 587958.14
K90: * Os valores da rescisão já compreendem a multa de 40% FGTS
